Workbook

Sheet Set25
A1: PERÍODO 05 á 14/SET/25 | C1: =D2+E2+F2+G2+H2+I2+J2+M2+P2 -> -3986.46 | D1: SPOT | E1: ITAU | F1: LUCILA | G1: LUCILA2 | H1: CAIXA | I1: CARTAO | J1: VENDAS | K1: GASOLINA | N1: ETANOL | Q1: ERALDO | R1: LUIZ F. | S1: LUCILA | T1: DIVIDA | U1: WL | V1: WL | AO1: Total | AP1: Saldo Total | AQ1: Saldo Edson | AR1: Saldo Master
B2: Saldo Inicial do dia | C2: =D2+E2+F2+G2+H2+I2+J2+M2+P2+SUM(Q2:AN2) -> -296310.2 | D2: 94.13 | E2: -37907.13 | F2: 6.19 | I2: 8907.15 | J2: 0 | K2: 2164 | L2: 5.2 | M2: =K2*L2 -> 11252.8 | N2: 3848 | O2: 3.55 | P2: =N2*O2 -> 13660.4 | Q2: 0 | S2: 0 | T2: -19288.14 | U2: =-11335.6-11265.54-11265.54-11268.92-12900-12900-12900-12900-11669-11665.5-11665.5-11665.5-11665.5-11669-8825-8825-11798.82-11798.82-11802.36-17750-17750-17750 -> -273035.6 | V2: 0 | W2: 0 | X2: 0 | Y2: 0 | AM2: 0 | AO2: =D2+E2+F2+G2+H2+I2+J2+M2+P2+SUM(Q2:AN2) -> -296310.2 | AP2: =#REF! -> #REF! | AQ2: =#REF! -> #REF! | AR2: =AP2-AQ2 -> #REF!
A3: 45905 | B3: Credito Vendas Cartão | D3: 8678.72 | I3: =-D3 -> -8678.72 | AQ3: Saidas | AR3: #REF!
B4: Desconto taxas Cartão | I4: =-I2-I3 -> -228.43 | AQ4: Saidas | AR4: #REF!
B5: Pix e depósitos Banco Itaú | E5: =50+20+10+320+395+1000+2000+10+100+5+50+700+20.7+20+20+50+100+170+30+50+50+25+50+70+20 -> 5335.7 | H5: =-E5 -> -5335.7 | M5: =K5*L5 -> 0 | P5: =N5*O5 -> 0 | AQ5: Saidas | AR5: #REF!
B6: Pix e depósitos Banco Itaú - Lucila | E6: =7700+1000 -> 8700 | G6: =-E6 -> -8700 | M6: =K6*L6 -> 0 | P6: =N6*O6 -> 0
B7: Pag boleto WL NF 73289 3/3 VENC 01/08 | E7: -11335.6 | M7: =K7*L7 -> 0 | P7: =N7*O7 -> 0 | U7: =-E7 -> 11335.6 | AQ7: Saidas | AR7: #REF!
B8: Crediario Emprestimo 1/6 parcelas 3.214,69 | E8: =-1141.12-5-50-700-20.7-20-20-50-100-170-30-50-50-25-50-732.87 -> -3214.69 | M8: =K8*L8 -> 0 | P8: =N8*O8 -> 0 | T8: =-E8 -> 3214.69 | AQ8: Saidas | AR8: #REF!
B9: Pag Pantoja & Co (mercado) | E9: -52.26 | P9: =N9*O9 -> 0 | AQ9: Saidas | AR9: #REF!
B10: Pix Lucila | D10: -300 | G10: =-D10 -> 300 | P10: =N10*O10 -> 0
B11: Tarifa pix | D11: -4.9 | P11: =N11*O11 -> 0
B12: Pix Eraldo Macedo | D12: 48200 | P12: =N12*O12 -> 0 | Q12: =-D12 -> -48200
B13: Tarifa pix recebido 0,8% | D13: -385.6 | P13: =N13*O13 -> 0
B14: Pag. NF 81861 Petroriente 10x4,82 GC (Eraldo) | D14: -48200 | K14: 10000 | L14: 4.82 | M14: =K14*L14 -> 48200 | P14: =N14*O14 -> 0
B15: Tarifa pix enviado Petroriente | D15: -4.9 | P15: =N15*O15 -> 0
B16: Pix Lucila (NUBANK) | D16: -8000 | G16: =-D16 -> 8000 | P16: =N16*O16 -> 0
B17: Tarifa pix enviado Petroriente | D17: -4.9
B18: Compra WL 20x3,67 EH 6x12.233,33 NF 81639 | N18: 20000 | O18: 3.67 | P18: =N18*O18 -> 73400 | V18: =-P18 -> -73400
B19: Cesta básica (dinheiro) | H19: -791.28
B20: Vale refeição 5x767,00 | H20: -3835
AP21: =#REF! -> #REF!
B22: Venda de Gasolina | J22: =-M22 -> 7208.88 | K22: -1226 | L22: 5.88 | M22: =K22*L22 -> -7208.88 | AP22: =#REF! -> #REF!
B23: Venda de Etanol | J23: =-P23 -> 7065.48 | N23: -1821 | O23: 3.88 | P23: =N23*O23 -> -7065.48 | AP23: =#REF! -> #REF!
B24: Separação Cartão/Outros | H24: =-J24-I24 -> 4369.19 | I24: 9905.17 | J24: =-SUM(J22:J23) -> -14274.36 | AO24: =A2 -> 0 | AP24: =#REF! -> #REF!
B25: Ajuste estoque e valor diário (lucro embutido) | K25: 118 | M25: =(K28*4.8876027)-M14-M2-M22 -> 1793.4155 | N25: 164 | P25: =(N28*3.650637)-P18-P2-P23 -> 1016.3657 | AP25: =#REF! -> #REF!
AO26: =A3 -> 45905 | AP26: =#REF! -> #REF!
B27: Saldo Giro no dia | C27: =D28+E28+F28+G28+H28+I28+J28+M28+P28 -> 100565.77 | M27: =K27*L27 -> 0 | P27: =N27*O27 -> 0 | AO27: =SUM($Q2:AN27) -> -399373.45 | AS27: TERCEIROS
B28: Saldo Líquido do dia | C28: =AO28 -> -298807.68 | D28: =SUM(D2:D27) -> 72.55 | E28: =SUM(E2:E27) -> -38473.98 | F28: =SUM(F2:F27) -> 6.19 | G28: =SUM(G2:G27) -> -400 | H28: =SUM(H2:H27) -> -5592.79 | I28: =SUM(I2:I27) -> 9905.17 | J28: =SUM(J2:J27) -> 0 | K28: =SUM(K2:K27) -> 11056 | L28: =M28/K28 -> 4.8876031 | M28: =ROUND(SUM(M2:M27),2) -> 54037.34 | N28: =SUM(N2:N27) -> 22191 | O28: =P28/N28 -> 3.6506372 | P28: =ROUND(SUM(P2:P27),2) -> 81011.29 | Q28: =SUM(Q2:Q27) -> -48200 | R28: =SUM(R2:R27) -> 0 | S28: =SUM(S2:S27) -> 0 | T28: =SUM(T2:T27) -> -16073.45 | U28: =SUM(U2:U27) -> -261700 | V28: =SUM(V2:V27) -> -73400 | W28: =SUM(W2:W27) -> 0 | X28: =SUM(X2:X27) -> 0 | ... AH28: =SUM(AH2:AH27) -> 0 | AJ28: =SUM(AJ2:AJ27) -> 0 | AK28: =SUM(AK2:AK27) -> 0 | AL28: =SUM(AL2:AL27) -> 0 | AM28: =SUM(AM2:AM27) -> 0 | AN28: =SUM(AN2:AN27) -> 0 | AO28: =D28+E28+F28+G28+H28+I28+J28+M28+P28+SUM(Q28:AN28) -> -298807.68 | AS28: SALDO C/C
A29: =A3+1 -> 45906 | B29: Credito Vendas Cartão | D29: 9693.15 | I29: -9693.15 | AP29: =#REF! -> #REF!
B30: Desconto taxas Cartão | I30: =-I28-I29 -> -212.02
B31: Luiz Neto (BB) | D31: -6000 | R31: =-D31 -> 6000
B32: Tarifa pix Luiz Neto | D32: -4.9
B33: Pag boleto Elektro (postp) | D33: -182.46
B34: Pag boleto | D34: -195
B35: Pag boleto | D35: -385.5
AP36: =#REF! -> #REF!
B37: Venda de Gasolina | J37: =-M37 -> 10548 | K37: -1800 | L37: 5.86 | M37: =K37*L37 -> -10548 | AP37: =#REF! -> #REF!
B38: Venda de Etanol | J38: =-P38 -> 9607.54 | N38: -2489 | O38: 3.86 | P38: =N38*O38 -> -9607.54 | AP38: =#REF! -> #REF!
B39: Separação Cartão/Outros | H39: =-J39-I39 -> 6047.48 | I39: 14108.06 | J39: =-SUM(J37:J38) -> -20155.54 | AP39: =#REF! -> #REF!
B40: Ajuste estoque e valor diário (lucro embutido) | K40: 0 | M40: =(K43*L28)-M28-M37 -> 1750.3144 | N40: -52 | P40: =(N43*O28)-P28-P38 -> 331.27089 | AP40: =#REF! -> #REF!
AO41: =A29 -> 45906 | AP41: =#REF! -> #REF!
B42: Saldo Giro no dia | C42: =D43+E43+F43+G43+H43+I43+J43+M43+P43 -> 95667.47 | AO42: =SUM($Q28:AN42) -> -393373.45 | AS42: TERCEIROS
B43: Saldo Líquido do dia | C43: =AO43 -> -297705.98 | D43: =SUM(D28:D42) -> 2997.84 | E43: =SUM(E28:E42) -> -38473.98 | F43: =SUM(F28:F42) -> 6.19 | G43: =SUM(G28:G42) -> -400 | H43: =SUM(H28:H42) -> 454.69 | I43: =SUM(I28:I42) -> 14108.06 | J43: =SUM(J28:J42) -> 0 | K43: =SUM(K28:K42) -> 9256 | L43: =M43/K43 -> 4.8876026 | M43: =ROUND(SUM(M28:M42),2) -> 45239.65 | N43: =SUM(N28:N42) -> 19650 | O43: =P43/N43 -> 3.6506372 | P43: =ROUND(SUM(P28:P42),2) -> 71735.02 | Q43: =SUM(Q28:Q42) -> -48200 | R43: =SUM(R28:R42) -> 6000 | S43: =SUM(S28:S42) -> 0 | T43: =SUM(T28:T42) -> -16073.45 | U43: =SUM(U28:U42) -> -261700 | V43: =SUM(V28:V42) -> -73400 | W43: =SUM(W28:W42) -> 0 | X43: =SUM(X28:X42) -> 0 | ... AN43: =SUM(AN28:AN42) -> 0 | AO43: =D43+E43+F43+G43+H43+I43+J43+M43+P43+SUM(Q43:AN43) -> -297705.98 | AS43: SALDO C/C
A44: =A29+1 -> 45907 | B44: Credito Vendas Cartão | D44: 13750.2 | I44: =-D44 -> -13750.2
B45: Desconto taxas Cartão | I45: =-I43-I44 -> -357.86
B46: Transf. Lucila Regina Ceregato Correa | D46: -16748 | F46: =-D46 -> 16748 | G46: =-E46 -> 0
B48: Venda de Gasolina | J48: =-M48 -> 6885.5 | K48: -1175 | L48: 5.86 | M48: =K48*L48 -> -6885.5 | AP48: =#REF! -> #REF!
B49: Venda de Etanol | J49: =-P49 -> 6450.06 | N49: -1671 | O49: 3.86 | P49: =N49*O49 -> -6450.06 | AP49: =#REF! -> #REF!
B50: Separação Cartão/Outros | H50: =-J50-I50 -> 5276.77 | I50: 8058.79 | J50: =-SUM(J48:J49) -> -13335.56 | AO50: =A31 -> 0 | AP50: =#REF! -> #REF!
B51: Ajuste de saldo e valor estoque diário | K51: -70 | M51: =(K54*L43)-M43-M48 -> 800.43472 | N51: -48 | P51: =(N54*O43)-P43-P49 -> 174.61474 | AO51: =A30 -> 0 | AP51: =#REF! -> #REF!
B53: Saldo Giro no dia | C53: =D54+E54+F54+G54+H54+I54+J54+M54+P54 -> 96284.65 | AO53: =SUM($Q43:AN53) -> -393373.45 | AS53: TERCEIROS
B54: Saldo Líquido do dia | C54: =AO54 -> -297088.8 | D54: =SUM(D43:D53) -> 0.04 | E54: =SUM(E43:E53) -> -38473.98 | F54: =SUM(F43:F53) -> 16754.19 | G54: =SUM(G43:G53) -> -400 | H54: =SUM(H43:H53) -> 5731.46 | I54: =SUM(I43:I53) -> 8058.79 | J54: =SUM(J43:J53) -> 0 | K54: =SUM(K43:K53) -> 8011 | L54: =M54/K54 -> 4.887602 | M54: =ROUND(SUM(M43:M53),2) -> 39154.58 | N54: =SUM(N43:N53) -> 17931 | O54: =P54/N54 -> 3.6506369 | P54: =ROUND(SUM(P43:P53),2) -> 65459.57 | Q54: =SUM(Q43:Q53) -> -48200 | R54: =SUM(R43:R53) -> 6000 | S54: =SUM(S43:S53) -> 0 | T54: =SUM(T43:T53) -> -16073.45 | U54: =SUM(U43:U53) -> -261700 | V54: =SUM(V43:V53) -> -73400 | W54: =SUM(W43:W53) -> 0 | X54: =SUM(X43:X53) -> 0 | ... AN54: =SUM(AN43:AN53) -> 0 | AO54: =D54+E54+F54+G54+H54+I54+J54+M54+P54+SUM(Q54:AN54) -> -297088.8 | AS54: SALDO C/C
A55: =A44+1 -> 45908 | B55: Pix e depósitos Banco Itaú | E55: 3364.47 | H55: =-E55 -> -3364.47
B56: DAAE | E56: -316.73
B57: Sindicato | E57: -654.5
B58: Credito Vendas Cartão | D58: 7867.37 | I58: =-D58 -> -7867.37
B59: Desconto taxas Cartão | I59: =-I54-I58 -> -191.42
B60: Transf. Lucila Regina Ceregato Correa | D60: -7867 | F60: =-D60 -> 7867
B61: Pag boleto WL NF 74192 1/3 VENC 08/08 | F61: -11265.54 | M61: =K61*L61 -> 0 | P61: =N61*O61 -> 0 | U61: =-F61 -> 11265.54 | AQ61: Saidas | AR61: #REF!
B62: Pag boleto WL NF 74192 2/3 VENC 11/08 | F62: -11265.54 | M62: =K62*L62 -> 0 | P62: =N62*O62 -> 0 | U62: =-F62 -> 11265.54 | AQ62: Saidas | AR62: #REF!
B63: Pag. NF 82199 Petroriente 5x5,00 GC (Eraldo) | K63: 5000 | L63: 5 | M63: =K63*L63 -> 25000 | P63: =N63*O63 -> 0 | Q63: =-M63 -> -25000
B66: Venda de Gasolina | J66: =-M66 -> 7067.16 | K66: -1206 | L66: 5.86 | M66: =K66*L66 -> -7067.16 | AP66: =#REF! -> #REF!
B67: Venda de Etanol | J67: =-P67 -> 7148.72 | N67: -1852 | O67: 3.86 | P67: =N67*O67 -> -7148.72 | AP67: =#REF! -> #REF!
B68: Separação Cartão/Outros | H68: =-J68-I68 -> 5258.85 | I68: 8957.03 | J68: =-SUM(J66:J67) -> -14215.88 | AP68: =#REF! -> #REF!
B69: Ajuste de saldo e valor estoque diário | K69: -21 | M69: =(K72*4.9307954)-M54-M66-M63 -> 1017.073 | N69: -20 | P69: =(N72*O54)-P54-P67 -> 314.72775 | AO69: =A43 -> 0 | AP69: =#REF! -> #REF!
AO70: =A55 -> 45908
B71: Saldo Giro no dia | C71: =D72+E72+F72+G72+H72+I72+J72+M72+P72 -> 98922.72 | AO71: =SUM($Q54:AN71) -> -395842.37 | AS71: TERCEIROS
B72: Saldo Líquido do dia | C72: =AO72 -> -296919.65 | D72: =SUM(D54:D71) -> 0.41 | E72: =SUM(E54:E71) -> -36080.74 | F72: =SUM(F54:F71) -> 2090.11 | G72: =SUM(G54:G71) -> -400 | H72: =SUM(H54:H71) -> 7625.84 | I72: =SUM(I54:I71) -> 8957.03 | J72: =SUM(J54:J71) -> 0 | K72: =SUM(K54:K71) -> 11784 | L72: =M72/K72 -> 4.9307951 | M72: =ROUND(SUM(M54:M71),2) -> 58104.49 | N72: =SUM(N54:N71) -> 16059 | O72: =P72/N72 -> 3.650637 | P72: =ROUND(SUM(P54:P71),2) -> 58625.58 | Q72: =SUM(Q54:Q71) -> -73200 | R72: =SUM(R54:R71) -> 6000 | S72: =SUM(S54:S71) -> 0 | T72: =SUM(T54:T71) -> -16073.45 | U72: =SUM(U54:U71) -> -239168.92 | V72: =SUM(V54:V71) -> -73400 | W72: =SUM(W54:W71) -> 0 | X72: =SUM(X54:X71) -> 0 | ... AN72: =SUM(AN54:AN71) -> 0 | AO72: =D72+E72+F72+G72+H72+I72+J72+M72+P72+SUM(Q72:AN72) -> -296919.65 | AS72: SALDO C/C
A73: =A55+1 -> 45909 | B73: Pix e depósitos Banco Itaú | E73: =36080.74-35145.74+180 -> 1115 | H73: =-E73 -> -1115
B74: Pag Universo | E74: -180
B75: Credito Vendas Cartão | D75: 8713.82 | I75: =-D75 -> -8713.82
B76: Desconto taxas Cartão | I76: =-I75-I72 -> -243.21
B77: Transf. Lucila Regina Ceregato Correa | D77: -8714 | F77: =-D77 -> 8714 | G77: =-E77 -> 0
B78: Pag boleto | F78: -99.76 | G78: =-E78 -> 0
B79: Pix Lucila (Nubank) | F79: -300 | G79: =-F79 -> 300
B81: Venda de Gasolina | J81: =-M81 -> 5432.22 | K81: -927 | L81: 5.86 | M81: =K81*L81 -> -5432.22 | AP81: =#REF! -> #REF!
B82: Venda de Etanol | J82: =-P82 -> 7349.44 | N82: -1904 | O82: 3.86 | P82: =N82*O82 -> -7349.44 | AP82: =#REF! -> #REF!
B83: Separação Cartão/Outros | H83: =-J83-I83 -> 4807.68 | I83: 7973.98 | J83: =-SUM(J81:J82) -> -12781.66 | AO83: =A57 -> 0 | AP83: =#REF! -> #REF!
B84: Ajuste de saldo e valor estoque diário | K84: 3 | M84: =(K87*L72)-M72-M81 -> 876.16529 | N84: -128 | P84: =(N87*O72)-P72-P82 -> -68.654437 | AO84: =A56 -> 0 | AP84: =#REF! -> #REF!
AO85: =A73 -> 45909
B86: Saldo Giro no dia | C86: =D87+E87+F87+G87+H87+I87+J87+M87+P87 -> 99207.27 | AO86: =SUM($Q72:AN86) -> -395842.37 | AS86: TERCEIROS
B87: Saldo Líquido do dia | C87: =AO87 -> -296635.1 | D87: =SUM(D72:D86) -> 0.23 | E87: =SUM(E72:E86) -> -35145.74 | F87: =SUM(F72:F86) -> 10404.35 | G87: =SUM(G72:G86) -> -100 | H87: =SUM(H72:H86) -> 11318.52 | I87: =SUM(I72:I86) -> 7973.98 | J87: =SUM(J72:J86) -> 0 | K87: =SUM(K72:K86) -> 10860 | L87: =M87/K87 -> 4.9307956 | M87: =ROUND(SUM(M72:M86),2) -> 53548.44 | N87: =SUM(N72:N86) -> 14027 | O87: =P87/N87 -> 3.6506373 | P87: =ROUND(SUM(P72:P86),2) -> 51207.49 | Q87: =SUM(Q72:Q86) -> -73200 | R87: =SUM(R72:R86) -> 6000 | S87: =SUM(S72:S86) -> 0 | T87: =SUM(T72:T86) -> -16073.45 | U87: =SUM(U72:U86) -> -239168.92 | V87: =SUM(V72:V86) -> -73400 | W87: =SUM(W72:W86) -> 0 | X87: =SUM(X72:X86) -> 0 | ... AN87: =SUM(AN72:AN86) -> 0 | AO87: =D87+E87+F87+G87+H87+I87+J87+M87+P87+SUM(Q87:AN87) -> -296635.1 | AS87: SALDO C/C
A88: =A73+1 -> 45910 | B88: Pix e depósitos Banco Itaú | E88: =100+5+100+615.5+50+60+100+100+100+100+80+9+30+50+30+25+100+15+15+40+50+15 -> 1789.5 | H88: =-E88 -> -1789.5
B89: Transf. Elaine | E89: 2175.26 | H89: =-E89 -> -2175.26
B90: Juros limite conta | E90: -2881.51
B91: Itau Seguro | E91: -188.82
B92: Da Claro Resid | E92: -110.28
B93: Pag IPVA+Licenciamento | E93: =-2657.14-174.95 -> -2832.09
B94: Transf Luiz Gustavo | E94: -600
B95: Credito Vendas Cartão | D95: 7782.79 | I95: =-D95 -> -7782.79
B96: Desconto taxas Cartão | I96: =-I87-I95 -> -191.19
B97: Transf. Lucila Regina Ceregato Correa | D97: -7780 | F97: =-D97 -> 7780 | G97: =-E97 -> 0
B98: Pag boleto WL NF 74192 3/3 VENC 12/08 | F98: -11268.92 | P98: =N98*O98 -> 0 | U98: =-F98 -> 11268.92 | AQ98: Saidas | AR98: #REF!
B99: Pix Sirlei (Itau) | F99: -178 | G99: =-E99 -> 0
B100: NF 83745 WL 3x12.233,33 | N100: 10000 | O100: 3.67 | P100: =N100*O100 -> 36700 | V100: =-P100 -> -36700
B102: Venda de Gasolina | J102: =-M102 -> 7260.54 | K102: -1239 | L102: 5.86 | M102: =K102*L102 -> -7260.54 | AP102: =#REF! -> #REF!
B103: Venda de Etanol | J103: =-P103 -> 7449.8 | N103: -1930 | O103: 3.86 | P103: =N103*O103 -> -7449.8 | AP103: =#REF! -> #REF!
B104: Separação Cartão/Outros | H104: =-J104-I104 -> 4746.45 | I104: 9963.89 | J104: =-SUM(J102:J103) -> -14710.34 | AO104: =A76 -> 0 | AP104: =#REF! -> #REF!
B105: Ajuste de saldo e valor estoque diário | K105: -3 | M105: =(K108*L87)-M87-M102 -> 1136.4919 | N105: 241 | P105: =(N108*3.658696)-P87-P103-P100 -> 1270.2612 | AO105: =A77 -> 0 | AP105: =#REF! -> #REF!
AO106: =A88 -> 45910
...

Sheet Out25
A1: PERÍODO 01 á 31/OUT/25 | C1: =D2+E2+F2+G2+H2+I2+J2+M2+P2 -> 51048.21 | D1: SPOT | E1: ITAU | F1: LUCILA | G1: HADEN | H1: CAIXA | I1: CARTAO | J1: VENDAS | K1: GASOLINA | N1: ETANOL | Q1: ERALDO | R1: LUIZ F. | S1: LUCILA | T1: DIVIDA | U1: AVANT | V1: WL | AO1: Total | AP1: Saldo Total | AQ1: Saldo Edson | AR1: Saldo Master
B2: Saldo Inicial do dia | C2: =D2+E2+F2+G2+H2+I2+J2+M2+P2+SUM(Q2:AN2) -> -316079.67 | D2: ='Set25'!D458 -> 20130.38 | E2: ='Set25'!E458 -> -20251.87 | F2: ='Set25'!F458 -> 649.16 | G2: 0 | H2: ='Set25'!H458 -> -32.68 | I2: ='Set25'!I458 -> 11179.04 | J2: ='Set25'!J458 -> 0 | K2: ='Set25'!K458 -> 5095 | L2: ='Set25'!L458 -> 4.9769323 | M2: ='Set25'!M458 -> 25357.47 | N2: ='Set25'!N458 -> 3969 | O2: ='Set25'!O458 -> 3.531547 | ... AN2: ='Set25'!AN458 -> 0 | AO2: =D2+E2+F2+G2+H2+I2+J2+M2+P2+SUM(Q2:AN2) -> -316079.67 | AP2: =#REF! -> #REF! | AQ2: =#REF! -> #REF! | AR2: =AP2-AQ2 -> #REF!
A3: 45931 | B3: Credito Vendas Cartão | D3: 10926.8 | I3: =-D3 -> -10926.8 | AQ3: Saidas | AR3: #REF!
B4: Desconto taxas Cartão | I4: =-I2-I3 -> -252.24 | AQ4: Saidas | AR4: #REF!
B5: Mensalidade POS | D5: -70 | AQ5: Saidas | AR5: #REF!
B6: Pix e depósitos Banco Itaú | E6: =50+25+50+25+260+30+30+10+25+50+0.39+30+11.25+40+20+30+30+10+20+20+519.93+100+50+65+15+40+60 -> 1616.57 | H6: =-E6 -> -1616.57 | AQ6: Saidas | AR6: #REF!
B7: Pix e depósitos Banco Itaú - Lucila | E7: =654+2000+2000+1500 -> 6154 | H7: =-E7 -> -6154
B8: Transf. Lucila | E8: -9900 | F8: =-E8 -> 9900 | AQ8: Saidas | AR8: #REF!
B9: Transf. Lucila Regina Ceregato Correa | D9: -30900 | F9: =-D9 -> 30900 | AQ9: Saidas | AR9: #REF!
B10: NF 99547 WL 15x3,55 EH 2X26625,00 | N10: 15000 | O10: 3.55 | P10: =N10*O10 -> 53250 | V10: =-P10 -> -53250
AP11: =#REF! -> #REF!
B12: Venda de Gasolina | J12: =-M12 -> 6612.18 | K12: -1142 | L12: 5.79 | M12: =K12*L12 -> -6612.18 | AP12: =#REF! -> #REF!
B13: Venda de Etanol | J13: =-P13 -> 8974.72 | N13: -2368 | O13: 3.79 | P13: =N13*O13 -> -8974.72 | AP13: =#REF! -> #REF!
B14: Separação Cartão/Outros | H14: =-J14-I14 -> 6038.9 | I14: 9548 | J14: =-SUM(J12:J13) -> -15586.9 | AO14: =A2 -> 0 | AP14: =#REF! -> #REF!
B15: Ajuste estoque e valor diário (lucro embutido) | K15: -53 | M15: =(K18*L2)-M2-M12 -> 664.74592 | N15: 83 | P15: =(N18*((P2+P10)/(N2+N10))-P10-P2-P13) -> 871.79247 | AP15: =#REF! -> #REF!
AO16: =A3 -> 45931 | AP16: =#REF! -> #REF!
B17: Saldo Giro no dia | C17: =D18+E18+F18+G18+H18+I18+J18+M18+P18 -> 105512.51 | M17: =K17*L17 -> 0 | P17: =N17*O17 -> 0 | AO17: =SUM($Q2:AN17) -> -420377.88 | AS17: TERCEIROS
B18: Saldo Líquido do dia | C18: =AO18 -> -314865.37 | D18: =SUM(D2:D17) -> 87.18 | E18: =SUM(E2:E17) -> -22381.3 | F18: =SUM(F2:F17) -> 41449.16 | G18: =SUM(G2:G17) -> 0 | H18: =SUM(H2:H17) -> -1764.35 | I18: =SUM(I2:I17) -> 9548 | J18: =SUM(J2:J17) -> 0 | K18: =SUM(K2:K17) -> 3900 | L18: =M18/K18 -> 4.9769333 | M18: =ROUND(SUM(M2:M17),2) -> 19410.04 | N18: =SUM(N2:N17) -> 16684 | O18: =P18/N18 -> 3.5461388 | P18: =ROUND(SUM(P2:P17),2) -> 59163.78 | Q18: =SUM(Q2:Q17) -> -248820 | R18: =SUM(R2:R17) -> 7865.57 | S18: =SUM(S2:S17) -> 0 | T18: =SUM(T2:T17) -> -16073.45 | U18: =SUM(U2:U17) -> 0 | V18: =SUM(V2:V17) -> -163350 | W18: =SUM(W2:W17) -> 0 | X18: =SUM(X2:X17) -> 0 | ... AH18: =SUM(AH2:AH17) -> 0 | AJ18: =SUM(AJ2:AJ17) -> 0 | AK18: =SUM(AK2:AK17) -> 0 | AL18: =SUM(AL2:AL17) -> 0 | AM18: =SUM(AM2:AM17) -> 0 | AN18: =SUM(AN2:AN17) -> 0 | AO18: =D18+E18+F18+G18+H18+I18+J18+M18+P18+SUM(Q18:AN18) -> -314865.37 | AS18: SALDO C/C
A19: =A3+1 -> 45932 | B19: Credito Vendas Cartão | D19: 9310.7 | I19: =-D19 -> -9310.7 | AP19: =#REF! -> #REF!
B20: Desconto taxas Cartão | I20: =-I18-I19 -> -237.3
B21: Pix e depósitos Banco Itaú | E21: =150+50+117+50+50+100+20+10+100+10+50+19+50+20+10+10+10+100+185+30 -> 1141 | H21: =-E21 -> -1141 | R21: =-D21 -> 0
B22: Tarifa pacote Itaú | E22: -92.5
B23: IOF | E23: -196.01
B24: Pag Elektro (casa) | E24: -541.5
B25: Pag Elektro (posto) | D25: -235.18
B26: Transf. Lucila Regina Ceregato Correa | D26: -9300 | F26: =-D26 -> 9300 | AQ26: Saidas | AR26: #REF!
B27: Transf. Lucila Regina Ceregato Correa | D27: =-F27 -> 50749.16 | F27: -50749.16 | AQ27: Saidas | AR27: #REF!
B28: Pix Petroriente | D28: -50000
B29: Estorno mensalidade POS | D29: 420
B30: Tarifa TED envio Petroriente | D30: -4.9
AP31: =#REF! -> #REF!
B32: Venda de Gasolina | J32: =-M32 -> 7683.33 | K32: -1327 | L32: 5.79 | M32: =K32*L32 -> -7683.33 | AP32: =#REF! -> #REF!
B33: Venda de Etanol | J33: =-P33 -> 8876.18 | N33: -2342 | O33: 3.79 | P33: =N33*O33 -> -8876.18 | AP33: =#REF! -> #REF!
B34: Separação Cartão/Outros | H34: =-J34-I34 -> 5921.58 | I34: 10637.93 | J34: =-SUM(J32:J33) -> -16559.51 | AP34: =#REF! -> #REF!
B35: Ajuste estoque e valor diário (lucro embutido) | K35: 133 | M35: =(K38*L18)-M18-M32 -> 1740.8716 | N35: -3 | P35: =(N38*O18)-P18-P33 -> 560.48448 | AP35: =#REF! -> #REF!
AO36: =A19 -> 45932 | AP36: =#REF! -> #REF!
B37: Saldo Giro no dia | C37: =D38+E38+F38+G38+H38+I38+J38+M38+P38 -> 56926.47 | AO37: =SUM($Q18:AN37) -> -420377.88 | AS37: TERCEIROS
B38: Saldo Líquido do dia | C38: =AO38 -> -363451.41 | D38: =SUM(D18:D37) -> 1026.96 | E38: =SUM(E18:E37) -> -22070.31 | F38: =SUM(F18:F37) -> 0 | G38: =SUM(G18:G37) -> 0 | H38: =SUM(H18:H37) -> 3016.23 | I38: =SUM(I18:I37) -> 10637.93 | J38: =SUM(J18:J37) -> 0 | K38: =SUM(K18:K37) -> 2706 | L38: =M38/K38 -> 4.9769327 | M38: =ROUND(SUM(M18:M37),2) -> 13467.58 | N38: =SUM(N18:N37) -> 14339 | O38: =P38/N38 -> 3.5461385 | P38: =ROUND(SUM(P18:P37),2) -> 50848.08 | Q38: =SUM(Q18:Q37) -> -248820 | R38: =SUM(R18:R37) -> 7865.57 | S38: =SUM(S18:S37) -> 0 | T38: =SUM(T18:T37) -> -16073.45 | U38: =SUM(U18:U37) -> 0 | V38: =SUM(V18:V37) -> -163350 | W38: =SUM(W18:W37) -> 0 | X38: =SUM(X18:X37) -> 0 | ... AN38: =SUM(AN18:AN37) -> 0 | AO38: =D38+E38+F38+G38+H38+I38+J38+M38+P38+SUM(Q38:AN38) -> -363451.41 | AS38: SALDO C/C
A39: =A19+1 -> 45933 | B39: Credito Vendas Cartão | D39: 10378.19 | I39: =-D39 -> -10378.19
B40: Desconto taxas Cartão | I40: =-I38-I39 -> -259.74
B41: Pix e depósitos Banco Itaú | E41: =20+100+19+20+40+50+10+50+50+20+20+50+800 -> 1249 | H41: =-E41 -> -1249 | R41: =-D41 -> 0
B42: Pix e depósitos Banco Itaú - Lucila | E42: =1680+1950+2000+290+110 -> 6030 | H42: =-E42 -> -6030
B43: Pix EDL | E43: -800
B44: Pag Papirus | E44: -19.15
B45: Transf. Lucila Regina Ceregato Correa | D45: -11300 | F45: =-D45 -> 11300 | AQ45: Saidas | AR45: #REF!
B46: Pag NF 81639 WL 1/6 12,233,33 (Eraldo) | Q46: =-V46 -> -12233.33 | V46: 12233.33
B47: Pag NF 81639 WL 2/6 12,233,33 (Eraldo) | Q47: =-V47 -> -12233.33 | V47: 12233.33
B48: NF 99547 WL 15x3,55 EH 1/2 26.625,00 (Eraldo) | Q48: =-V48 -> -26625 | V48: 26625
B49: NF 87806 Petroriente 10x5,00 GC (pago pelo posto) | K49: 10000 | L49: 5 | M49: =K49*L49 -> 50000 | U49: =-P49 -> 0
B51: Venda de Gasolina | J51: =-M51 -> 6397.95 | K51: -1105 | L51: 5.79 | M51: =K51*L51 -> -6397.95 | AP51: =#REF! -> #REF!
B52: Venda de Etanol | J52: =-P52 -> 9005.04 | N52: -2376 | O52: 3.79 | P52: =N52*O52 -> -9005.04 | AP52: =#REF! -> #REF!
B53: Separação Cartão/Outros | H53: =-J53-I53 -> 4192.88 | I53: 11210.11 | J53: =-SUM(J51:J52) -> -15402.99 | AO53: =A21 -> 0 | AP53: =#REF! -> #REF!
B54: Ajuste de saldo e valor estoque diário | K54: 77 | M54: =(K57*((M38+M49)/(K38+K49)))-M38-M51-M49 -> 1263.0002 | N54: -105 | P54: =(N57*O38)-P38-P52 -> 207.07037 | AO54: =A20 -> 0 | AP54: =#REF! -> #REF!
B56: Saldo Giro no dia | C56: =D57+E57+F57+G57+H57+I57+J57+M57+P57 -> 107317.65 | AO56: =SUM($Q38:AN56) -> -420377.88 | AS56: TERCEIROS
B57: Saldo Líquido do dia | C57: =AO57 -> -313060.23 | D57: =SUM(D38:D56) -> 105.15 | E57: =SUM(E38:E56) -> -15610.46 | F57: =SUM(F38:F56) -> 11300 | G57: =SUM(G38:G56) -> 0 | H57: =SUM(H38:H56) -> -69.89 | I57: =SUM(I38:I56) -> 11210.11 | J57: =SUM(J38:J56) -> 0 | K57: =SUM(K38:K56) -> 11678 | L57: =M57/K57 -> 4.9950873 | M57: =ROUND(SUM(M38:M56),2) -> 58332.63 | N57: =SUM(N38:N56) -> 11858 | O57: =P57/N57 -> 3.5461385 | P57: =ROUND(SUM(P38:P56),2) -> 42050.11 | Q57: =SUM(Q38:Q56) -> -299911.66 | R57: =SUM(R38:R56) -> 7865.57 | S57: =SUM(S38:S56) -> 0 | T57: =SUM(T38:T56) -> -16073.45 | U57: =SUM(U38:U56) -> 0 | V57: =SUM(V38:V56) -> -112258.34 | W57: =SUM(W38:W56) -> 0 | X57: =SUM(X38:X56) -> 0 | ... AN57: =SUM(AN38:AN56) -> 0 | AO57: =D57+E57+F57+G57+H57+I57+J57+M57+P57+SUM(Q57:AN57) -> -313060.23 | AS57: SALDO C/C
A58: =A39+1 -> 45934 | B58: Credito Vendas Cartão | D58: 10935.65 | I58: =-D58 -> -10935.65
B59: Desconto taxas Cartão | I59: =-I57-I58 -> -274.46
B60: Transf. Lucila Regina Ceregato Correa | D60: -11000 | F60: =-D60 -> 11000 | AQ60: Saidas | AR60: #REF!
B62: Venda de Gasolina | J62: =-M62 -> 7283.82 | K62: -1258 | L62: 5.79 | M62: =K62*L62 -> -7283.82 | AP62: =#REF! -> #REF!
B63: Venda de Etanol | J63: =-P63 -> 8826.91 | N63: -2329 | O63: 3.79 | P63: =N63*O63 -> -8826.91 | AP63: =#REF! -> #REF!
B64: Separação Cartão/Outros | H64: =-J64-I64 -> 5052.46 | I64: 11058.27 | J64: =-SUM(J62:J63) -> -16110.73 | AP64: =#REF! -> #REF!
B65: Ajuste de saldo e valor estoque diário | K65: 0 | M65: =(K68*L57)-M57-M62 -> 1000.0001 | N65: 0 | P65: =(N68*O57)-P57-P63 -> 567.9535 | AO65: =A38 -> 0 | AP65: =#REF! -> #REF!
AO66: =A58 -> 45934
B67: Saldo Giro no dia | C67: =D68+E68+F68+G68+H68+I68+J68+M68+P68 -> 108611.14 | AO67: =SUM($Q57:AN67) -> -420377.88 | AS67: TERCEIROS
B68: Saldo Líquido do dia | C68: =AO68 -> -311766.74 | D68: =SUM(D57:D67) -> 40.8 | E68: =SUM(E57:E67) -> -15610.46 | F68: =SUM(F57:F67) -> 22300 | G68: =SUM(G57:G67) -> 0 | H68: =SUM(H57:H67) -> 4982.57 | I68: =SUM(I57:I67) -> 11058.27 | J68: =SUM(J57:J67) -> 0 | K68: =SUM(K57:K67) -> 10420 | L68: =M68/K68 -> 4.9950873 | M68: =ROUND(SUM(M57:M67),2) -> 52048.81 | N68: =SUM(N57:N67) -> 9529 | O68: =P68/N68 -> 3.5461381 | P68: =ROUND(SUM(P57:P67),2) -> 33791.15 | Q68: =SUM(Q57:Q67) -> -299911.66 | R68: =SUM(R57:R67) -> 7865.57 | S68: =SUM(S57:S67) -> 0 | T68: =SUM(T57:T67) -> -16073.45 | U68: =SUM(U57:U67) -> 0 | V68: =SUM(V57:V67) -> -112258.34 | W68: =SUM(W57:W67) -> 0 | X68: =SUM(X57:X67) -> 0 | ... AN68: =SUM(AN57:AN67) -> 0 | AO68: =D68+E68+F68+G68+H68+I68+J68+M68+P68+SUM(Q68:AN68) -> -311766.74 | AS68: SALDO C/C
A69: =A58+1 -> 45935 | B69: Credito Vendas Cartão | D69: 10797.38 | I69: =-D69 -> -10797.38
B70: Desconto taxas Cartão | I70: =-I68-I69 -> -260.89
B71: Transf. Lucila Regina Ceregato Correa | D71: -10800 | F71: =-D71 -> 10800 | AQ71: Saidas | AR71: #REF!
B72: Cesta básica (dinheiro) | H72: -791.28
B73: Vale refeição 5x767,00 | H73: -3835
B75: Venda de Gasolina | J75: =-M75 -> 5876.85 | K75: -1015 | L75: 5.79 | M75: =K75*L75 -> -5876.85 | AP75: =#REF! -> #REF!
B76: Venda de Etanol | J76: =-P76 -> 4870.15 | N76: -1285 | O76: 3.79 | P76: =N76*O76 -> -4870.15 | AP76: =#REF! -> #REF!
B77: Separação Cartão/Outros | H77: =-J77-I77 -> 3916.25 | I77: 6830.75 | J77: =-SUM(J75:J76) -> -10747 | AP77: =#REF! -> #REF!
B78: Ajuste de saldo e valor estoque diário | K78: 2 | M78: =(K81*L68)-M68-M75 -> 816.82653 | N78: -122 | P78: =(N81*O68)-P68-P76 -> -119.26631 | AO78: =A59 -> 0 | AP78: =#REF! -> #REF!
AO79: =A69 -> 45935
B80: Saldo Giro no dia | C80: =D81+E81+F81+G81+H81+I81+J81+M81+P81 -> 104421.53 | AO80: =SUM($Q68:AN80) -> -420377.88 | AS80: TERCEIROS
B81: Saldo Líquido do dia | C81: =AO81 -> -315956.35 | D81: =SUM(D68:D80) -> 38.18 | E81: =SUM(E68:E80) -> -15610.46 | F81: =SUM(F68:F80) -> 33100 | G81: =SUM(G68:G80) -> 0 | H81: =SUM(H68:H80) -> 4272.54 | I81: =SUM(I68:I80) -> 6830.75 | J81: =SUM(J68:J80) -> 0 | K81: =SUM(K68:K80) -> 9407 | L81: =M81/K81 -> 4.9950877 | M81: =ROUND(SUM(M68:M80),2) -> 46988.79 | N81: =SUM(N68:N80) -> 8122 | O81: =P81/N81 -> 3.5461377 | P81: =ROUND(SUM(P68:P80),2) -> 28801.73 | Q81: =SUM(Q68:Q80) -> -299911.66 | R81: =SUM(R68:R80) -> 7865.57 | S81: =SUM(S68:S80) -> 0 | T81: =SUM(T68:T80) -> -16073.45 | U81: =SUM(U68:U80) -> 0 | V81: =SUM(V68:V80) -> -112258.34 | W81: =SUM(W68:W80) -> 0 | X81: =SUM(X68:X80) -> 0 | ... AN81: =SUM(AN68:AN80) -> 0 | AO81: =D81+E81+F81+G81+H81+I81+J81+M81+P81+SUM(Q81:AN81) -> -315956.35 | AS81: SALDO C/C
A82: =A69+1 -> 45936 | B82: Credito Vendas Cartão | D82: 6680.75 | I82: =-D82 -> -6680.75
B83: Desconto taxas Cartão | I83: =-I81-I82 -> -150
B84: Crediario Emprestimo 2/6 parcelas 3.214,69 | E84: =-1141.12-5-50-700-20.7-20-20-50-100-170-30-50-50-25-50-732.87 -> -3214.69 | M84: =K84*L84 -> 0 | P84: =N84*O84 -> 0 | T84: =-E84 -> 3214.69 | AQ84: Saidas | AR84: #REF!
B85: Transf. Lucila Regina Ceregato Correa | D85: -6700 | F85: =-D85 -> 6700 | AQ85: Saidas | AR85: #REF!
B86: Pag boleto WL NF 99547 2/2 VENC 06/10 | F86: -26625 | V86: =-F86 -> 26625
B87: NF 101652 WL 15x3,55 EH 2X26625,00 | N87: 15000 | O87: 3.55 | P87: =N87*O87 -> 53250 | V87: =-P87 -> -53250
B88: Pag NF 81639 WL 3/6 12,233,33 (Eraldo) | Q88: =-V88 -> -12233.33 | V88: 12233.33
B89: Pag NF 81639 WL 4/6 12,233,33 (Eraldo) | Q89: =-V89 -> -12233.33 | V89: 12233.33
B91: Venda de Gasolina | J91: =-M91 -> 6664.29 | K91: -1151 | L91: 5.79 | M91: =K91*L91 -> -6664.29 | AP91: =#REF! -> #REF!
B92: Venda de Etanol | J92: =-P92 -> 8125.76 | N92: -2144 | O92: 3.79 | P92: =N92*O92 -> -8125.76 | AP92: =#REF! -> #REF!
B93: Separação Cartão/Outros | H93: =-J93-I93 -> 5502.17 | I93: 9287.88 | J93: =-SUM(J91:J92) -> -14790.05 | AP93: =#REF! -> #REF!
B94: Ajuste de saldo e valor estoque diário | K94: -82 | M94: =(K97*L81)-M81-M91 -> 505.34687 | N94: 57 | P94: =(N97*((P81+P87)/(N81+N87))-P81-P92-P87) -> 719.74147 | AO94: =A71 -> 0 | AP94: =#REF! -> #REF!
AO95: =A82 -> 45936
B96: Saldo Giro no dia | C96: =D97+E97+F97+G97+H97+I97+J97+M97+P97 -> 128906.93 | AO96: =SUM($Q81:AN96) -> -443788.19 | AS96: TERCEIROS
B97: Saldo Líquido do dia | C97: =AO97 -> -314881.26 | D97: =SUM(D81:D96) -> 18.93 | E97: =SUM(E81:E96) -> -18825.15 | F97: =SUM(F81:F96) -> 13175 | G97: =SUM(G81:G96) -> 0 | H97: =SUM(H81:H96) -> 9774.71 | I97: =SUM(I81:I96) -> 9287.88 | J97: =SUM(J81:J96) -> 0 | K97: =SUM(K81:K96) -> 8174 | L97: =M97/K97 -> 4.9950881 | M97: =ROUND(SUM(M81:M96),2) -> 40829.85 | N97: =SUM(N81:N96) -> 21035 | O97: =P97/N97 -> 3.5486432 | P97: =ROUND(SUM(P81:P96),2) -> 74645.71 | Q97: =SUM(Q81:Q96) -> -324378.32 | R97: =SUM(R81:R96) -> 7865.57 | S97: =SUM(S81:S96) -> 0 | T97: =SUM(T81:T96) -> -12858.76 | U97: =SUM(U81:U96) -> 0 | V97: =SUM(V81:V96) -> -114416.68 | W97: =SUM(W81:W96) -> 0 | X97: =SUM(X81:X96) -> 0 | ... AN97: =SUM(AN81:AN96) -> 0 | AO97: =D97+E97+F97+G97+H97+I97+J97+M97+P97+SUM(Q97:AN97) -> -314881.26 | AS97: SALDO C/C
A98: =A82+1 -> 45937 | B98: Credito Vendas Cartão | D98: 9050.51 | I98: =-D98 -> -9050.51
B99: Desconto taxas Cartão | I99: =-I97-I98 -> -237.37
B100: Pix e depósitos Banco Itaú | E100: =150 -> 150 | H100: =-E100 -> -150
B101: Transf. Lucila Regina Ceregato Correa | D101: -9000 | F101: =-D101 -> 9000 | AQ101: Saidas | AR101: #REF!
B103: Venda de Gasolina | J103: =-M103 -> 7538.58 | K103: -1302 | L103: 5.79 | M103: =K103*L103 -> -7538.58 | AP103: =#REF! -> #REF!
B104: Venda de Etanol | J104: =-P104 -> 8193.98 | N104: -2162 | O104: 3.79 | P104: =N104*O104 -> -8193.98 | AP104: =#REF! -> #REF!
B105: Separação Cartão/Outros | H105: =-J105-I105 -> 6555.78 | I105: 9176.78 | J105: =-SUM(J103:J104) -> -15732.56 | AP105: =#REF! -> #REF!
B106: Ajuste de saldo e valor estoque diário | K106: -14 | M106: =(K109*L97)-M97-M103 -> 965.04408 | N106: 142 | P106: =(N109*O97)-P97-P104 -> 1025.7207 | AO106: =A94 -> 0 | AP106: =#REF! -> #REF!
...

Sheet Nov25
A1: PERÍODO 01 á 30/NOV/25 | C1: =D2+E2+F2+G2+H2+I2+J2+M2+P2 -> 135970.47 | D1: SPOT | E1: ITAU | F1: LUCILA | G1: HADEN | H1: CAIXA | I1: CARTAO | J1: VENDAS | K1: GASOLINA | N1: ETANOL | Q1: ERALDO | R1: LUIZ F. | S1: LUCILA | T1: DIVIDA | U1: AVANT | V1: WL | AO1: Total | AP1: Saldo Total | AQ1: Saldo Edson | AR1: Saldo Master
B2: Saldo Inicial do dia | C2: =D2+E2+F2+G2+H2+I2+J2+M2+P2+SUM(Q2:AN2) -> -310071.44 | D2: ='Out25'!D486 -> 9194.857 | E2: ='Out25'!E486 -> -22339.08 | F2: ='Out25'!F486 -> 0 | G2: ='Out25'!G486 -> 0 | H2: ='Out25'!H486 -> 9400 | I2: ='Out25'!I486 -> 11823.73 | J2: ='Out25'!J486 -> 0 | K2: ='Out25'!K486 -> 12517 | ... AO2: ='Out25'!AO486 -> -310071.44 | AP2: =#REF! -> #REF! | AQ2: =#REF! -> #REF! | AR2: =AP2-AQ2 -> #REF!
A3: 45962 | B3: Credito Vendas Cartão | D3: 11540.89 | I3: =-D3 -> -11540.89 | AQ3: Saidas | AR3: #REF!
B4: Desconto taxas Cartão | I4: =-I2-I3 -> -282.84 | AQ4: Saidas | AR4: #REF!
B5: Mensalidade POS | D5: -70 | AQ5: Saidas | AR5: #REF!
B6: Pix e depósitos Banco Itaú | AQ6: Saidas | AR6: #REF!
B7: Transf. Lucila Regina Ceregato Correa | D7: -20600 | F7: =-D7 -> 20600 | AQ7: Saidas | AR7: #REF!
AP8: =#REF! -> #REF!
B9: Venda de Gasolina | J9: =-M9 -> 6171.75 | K9: -1055 | L9: 5.85 | M9: =K9*L9 -> -6171.75 | AP9: =#REF! -> #REF!
B10: Venda de Etanol | J10: =-P10 -> 9365.09 | N10: -2471 | O10: 3.79 | P10: =N10*O10 -> -9365.09 | AP10: =#REF! -> #REF!
B11: Separação Cartão/Outros | H11: =-J11-I11 -> 5287.86 | I11: 10248.98 | J11: =-SUM(J9:J10) -> -15536.84 | AO11: =A2 -> 0 | AP11: =#REF! -> #REF!
B12: Ajuste estoque e valor diário (lucro embutido) | K12: -159 | M12: =(K15*((M2)/(K2))-M2-M9) -> 54.018278 | N12: -126 | P12: =(N15*((P2)/(N2))-P2-P10) -> 292.13342 | AP12: =#REF! -> #REF!
AO13: =A3 -> 45962 | AP13: =#REF! -> #REF!
B14: Saldo Giro no dia | C14: =D15+E15+F15+G15+H15+I15+J15+M15+P15 -> 135963.78 | M14: =K14*L14 -> 0 | P14: =N14*O14 -> 0 | AO14: =SUM($Q2:AN14) -> -446041.91 | AS14: TERCEIROS
B15: Saldo Líquido do dia | C15: =AO15 -> -310078.13 | D15: =SUM(D2:D14) -> 65.74704 | E15: =SUM(E2:E14) -> -22339.08 | F15: =SUM(F2:F14) -> 20600 | G15: =SUM(G2:G14) -> 0 | H15: =SUM(H2:H14) -> 14687.86 | I15: =SUM(I2:I14) -> 10248.98 | J15: =SUM(J2:J14) -> 0 | K15: =SUM(K2:K14) -> 11303 | L15: =M15/K15 -> 5.0393179 | M15: =ROUND(SUM(M2:M14),2) -> 56959.41 | N15: =SUM(N2:N14) -> 15955 | O15: =P15/N15 -> 3.4936296 | P15: =ROUND(SUM(P2:P14),2) -> 55740.86 | Q15: =SUM(Q2:Q14) -> -423778.33 | R15: =SUM(R2:R14) -> 37928.52 | S15: =SUM(S2:S14) -> 0 | T15: =SUM(T2:T14) -> -12858.76 | U15: =SUM(U2:U14) -> -35100 | V15: =SUM(V2:V14) -> -12233.34 | W15: =SUM(W2:W14) -> 0 | X15: =SUM(X2:X14) -> 0 | ... AH15: =SUM(AH2:AH14) -> 0 | AJ15: =SUM(AJ2:AJ14) -> 0 | AK15: =SUM(AK2:AK14) -> 0 | AL15: =SUM(AL2:AL14) -> 0 | AM15: =SUM(AM2:AM14) -> 0 | AN15: =SUM(AN2:AN14) -> 0 | AO15: =D15+E15+F15+G15+H15+I15+J15+M15+P15+SUM(Q15:AN15) -> -310078.13 | AS15: SALDO C/C
A16: =A3+1 -> 45963 | B16: Credito Vendas Cartão | D16: 10001.27 | I16: =-D16 -> -10001.27 | AP16: =#REF! -> #REF!
B17: Desconto taxas Cartão | I17: =-I15-I16 -> -247.71
B18: Pix e depósitos Banco Itaú | R18: =-D18 -> 0
B19: Transf. Lucila Regina Ceregato Correa | D19: -10000 | F19: =-D19 -> 10000 | AQ19: Saidas | AR19: #REF!
AP20: =#REF! -> #REF!
B21: Venda de Gasolina | J21: =-M21 -> 5528.25 | K21: -945 | L21: 5.85 | M21: =K21*L21 -> -5528.25 | AP21: =#REF! -> #REF!
B22: Venda de Etanol | J22: =-P22 -> 5825.23 | N22: -1537 | O22: 3.79 | P22: =N22*O22 -> -5825.23 | AP22: =#REF! -> #REF!
B23: Separação Cartão/Outros | H23: =-J23-I23 -> 4815.04 | I23: 6538.44 | J23: =-SUM(J21:J22) -> -11353.48 | AP23: =#REF! -> #REF!
B24: Ajuste estoque e valor diário (lucro embutido) | K24: -26 | M24: =(K27*((M15)/(K15))-M15-M21) -> 635.07234 | N24: 82 | P24: =(N27*((P15)/(N15))-P15-P22) -> 741.99896 | AP24: =#REF! -> #REF!
AO25: =A16 -> 45963 | AP25: =#REF! -> #REF!
B26: Saldo Giro no dia | C26: =D27+E27+F27+G27+H27+I27+J27+M27+P27 -> 137093.14 | AO26: =SUM($Q15:AN26) -> -446041.91 | AS26: TERCEIROS
B27: Saldo Líquido do dia | C27: =AO27 -> -308948.77 | D27: =SUM(D15:D26) -> 67.01704 | E27: =SUM(E15:E26) -> -22339.08 | F27: =SUM(F15:F26) -> 30600 | G27: =SUM(G15:G26) -> 0 | H27: =SUM(H15:H26) -> 19502.9 | I27: =SUM(I15:I26) -> 6538.44 | J27: =SUM(J15:J26) -> 0 | K27: =SUM(K15:K26) -> 10332 | L27: =M27/K27 -> 5.0393177 | M27: =ROUND(SUM(M15:M26),2) -> 52066.23 | N27: =SUM(N15:N26) -> 14500 | O27: =P27/N27 -> 3.4936297 | P27: =ROUND(SUM(P15:P26),2) -> 50657.63 | Q27: =SUM(Q15:Q26) -> -423778.33 | R27: =SUM(R15:R26) -> 37928.52 | S27: =SUM(S15:S26) -> 0 | T27: =SUM(T15:T26) -> -12858.76 | U27: =SUM(U15:U26) -> -35100 | V27: =SUM(V15:V26) -> -12233.34 | W27: =SUM(W15:W26) -> 0 | X27: =SUM(X15:X26) -> 0 | ... AN27: =SUM(AN15:AN26) -> 0 | AO27: =D27+E27+F27+G27+H27+I27+J27+M27+P27+SUM(Q27:AN27) -> -308948.77 | AS27: SALDO C/C
A28: =A16+1 -> 45964 | B28: Credito Vendas Cartão | D28: 6358.67 | I28: =-D28 -> -6358.67
B29: Desconto taxas Cartão | I29: =-I27-I28 -> -179.77
B30: Transf. Lucila Regina Ceregato Correa | D30: -6400 | F30: =-D30 -> 6400 | AQ30: Saidas | AR30: #REF!
B31: Pix e depósitos Banco Itaú | E31: =-18952.16+64.89-E27 -> 3451.81 | H31: =-E31 -> -3451.81 | AQ31: Saidas | AR31: #REF!
B32: Conselho Regional | E32: -64.89
B33: Pag NF 109841 Avant 10x3,51 EH Venc 03/11 | F33: -35100 | U33: =-F33 -> 35100
B35: Venda de Gasolina | J35: =-M35 -> 7914.93 | K35: -1367 | L35: 5.79 | M35: =K35*L35 -> -7914.93 | AP35: =#REF! -> #REF!
B36: Venda de Etanol | J36: =-P36 -> 8273.57 | N36: -2183 | O36: 3.79 | P36: =N36*O36 -> -8273.57 | AP36: =#REF! -> #REF!
B37: Separação Cartão/Outros | H37: =-J37-I37 -> 5065.79 | I37: 11122.71 | J37: =-SUM(J35:J36) -> -16188.5 | AO37: =A18 -> 0 | AP37: =#REF! -> #REF!
B38: Ajuste de saldo e valor estoque diário | K38: 35 | M38: =(K41*((M27)/(K27))-M27-M35) -> 1202.5589 | N38: 3 | P38: =(N41*((P27)/(N27))-P27-P36) -> 657.45735 | AO38: =A17 -> 0 | AP38: =#REF! -> #REF!
B40: Saldo Giro no dia | C40: =D41+E41+F41+G41+H41+I41+J41+M41+P41 -> 103608.5 | AO40: =SUM($Q27:AN40) -> -410941.91 | AS40: TERCEIROS
B41: Saldo Líquido do dia | C41: =AO41 -> -307333.41 | D41: =SUM(D27:D40) -> 25.68704 | E41: =SUM(E27:E40) -> -18952.16 | F41: =SUM(F27:F40) -> 1900 | G41: =SUM(G27:G40) -> 0 | H41: =SUM(H27:H40) -> 21116.88 | I41: =SUM(I27:I40) -> 11122.71 | J41: =SUM(J27:J40) -> 0 | K41: =SUM(K27:K40) -> 9000 | L41: =M41/K41 -> 5.0393178 | M41: =ROUND(SUM(M27:M40),2) -> 45353.86 | N41: =SUM(N27:N40) -> 12320 | O41: =P41/N41 -> 3.4936299 | P41: =ROUND(SUM(P27:P40),2) -> 43041.52 | Q41: =SUM(Q27:Q40) -> -423778.33 | R41: =SUM(R27:R40) -> 37928.52 | S41: =SUM(S27:S40) -> 0 | T41: =SUM(T27:T40) -> -12858.76 | U41: =SUM(U27:U40) -> 0 | V41: =SUM(V27:V40) -> -12233.34 | W41: =SUM(W27:W40) -> 0 | X41: =SUM(X27:X40) -> 0 | ... AN41: =SUM(AN27:AN40) -> 0 | AO41: =D41+E41+F41+G41+H41+I41+J41+M41+P41+SUM(Q41:AN41) -> -307333.41 | AS41: SALDO C/C
A42: =A28+1 -> 45965 | B42: Credito Vendas Cartão | D42: 10857.77 | I42: =-D42 -> -10857.77
B43: Desconto taxas Cartão | I43: =-I41-I42 -> -264.94
B44: Transf. Lucila Regina Ceregato Correa | D44: -10800 | F44: =-D44 -> 10800 | AQ44: Saidas | AR44: #REF!
B45: Pix e depósitos Banco Itaú | E45: =-17958.79+232.07+92.5+18952.16 -> 1317.94 | H45: =-E45 -> -1317.94 | AQ45: Saidas | AR45: #REF!
B46: Tarifa pacote Itaú | E46: -92.5
B47: IOF | E47: -232.07
B49: Venda de Gasolina | J49: =-M49 -> 6943.95 | K49: -1187 | L49: 5.85 | M49: =K49*L49 -> -6943.95 | AP49: =#REF! -> #REF!
B50: Venda de Etanol | J50: =-P50 -> 8156.08 | N50: -2152 | O50: 3.79 | P50: =N50*O50 -> -8156.08 | AP50: =#REF! -> #REF!
B51: Separação Cartão/Outros | H51: =-J51-I51 -> 5443.04 | I51: 9656.99 | J51: =-SUM(J49:J50) -> -15100.03 | AP51: =#REF! -> #REF!
B52: Ajuste de saldo e valor estoque diário | K52: -55 | M52: =(K55*((M41)/(K41))-M41-M49) -> 685.11732 | N52: -132 | P52: =(N55*((P41)/(N41))-P41-P50) -> 176.62938 | AO52: =A27 -> 0 | AP52: =#REF! -> #REF!
AO53: =A42 -> 45965
B54: Saldo Giro no dia | C54: =D55+E55+F55+G55+H55+I55+J55+M55+P55 -> 103880.74 | AO54: =SUM($Q41:AN54) -> -410941.91 | AS54: TERCEIROS
B55: Saldo Líquido do dia | C55: =AO55 -> -307061.17 | D55: =SUM(D41:D54) -> 83.45704 | E55: =SUM(E41:E54) -> -17958.79 | F55: =SUM(F41:F54) -> 12700 | G55: =SUM(G41:G54) -> 0 | H55: =SUM(H41:H54) -> 25241.98 | I55: =SUM(I41:I54) -> 9656.99 | J55: =SUM(J41:J54) -> 0 | K55: =SUM(K41:K54) -> 7758 | L55: =M55/K55 -> 5.0393181 | M55: =ROUND(SUM(M41:M54),2) -> 39095.03 | N55: =SUM(N41:N54) -> 10036 | O55: =P55/N55 -> 3.4936299 | P55: =ROUND(SUM(P41:P54),2) -> 35062.07 | Q55: =SUM(Q41:Q54) -> -423778.33 | R55: =SUM(R41:R54) -> 37928.52 | S55: =SUM(S41:S54) -> 0 | T55: =SUM(T41:T54) -> -12858.76 | U55: =SUM(U41:U54) -> 0 | V55: =SUM(V41:V54) -> -12233.34 | W55: =SUM(W41:W54) -> 0 | X55: =SUM(X41:X54) -> 0 | ... AN55: =SUM(AN41:AN54) -> 0 | AO55: =D55+E55+F55+G55+H55+I55+J55+M55+P55+SUM(Q55:AN55) -> -307061.17 | AS55: SALDO C/C
A56: =A42+1 -> 45966 | B56: Credito Vendas Cartão | D56: 9460.31 | I56: =-D56 -> -9460.31
B57: Desconto taxas Cartão | I57: =-I55-I56 -> -196.68
B58: Transf. Lucila Regina Ceregato Correa | D58: -9500 | F58: =-D58 -> 9500 | AQ58: Saidas | AR58: #REF!
B59: Pix Arquivo Claro | D59: 360.1 | H59: =-D59 -> -360.1 | AQ59: Saidas | AR59: #REF!
B60: Tarifa pix Arquivo Claro | D60: -2.88 | AQ60: Saidas | AR60: #REF!
B61: Pix e depósitos Banco Itaú | E61: =-20651.02+3214.69+227.53+1366.01+17958.79 -> 2116 | H61: =-E61 -> -2116 | AQ61: Saidas | AR61: #REF!
B62: Pag Elektro | E62: -227.53
B63: Pag Unimed | E63: -1366.01
B64: Crediario Emprestimo 3/6 parcelas 3.214,69 | E64: =-1141.12-5-50-700-20.7-20-20-50-100-170-30-50-50-25-50-732.87 -> -3214.69 | M64: =K64*L64 -> 0 | P64: =N64*O64 -> 0 | T64: =-E64 -> 3214.69 | AQ64: Saidas | AR64: #REF!
B65: Cesta básica (dinheiro) | H65: -791.28
B66: Vale refeição 5x767,00 | H66: -3835
B68: Venda de Gasolina | J68: =-M68 -> 6142.5 | K68: -1050 | L68: 5.85 | M68: =K68*L68 -> -6142.5 | AP68: =#REF! -> #REF!
B69: Venda de Etanol | J69: =-P69 -> 9285.5 | N69: -2450 | O69: 3.79 | P69: =N69*O69 -> -9285.5 | AP69: =#REF! -> #REF!
B70: Separação Cartão/Outros | H70: =-J70-I70 -> 5750.3 | I70: 9677.7 | J70: =-SUM(J68:J69) -> -15428 | AP70: =#REF! -> #REF!
B71: Ajuste de saldo e valor estoque diário | K71: 49 | M71: =(K74*((M55)/(K55))-M55-M68) -> 1098.1426 | N71: -36 | P71: =(N74*((P55)/(N55))-P55-P69) -> 600.33599 | AO71: =A43 -> 0 | AP71: =#REF! -> #REF!
AO72: =A56 -> 45966
B73: Saldo Giro no dia | C73: =D74+E74+F74+G74+H74+I74+J74+M74+P74 -> 95945.147 | AO73: =SUM($Q55:AN73) -> -407727.22 | AS73: TERCEIROS
B74: Saldo Líquido do dia | C74: =AO74 -> -311782.07 | D74: =SUM(D55:D73) -> 400.98704 | E74: =SUM(E55:E73) -> -20651.02 | F74: =SUM(F55:F73) -> 22200 | G74: =SUM(G55:G73) -> 0 | H74: =SUM(H55:H73) -> 23889.9 | I74: =SUM(I55:I73) -> 9677.7 | J74: =SUM(J55:J73) -> 0 | K74: =SUM(K55:K73) -> 6757 | L74: =M74/K74 -> 5.0393177 | M74: =ROUND(SUM(M55:M73),2) -> 34050.67 | N74: =SUM(N55:N73) -> 7550 | O74: =P74/N74 -> 3.4936305 | P74: =ROUND(SUM(P55:P73),2) -> 26376.91 | Q74: =SUM(Q55:Q73) -> -423778.33 | R74: =SUM(R55:R73) -> 37928.52 | S74: =SUM(S55:S73) -> 0 | T74: =SUM(T55:T73) -> -9644.07 | U74: =SUM(U55:U73) -> 0 | V74: =SUM(V55:V73) -> -12233.34 | W74: =SUM(W55:W73) -> 0 | X74: =SUM(X55:X73) -> 0 | ... AN74: =SUM(AN55:AN73) -> 0 | AO74: =D74+E74+F74+G74+H74+I74+J74+M74+P74+SUM(Q74:AN74) -> -311782.07 | AS74: SALDO C/C
A75: =A56+1 -> 45967 | B75: Credito Vendas Cartão | D75: 9447.55 | I75: =-D75 -> -9447.55
B76: Desconto taxas Cartão | I76: =-I74-I75 -> -230.15
B77: Transf. Lucila Regina Ceregato Correa | D77: -9800 | F77: =-D77 -> 9800 | AQ77: Saidas | AR77: #REF!
B78: Pix e depósitos Banco Itaú | E78: =-E74-18420.95 -> 2230.07 | H78: =-E78 -> -2230.07 | AQ78: Saidas | AR78: #REF!
B79: Transf. Lucila Regina Ceregato Correa | AQ79: Saidas | AR79: #REF!
B80: Pag boleto WL NF 93745 3/3 VENC 26/09 | F80: -12233.34 | V80: =-F80 -> 12233.34
B82: Venda de Gasolina | J82: =-M82 -> 8488.35 | K82: -1451 | L82: 5.85 | M82: =K82*L82 -> -8488.35 | AP82: =#REF! -> #REF!
B83: Venda de Etanol | J83: =-P83 -> 10797.71 | N83: -2849 | O83: 3.79 | P83: =N83*O83 -> -10797.71 | AP83: =#REF! -> #REF!
B84: Separação Cartão/Outros | H84: =-J84-I84 -> 8360.96 | I84: 10925.1 | J84: =-SUM(J82:J83) -> -19286.06 | AP84: =#REF! -> #REF!
B85: Ajuste de saldo e valor estoque diário | K85: -17 | M85: =(K88*((M74)/(K74))-M74-M82) -> 1090.6316 | N85: -1 | P85: =(N88*((P74)/(N74))-P74-P83) -> 840.86318 | AP85: =#REF! -> #REF!
AO86: =A75 -> 45967
B87: Saldo Giro no dia | C87: =D88+E88+F88+G88+H88+I88+J88+M88+P88 -> 85413.147 | AO87: =SUM($Q74:AN87) -> -395493.88 | AS87: TERCEIROS
B88: Saldo Líquido do dia | C88: =AO88 -> -310080.73 | D88: =SUM(D74:D87) -> 48.53704 | E88: =SUM(E74:E87) -> -18420.95 | F88: =SUM(F74:F87) -> 19766.66 | G88: =SUM(G74:G87) -> 0 | H88: =SUM(H74:H87) -> 30020.79 | I88: =SUM(I74:I87) -> 10925.1 | J88: =SUM(J74:J87) -> 0 | K88: =SUM(K74:K87) -> 5289 | L88: =M88/K88 -> 5.0393175 | M88: =ROUND(SUM(M74:M87),2) -> 26652.95 | N88: =SUM(N74:N87) -> 4700 | O88: =P88/N88 -> 3.4936298 | P88: =ROUND(SUM(P74:P87),2) -> 16420.06 | Q88: =SUM(Q74:Q87) -> -423778.33 | R88: =SUM(R74:R87) -> 37928.52 | S88: =SUM(S74:S87) -> 0 | T88: =SUM(T74:T87) -> -9644.07 | U88: =SUM(U74:U87) -> 0 | V88: =SUM(V74:V87) -> 0 | W88: =SUM(W74:W87) -> 0 | X88: =SUM(X74:X87) -> 0 | ... AN88: =SUM(AN74:AN87) -> 0 | AO88: =D88+E88+F88+G88+H88+I88+J88+M88+P88+SUM(Q88:AN88) -> -310080.73 | AS88: SALDO C/C
A89: =A75+1 -> 45968 | B89: Credito Vendas Cartão | D89: 10682.22 | I89: =-D89 -> -10682.22
B90: Desconto taxas Cartão | I90: =-I88-I89 -> -242.88
B91: Transf. Lucila Regina Ceregato Correa | D91: -10700 | F91: =-D91 -> 10700 | AQ91: Saidas | AR91: #REF!
B92: Transf. Lucila Regina Ceregato Correa | D92: 25435 | F92: =-D92 -> -25435 | AQ92: Saidas | AR92: #REF!
B93: Transf. Lucila Regina Ceregato Correa | D93: 5031.66 | F93: =-D93 -> -5031.66 | AQ93: Saidas | AR93: #REF!
B94: Pix Eraldo | D94: 6550 | Q94: =-D94 -> -6550 | AQ94: Saidas | AR94: #REF!
B95: Tarifa pix recebido 6550,00 | D95: -52.4 | AQ95: Saidas | AR95: #REF!
B96: Pix e depósitos Banco Itaú | E96: =-E88-10347.46+14000+5 -> 22078.49 | H96: =-E96 -> -22078.49 | AQ96: Saidas | AR96: #REF!
B97: Transf. Banco Itau | D97: 14000 | E97: -14000 | AQ97: Saidas | AR97: #REF!
B98: Tarifa pix recebido 14000,00 | D98: -112 | AQ98: Saidas | AR98: #REF!
B99: Transf. Banco Itau | D99: 5 | E99: -5 | AQ99: Saidas | AR99: #REF!
B100: Tarifa pix recebido 5,00 | D100: -0.99 | AQ100: Saidas | AR100: #REF!
B101: NF 42916 SIM GC 10x5,0879 | D101: =-M101 -> -50879 | K101: 10000 | L101: 5.0879 | M101: =K101*L101 -> 50879 | U101: =-P101 -> 0
B102: Tarifa envio pix SIM | D102: -4.9 | AQ102: Saidas | AR102: #REF!
B104: Venda de Gasolina | J104: =-M104 -> 6791.85 | K104: -1161 | L104: 5.85 | M104: =K104*L104 -> -6791.85 | AP104: =#REF! -> #REF!
B105: Venda de Etanol | J105: =-P105 -> 10983.42 | N105: -2898 | O105: 3.79 | P105: =N105*O105 -> -10983.42 | AP105: =#REF! -> #REF!
B106: Separação Cartão/Outros | H106: =-J106-I106 -> 5135.22 | I106: 12640.05 | J106: =-SUM(J104:J105) -> -17775.27 | AP106: =#REF! -> #REF!
...

Sheet Dez25
A1: PERÍODO 01 á 31/DEZ/25 | C1: =D2+E2+F2+G2+H2+I2+J2+M2+P2 -> 119457.56 | D1: SPOT | E1: ITAU | F1: LUCILA | G1: HADEN | H1: CAIXA | I1: CARTAO | J1: VENDAS | K1: GASOLINA | N1: ETANOL | Q1: ERALDO | R1: LUIZ F. | S1: LUCILA | T1: DIVIDA | U1: AVANT | V1: WL | AO1: Total | AP1: Saldo Total | AQ1: Saldo Edson | AR1: Saldo Master
B2: Saldo Inicial do dia | C2: =D2+E2+F2+G2+H2+I2+J2+M2+P2+SUM(Q2:AN2) -> -303063.44 | D2: ='Nov25'!D443 -> 23.65704 | E2: ='Nov25'!E443 -> -19624.86 | F2: ='Nov25'!F443 -> 26680 | G2: ='Nov25'!G443 -> 0 | H2: ='Nov25'!H443 -> 48361.543 | I2: ='Nov25'!I443 -> 8718.39 | J2: ='Nov25'!J443 -> 0 | K2: ='Nov25'!K443 -> 6757 | ... AO2: ='Nov25'!AO443 -> -303063.44 | AP2: =#REF! -> #REF! | AQ2: =#REF! -> #REF! | AR2: =AP2-AQ2 -> #REF!
A3: 45992 | B3: Credito Vendas Cartão | D3: 8509.07 | I3: =-D3 -> -8509.07 | AQ3: Saidas | AR3: #REF!
B4: Desconto taxas Cartão | I4: =-I2-I3 -> -209.32 | AQ4: Saidas | AR4: #REF!
B5: Transf. Lucila Regina Ceregato Correa | D5: -8500 | F5: =-D5 -> 8500 | AQ5: Saidas | AR5: #REF!
B6: Transf. Itau p/ Spotbank | D6: 1300 | E6: =-D6 -> -1300 | AQ6: Saidas | AR6: #REF!
B7: Tarifa recebimento pix | D7: -10.4 | AQ7: Saidas | AR7: #REF!
B8: Transf. Lucila Regina Ceregato Correa | D8: 35180 | F8: =-D8 -> -35180 | AQ8: Saidas | AR8: #REF!
B9: Pag NF 98565 Petroriente 10x3,63 EH | D9: -36300 | V9: =-D9 -> 36300
B10: Pix e depósitos Banco Itaú | E10: =-E2+1300-10141.86+550.81 -> 11333.81 | H10: =-E10 -> -11333.81 | AQ10: Saidas | AR10: #REF!
B11: Pag DARF | E11: -550.81
AQ12: Saidas | AR12: #REF!
AP13: =#REF! -> #REF!
B14: Venda de Gasolina | J14: =-M14 -> 8862.75 | K14: -1515 | L14: 5.85 | M14: =K14*L14 -> -8862.75 | AP14: =#REF! -> #REF!
B15: Venda de Etanol | J15: =-P15 -> 9692.89 | N15: -2479 | O15: 3.91 | P15: =N15*O15 -> -9692.89 | AP15: =#REF! -> #REF!
B16: Separação Cartão/Outros | H16: =-J16-I16 -> 6933.26 | I16: 11622.38 | J16: =-SUM(J14:J15) -> -18555.64 | AO16: =A2 -> 0 | AP16: =#REF! -> #REF!
B17: Ajuste estoque e valor diário (lucro embutido) | K17: 47 | M17: =(K20*L2)-M2-M14 -> 1460.5474 | N17: 80 | P17: =(N20*((P2)/(N2))-P2-P15) -> 1046.9103 | AP17: =#REF! -> #REF!
AO18: =A3 -> 45992 | AP18: =#REF! -> #REF!
B19: Saldo Giro no dia | C19: =D20+E20+F20+G20+H20+I20+J20+M20+P20 -> 84894.49 | M19: =K19*L19 -> 0 | P19: =N19*O19 -> 0 | AO19: =SUM($Q2:AN19) -> -386221 | AS19: TERCEIROS
B20: Saldo Líquido do dia | C20: =AO20 -> -301326.51 | D20: =SUM(D2:D19) -> 202.32704 | E20: =SUM(E2:E19) -> -10141.86 | F20: =SUM(F2:F19) -> 0 | G20: =SUM(G2:G19) -> 0 | H20: =SUM(H2:H19) -> 43960.993 | I20: =SUM(I2:I19) -> 11622.38 | J20: =SUM(J2:J19) -> 0 | K20: =SUM(K2:K19) -> 5289 | L20: =M20/K20 -> 5.0423728 | M20: =ROUND(SUM(M2:M19),2) -> 26669.11 | N20: =SUM(N2:N19) -> 3491 | O20: =P20/N20 -> 3.6039931 | P20: =ROUND(SUM(P2:P19),2) -> 12581.54 | Q20: =SUM(Q2:Q19) -> -426806.23 | R20: =SUM(R2:R19) -> 50229.3 | S20: =SUM(S2:S19) -> 0 | T20: =SUM(T2:T19) -> -9644.07 | U20: =SUM(U2:U19) -> 0 | V20: =SUM(V2:V19) -> 0 | W20: =SUM(W2:W19) -> 0 | X20: =SUM(X2:X19) -> 0 | ... AH20: =SUM(AH2:AH19) -> 0 | AJ20: =SUM(AJ2:AJ19) -> 0 | AK20: =SUM(AK2:AK19) -> 0 | AL20: =SUM(AL2:AL19) -> 0 | AM20: =SUM(AM2:AM19) -> 0 | AN20: =SUM(AN2:AN19) -> 0 | AO20: =D20+E20+F20+G20+H20+I20+J20+M20+P20+SUM(Q20:AN20) -> -301326.51 | AS20: SALDO C/C
A21: =A3+1 -> 45993 | B21: Credito Vendas Cartão | D21: 11328.94 | I21: =-D21 -> -11328.94 | AP21: =#REF! -> #REF!
B22: Desconto taxas Cartão | I22: =-I20-I21 -> -293.44
B23: Pix e depósitos Banco Itaú | E23: =-E20-8223.89+92.5+232.01+388.81+244.4+1671 -> 4546.69 | H23: =-E23 -> -4546.69 | R23: =-D23 -> 0
B24: Tarifa pacote | E24: -92.5
B25: IOF | E25: -232.01
B26: Pag Elektro (casa)
B27: Pag Juliano Araujo | D27: -488
B28: Tarifa pix Juliano Araujo | D28: -4.9 | AQ28: Saidas | AR28: #REF!
B29: Pag DAAE | E29: -388.81
B30: Pag Elektro | E30: -244.4
B31: Transf. p/ Eraldo | E31: -1671 | Q31: =-E31 -> 1671
AP34: =#REF! -> #REF!
B35: Venda de Gasolina | J35: =-M35 -> 7610.85 | K35: -1301 | L35: 5.85 | M35: =K35*L35 -> -7610.85 | AP35: =#REF! -> #REF!
B36: Venda de Etanol | J36: =-P36 -> 7260.87 | N36: -1857 | O36: 3.91 | P36: =N36*O36 -> -7260.87 | AP36: =#REF! -> #REF!
B37: Separação Cartão/Outros | H37: =-J37-I37 -> 4787.27 | I37: 10084.45 | J37: =-SUM(J35:J36) -> -14871.72 | AP37: =#REF! -> #REF!
B38: Ajuste estoque e valor diário (lucro embutido) | K38: 4 | M38: =(K41*L20)-M20-M35 -> 1070.8924 | N38: 140 | P38: =(N41*O20)-P20-P36 -> 1072.8138 | AP38: =#REF! -> #REF!
AO39: =A21 -> 45993 | AP39: =#REF! -> #REF!
B40: Saldo Giro no dia | C40: =D41+E41+F41+G41+H41+I41+J41+M41+P41 -> 83623.13 | AO40: =SUM($Q20:AN40) -> -384550 | AS40: TERCEIROS
B41: Saldo Líquido do dia | C41: =AO41 -> -300926.87 | D41: =SUM(D20:D40) -> 11038.367 | E41: =SUM(E20:E40) -> -8223.89 | F41: =SUM(F20:F40) -> 0 | G41: =SUM(G20:G40) -> 0 | H41: =SUM(H20:H40) -> 44201.573 | I41: =SUM(I20:I40) -> 10084.45 | J41: =SUM(J20:J40) -> 0 | K41: =SUM(K20:K40) -> 3992 | L41: =M41/K41 -> 5.0423722 | M41: =ROUND(SUM(M20:M40),2) -> 20129.15 | N41: =SUM(N20:N40) -> 1774 | O41: =P41/N41 -> 3.603991 | P41: =ROUND(SUM(P20:P40),2) -> 6393.48 | Q41: =SUM(Q20:Q40) -> -425135.23 | R41: =SUM(R20:R40) -> 50229.3 | S41: =SUM(S20:S40) -> 0 | T41: =SUM(T20:T40) -> -9644.07 | U41: =SUM(U20:U40) -> 0 | V41: =SUM(V20:V40) -> 0 | W41: =SUM(W20:W40) -> 0 | X41: =SUM(X20:X40) -> 0 | ... AN41: =SUM(AN20:AN40) -> 0 | AO41: =D41+E41+F41+G41+H41+I41+J41+M41+P41+SUM(Q41:AN41) -> -300926.87 | AS41: SALDO C/C
A42: =A21+1 -> 45994 | B42: Credito Vendas Cartão | D42: 9833.36 | I42: =-D42 -> -9833.36
B43: Desconto taxas Cartão | I43: =-I41-I42 -> -251.09
B44: Transf. Itau p/ Spotbank | D44: 31000 | E44: =-D44 -> -31000 | AQ44: Saidas | AR44: #REF!
B45: Tarifa recebimento pix | D45: -248 | AQ45: Saidas | AR45: #REF!
B46: Pix e depósitos Banco Itaú | E46: =-E41-37567.49+31000 -> 1656.4 | H46: =-E46 -> -1656.4 | R46: =-D46 -> 0
B47: Pix e depósitos Banco Itaú - Lucila
B48: Pix EDL
B49: Pag Papirus
B50: NF 44557 SIM 10x5,06 GC (pago pelo posto) | D50: =-M50 -> -50600 | K50: 10000 | L50: 5.06 | M50: =K50*L50 -> 50600 | U50: =-P50 -> 0
B51: NF 99643 SIM 10x3,66 EH (WL VENC 08/12) | D51: =-M51 -> 0 | N51: 10000 | O51: 3.66 | P51: =N51*O51 -> 36600 | V51: =-P51 -> -36600
B52: Tarifa pix enviado | D52: -4.9 | U52: =-P52 -> 0 | AQ52: Saidas | AR52: #REF!
U53: =-P53 -> 0
B54: Venda de Gasolina | J54: =-M54 -> 8353.8 | K54: -1428 | L54: 5.85 | M54: =K54*L54 -> -8353.8 | AP54: =#REF! -> #REF!
B55: Venda de Etanol | J55: =-P55 -> 11292.08 | N55: -2888 | O55: 3.91 | P55: =N55*O55 -> -11292.08 | AP55: =#REF! -> #REF!
B56: Separação Cartão/Outros | H56: =-J56-I56 -> 6843.19 | I56: 12802.69 | J56: =-SUM(J54:J55) -> -19645.88 | AO56: =A23 -> 0 | AP56: =#REF! -> #REF!
B57: Ajuste de saldo e valor estoque diário | K57: 58 | M57: =(K60*((M41+M50)/(K41+K50)))-M41-M54-M50 -> 1428.4901 | N57: -36 | P57: =(N60*((P41+P51)/(N41+N51)))-P41-P55-P51 -> 614.91544 | AO57: =A22 -> 0 | AP57: =#REF! -> #REF!
B59: Saldo Giro no dia | C59: =D60+E60+F60+G60+H60+I60+J60+M60+P60 -> 121762.55 | AO59: =SUM($Q41:AN59) -> -421150 | AS59: TERCEIROS
B60: Saldo Líquido do dia | C60: =AO60 -> -299387.45 | D60: =SUM(D41:D59) -> 1018.827 | E60: =SUM(E41:E59) -> -37567.49 | F60: =SUM(F41:F59) -> 0 | G60: =SUM(G41:G59) -> 0 | H60: =SUM(H41:H59) -> 49388.362 | I60: =SUM(I41:I59) -> 12802.69 | J60: =SUM(J41:J59) -> 0 | K60: =SUM(K41:K59) -> 12622 | L60: =M60/K60 -> 5.0549707 | M60: =ROUND(SUM(M41:M59),2) -> 63803.84 | N60: =SUM(N41:N59) -> 8850 | O60: =P60/N60 -> 3.6515616 | P60: =ROUND(SUM(P41:P59),2) -> 32316.32 | Q60: =SUM(Q41:Q59) -> -425135.23 | R60: =SUM(R41:R59) -> 50229.3 | S60: =SUM(S41:S59) -> 0 | T60: =SUM(T41:T59) -> -9644.07 | U60: =SUM(U41:U59) -> 0 | V60: =SUM(V41:V59) -> -36600 | W60: =SUM(W41:W59) -> 0 | X60: =SUM(X41:X59) -> 0 | ... AN60: =SUM(AN41:AN59) -> 0 | AO60: =D60+E60+F60+G60+H60+I60+J60+M60+P60+SUM(Q60:AN60) -> -299387.45 | AS60: SALDO C/C
A61: =A42+1 -> 45995 | B61: Credito Vendas Cartão | D61: 12501.48 | I61: =-D61 -> -12501.48
B62: Desconto taxas Cartão | I62: =-I60-I61 -> -301.21
B63: Pix e depósitos Banco Itaú | E63: =104+52+1462+1980+67+974+100+1000+15+40+150+9+60 -> 6013 | H63: =-E63 -> -6013 | R63: =-D63 -> 0
B66: Venda de Gasolina | J66: =-M66 -> 7710.3 | K66: -1318 | L66: 5.85 | M66: =K66*L66 -> -7710.3 | AP66: =#REF! -> #REF!
B67: Venda de Etanol | J67: =-P67 -> 9446.56 | N67: -2416 | O67: 3.91 | P67: =N67*O67 -> -9446.56 | AP67: =#REF! -> #REF!
B68: Separação Cartão/Outros | H68: =-J68-I68 -> 5987.46 | I68: 11169.4 | J68: =-SUM(J66:J67) -> -17156.86 | AP68: =#REF! -> #REF!
B69: Ajuste de saldo e valor estoque diário | K69: -21 | M69: =(K72*((M60)/(K60)))-M60-M66 -> 941.69425 | N69: -138 | P69: =(N72*((P60)/(N60)))-P60-P67 -> 120.47172 | AO69: =A41 -> 0 | AP69: =#REF! -> #REF!
AO70: =A61 -> 45995
B71: Saldo Giro no dia | C71: =D72+E72+F72+G72+H72+I72+J72+M72+P72 -> 122523.5 | AO71: =SUM($Q60:AN71) -> -421150 | AS71: TERCEIROS
B72: Saldo Líquido do dia | C72: =AO72 -> -298626.5 | D72: =SUM(D60:D71) -> 13520.307 | E72: =SUM(E60:E71) -> -31554.49 | F72: =SUM(F60:F71) -> 0 | G72: =SUM(G60:G71) -> 0 | H72: =SUM(H60:H71) -> 49362.822 | I72: =SUM(I60:I71) -> 11169.4 | J72: =SUM(J60:J71) -> 0 | K72: =SUM(K60:K71) -> 11283 | L72: =M72/K72 -> 5.0549703 | M72: =ROUND(SUM(M60:M71),2) -> 57035.23 | N72: =SUM(N60:N71) -> 6296 | O72: =P72/N72 -> 3.6515613 | P72: =ROUND(SUM(P60:P71),2) -> 22990.23 | Q72: =SUM(Q60:Q71) -> -425135.23 | R72: =SUM(R60:R71) -> 50229.3 | S72: =SUM(S60:S71) -> 0 | T72: =SUM(T60:T71) -> -9644.07 | U72: =SUM(U60:U71) -> 0 | V72: =SUM(V60:V71) -> -36600 | W72: =SUM(W60:W71) -> 0 | X72: =SUM(X60:X71) -> 0 | ... AN72: =SUM(AN60:AN71) -> 0 | AO72: =D72+E72+F72+G72+H72+I72+J72+M72+P72+SUM(Q72:AN72) -> -298626.5 | AS72: SALDO C/C
A73: =A61+1 -> 45996 | B73: Credito Vendas Cartão | D73: 10919 | I73: =-D73 -> -10919
B74: Desconto taxas Cartão | I74: =-I72-I73 -> -250.4
B75: Pix Jonatas Souza | D75: -800 | AQ75: Saidas | AR75: #REF!
B76: Tarifa pix enviado | D76: -4.9 | AQ76: Saidas | AR76: #REF!
B77: Pix e depósitos Banco Itaú | E77: =30+929.95+150+100+50+40+20.12+50+181+20+50+100+53+50+30+122+50+165+50+205.5+35+1000+30+20+20+50+20+100+100+120+150+50 -> 4141.57 | H77: =-E77 -> -4141.57 | R77: =-D77 -> 0
B78: Retirada Eraldo | E78: -1588.96 | R78: =-D78 -> 0
B79: Retirada Luiz Fernando | E79: -1588.96 | R79: =-D79 -> 0
B80: Crediario Emprestimo 4/6 parcelas 3.214,69 | E80: =-1141.12-5-50-700-20.7-20-20-50-100-170-30-50-50-25-50-732.87 -> -3214.69 | M80: =K80*L80 -> 0 | P80: =N80*O80 -> 0 | T80: =-E80 -> 3214.69 | AQ80: Saidas | AR80: #REF!
B81: Cesta básica (dinheiro) | H81: -791.28
B82: Vale refeição 5x767,00 | H82: -3835
B83: NF 561959 10x3,66 EH (reembolso 08/12) | D83: =-M83 -> 0 | N83: 10000 | O83: 3.66 | P83: =N83*O83 -> 36600 | Q83: =-P83 -> -36600
B84: NF 562278 10x3,64 EH (reembolso 10/12) | D84: =-M84 -> 0 | N84: 10000 | O84: 3.64 | P84: =N84*O84 -> 36400 | Q84: =-P84 -> -36400
B86: Venda de Gasolina | J86: =-M86 -> 9822.15 | K86: -1679 | L86: 5.85 | M86: =K86*L86 -> -9822.15 | AP86: =#REF! -> #REF!
B87: Venda de Etanol | J87: =-P87 -> 11022.29 | N87: -2819 | O87: 3.91 | P87: =N87*O87 -> -11022.29 | AP87: =#REF! -> #REF!
B88: Separação Cartão/Outros | H88: =-J88-I88 -> 7077.53 | I88: 13766.91 | J88: =-SUM(J86:J87) -> -20844.44 | AP88: =#REF! -> #REF!
B89: Ajuste de saldo e valor estoque diário | K89: 14 | M89: =(K92*((M72)/(K72)))-M72-M86 -> 1405.6244 | N89: 165 | P89: =(N92*((P72+P83+P84)/(N72+N83+N84)))-P72-P87-P83-P84 -> 1334.1979 | AO89: =A62 -> 0 | AP89: =#REF! -> #REF!
AO90: =A73 -> 45996
B91: Saldo Giro no dia | C91: =D92+E92+F92+G92+H92+I92+J92+M92+P92 -> 186189.13 | AO91: =SUM($Q72:AN91) -> -490935.31 | AS91: TERCEIROS
B92: Saldo Líquido do dia | C92: =AO92 -> -304746.18 | D92: =SUM(D72:D91) -> 23634.407 | E92: =SUM(E72:E91) -> -33805.53 | F92: =SUM(F72:F91) -> 0 | G92: =SUM(G72:G91) -> 0 | H92: =SUM(H72:H91) -> 47672.503 | I92: =SUM(I72:I91) -> 13766.91 | J92: =SUM(J72:J91) -> 0 | K92: =SUM(K72:K91) -> 9618 | L92: =M92/K92 -> 5.0549698 | M92: =ROUND(SUM(M72:M91),2) -> 48618.7 | N92: =SUM(N72:N91) -> 23642 | O92: =P92/N92 -> 3.6503739 | P92: =ROUND(SUM(P72:P91),2) -> 86302.14 | Q92: =SUM(Q72:Q91) -> -498135.23 | R92: =SUM(R72:R91) -> 50229.3 | S92: =SUM(S72:S91) -> 0 | T92: =SUM(T72:T91) -> -6429.38 | U92: =SUM(U72:U91) -> 0 | V92: =SUM(V72:V91) -> -36600 | W92: =SUM(W72:W91) -> 0 | X92: =SUM(X72:X91) -> 0 | ... AN92: =SUM(AN72:AN91) -> 0 | AO92: =D92+E92+F92+G92+H92+I92+J92+M92+P92+SUM(Q92:AN92) -> -304746.18 | AS92: SALDO C/C
A93: =A73+1 -> 45997 | B93: Credito Vendas Cartão | D93: 13437.98 | I93: =-D93 -> -13437.98
B94: Desconto taxas Cartão | I94: =-I92-I93 -> -328.93
B95: Transf. Lucila Regina Ceregato Correa | D95: -37000 | F95: =-D95 -> 37000 | AQ95: Saidas | AR95: #REF!
B98: Venda de Gasolina | J98: =-M98 -> 8851.05 | K98: -1513 | L98: 5.85 | M98: =K98*L98 -> -8851.05 | AP98: =#REF! -> #REF!
B99: Venda de Etanol | J99: =-P99 -> 10717.31 | N99: -2741 | O99: 3.91 | P99: =N99*O99 -> -10717.31 | AP99: =#REF! -> #REF!
B100: Separação Cartão/Outros | H100: =-J100-I100 -> 5318.17 | I100: 14250.19 | J100: =-SUM(J98:J99) -> -19568.36 | AP100: =#REF! -> #REF!
B101: Ajuste de saldo e valor estoque diário | K101: -35 | M101: =(K104*M92/K92)-M92-M98 -> 1025.9567 | N101: -205 | P101: =(N104*P92/N92)-P92-P99 -> -36.691541 | AO101: =A75 -> 0 | AP101: =#REF! -> #REF!
AO102: =A93 -> 45997
B103: Saldo Giro no dia | C103: =D104+E104+F104+G104+H104+I104+J104+M104+P104 -> 186849.47 | AO103: =SUM($Q92:AN103) -> -490935.31 | AS103: TERCEIROS
B104: Saldo Líquido do dia | C104: =AO104 -> -304085.84 | D104: =SUM(D92:D103) -> 72.38704 | E104: =SUM(E92:E103) -> -33805.53 | F104: =SUM(F92:F103) -> 37000 | G104: =SUM(G92:G103) -> 0 | H104: =SUM(H92:H103) -> 52990.673 | I104: =SUM(I92:I103) -> 14250.19 | J104: =SUM(J92:J103) -> 0 | K104: =SUM(K92:K103) -> 8070 | L104: =M104/K104 -> 5.0549703 | M104: =ROUND(SUM(M92:M103),2) -> 40793.61 | N104: =SUM(N92:N103) -> 20696 | O104: =P104/N104 -> 3.650374 | P104: =ROUND(SUM(P92:P103),2) -> 75548.14 | Q104: =SUM(Q92:Q103) -> -498135.23 | R104: =SUM(R92:R103) -> 50229.3 | S104: =SUM(S92:S103) -> 0 | T104: =SUM(T92:T103) -> -6429.38 | U104: =SUM(U92:U103) -> 0 | V104: =SUM(V92:V103) -> -36600 | W104: =SUM(W92:W103) -> 0 | X104: =SUM(X92:X103) -> 0 | ... AN104: =SUM(AN92:AN103) -> 0 | AO104: =D104+E104+F104+G104+H104+I104+J104+M104+P104+SUM(Q104:AN104) -> -304085.84 | AS104: SALDO C/C
A105: =A93+1 -> 45998 | B105: Credito Vendas Cartão | D105: 13929.78 | I105: =-D105 -> -13929.78
B106: Desconto taxas Cartão | I106: =-I104-I105 -> -320.41
B107: Transf. Lucila Regina Ceregato Correa | D107: -13900 | F107: =-D107 -> 13900 | AQ107: Saidas | AR107: #REF!
B109: Venda de Gasolina | J109: =-M109 -> 5335.2 | K109: -912 | L109: 5.85 | M109: =K109*L109 -> -5335.2 | AP109: =#REF! -> #REF!
...

Sheet Jan26
A1: PERÍODO 01 á 31/JAN/26 | C1: =D2+E2+F2+G2+H2+I2+J2+M2+P2 -> 153061.83 | D1: SPOT | E1: ITAU | F1: LUCILA | G1: HADEN | H1: CAIXA | I1: CARTAO | J1: VENDAS | K1: GASOLINA | N1: ETANOL | Q1: ERALDO | R1: LUIZ F. | S1: LUCILA | T1: DIVIDA | U1: AVANT | V1: WL | AO1: Total | AP1: Saldo Total | AQ1: Saldo Edson | AR1: Saldo Master
B2: Saldo Inicial do dia | C2: =D2+E2+F2+G2+H2+I2+J2+M2+P2+SUM(Q2:AN2) -> -333323.48 | D2: ='Dez25'!D454 -> 6322.387 | E2: ='Dez25'!E454 -> -31610.26 | F2: ='Dez25'!F454 -> 0.5 | G2: ='Dez25'!G454 -> 0 | H2: ='Dez25'!H454 -> 60399.273 | I2: ='Dez25'!I454 -> 34519.82 | J2: ='Dez25'!J454 -> 0 | K2: ='Dez25'!K454 -> 6152 | ... AO2: ='Dez25'!AO454 -> -333323.48 | AP2: =#REF! -> #REF! | AQ2: =#REF! -> #REF! | AR2: =AP2-AQ2 -> #REF!
A3: 46023 | B3: Credito Vendas Cartão | AQ3: Saidas | AR3: #REF!
B4: Desconto taxas Cartão | AQ4: Saidas | AR4: #REF!
B5: Mensalidade POS | AQ5: Saidas | AR5: #REF!
B6: Pix e depósitos Banco Itaú | AQ6: Saidas | AR6: #REF!
B7: Pix e depósitos Banco Itaú - Lucila
B8: Transf. Lucila | AQ8: Saidas | AR8: #REF!
B9: Transf. Lucila Regina Ceregato Correa | AQ9: Saidas | AR9: #REF!
AP10: =#REF! -> #REF!
B11: Venda de Gasolina | J11: =-M11 -> 3082.1 | K11: -518 | L11: 5.95 | M11: =K11*L11 -> -3082.1 | AP11: =#REF! -> #REF!
B12: Venda de Etanol | J12: =-P12 -> 5599.86 | N12: -1407 | O12: 3.98 | P12: =N12*O12 -> -5599.86 | AP12: =#REF! -> #REF!
B13: Separação Cartão/Outros | H13: =-J13-I13 -> 3006.64 | I13: 5675.32 | J13: =-SUM(J11:J12) -> -8681.96 | AO13: =A2 -> 0 | AP13: =#REF! -> #REF!
B14: Ajuste estoque e valor diário (lucro embutido) | K14: -52 | M14: =(K17*M2/K2)-M2-M11 -> 183.82141 | N14: 9 | P14: =(N17*((P2)/(N2))-P2-P12) -> 402.42948 | AP14: =#REF! -> #REF!
AO15: =A3 -> 46023 | AP15: =#REF! -> #REF!
B16: Saldo Giro no dia | C16: =D17+E17+F17+G17+H17+I17+J17+M17+P17 -> 153648.08 | M16: =K16*L16 -> 0 | P16: =N16*O16 -> 0 | AO16: =SUM($Q2:AN16) -> -486385.31 | AS16: TERCEIROS
B17: Saldo Líquido do dia | C17: =AO17 -> -332737.23 | D17: =SUM(D2:D16) -> 6322.387 | E17: =SUM(E2:E16) -> -31610.26 | F17: =SUM(F2:F16) -> 0.5 | G17: =SUM(G2:G16) -> 0 | H17: =SUM(H2:H16) -> 63405.913 | I17: =SUM(I2:I16) -> 40195.14 | J17: =SUM(J2:J16) -> 0 | K17: =SUM(K2:K16) -> 5582 | L17: =M17/K17 -> 5.084699 | M17: =ROUND(SUM(M2:M16),2) -> 28382.79 | N17: =SUM(N2:N16) -> 12629 | O17: =P17/N17 -> 3.7177615 | P17: =ROUND(SUM(P2:P16),2) -> 46951.61 | Q17: =SUM(Q2:Q16) -> -530185.23 | R17: =SUM(R2:R16) -> 50229.3 | S17: =SUM(S2:S16) -> 0 | T17: =SUM(T2:T16) -> -6429.38 | U17: =SUM(U2:U16) -> 0 | V17: =SUM(V2:V16) -> 0 | W17: =SUM(W2:W16) -> 0 | X17: =SUM(X2:X16) -> 0 | ... AH17: =SUM(AH2:AH16) -> 0 | AJ17: =SUM(AJ2:AJ16) -> 0 | AK17: =SUM(AK2:AK16) -> 0 | AL17: =SUM(AL2:AL16) -> 0 | AM17: =SUM(AM2:AM16) -> 0 | AN17: =SUM(AN2:AN16) -> 0 | AO17: =D17+E17+F17+G17+H17+I17+J17+M17+P17+SUM(Q17:AN17) -> -332737.23 | AS17: SALDO C/C
A18: =A3+1 -> 46024 | B18: Credito Vendas Cartão 29/12/25 | D18: 9957.83 | I18: =-D18 -> -9957.83 | AP18: =#REF! -> #REF!
B19: Desconto taxas Cartão | I19: =D18-10212.14 -> -254.31
B20: Credito Vendas Cartão 30/12/25 | D20: 11108.16 | I20: =-D20 -> -11108.16 | AP20: =#REF! -> #REF!
B21: Desconto taxas Cartão | I21: =D20-11357.12 -> -248.96
B22: Credito Vendas Cartão 31/12/25 | D22: 12664.08 | I22: =-D22 -> -12664.08 | AP22: =#REF! -> #REF!
B23: Desconto taxas Cartão | I23: =D22-12950.56 -> -286.48
B24: Credito Vendas Cartão 01/01/26 | D24: 5554.6 | I24: =-D24 -> -5554.6 | AP24: =#REF! -> #REF!
B25: Desconto taxas Cartão | I25: =D24-5675.32 -> -120.72
B26: Pix e depósitos Banco Itaú | E26: =80+50+100+13+100+50+100+5+55+50+30+25+80+80+30+50+110+160+20+30+20+100+23+150+13+320+50+50+20+70+100+30+200+25+40+100+59.5+50+70+60+10+30+50 -> 2858.5 | H26: =-E26 -> -2858.5 | R26: =-D26 -> 0
B27: Tarifa pacote Itaú
B28: IOF
B29: Pag Elektro (casa)
B30: Pag Elektro (posto)
B31: Transf. Lucila Regina Ceregato Correa | D31: -45600 | F31: =-D31 -> 45600 | AQ31: Saidas | AR31: #REF!
B32: Pix Petroriente
B33: Estorno mensalidade POS
B34: Tarifa TED envio Petroriente
AP35: =#REF! -> #REF!
B36: Venda de Gasolina | J36: =-M36 -> 5825.05 | K36: -979 | L36: 5.95 | M36: =K36*L36 -> -5825.05 | AP36: =#REF! -> #REF!
B37: Venda de Etanol | J37: =-P37 -> 5046.64 | N37: -1268 | O37: 3.98 | P37: =N37*O37 -> -5046.64 | AP37: =#REF! -> #REF!
B38: Separação Cartão/Outros | H38: =-J38-I38 -> 3430.45 | I38: 7441.24 | J38: =-SUM(J36:J37) -> -10871.69 | AP38: =#REF! -> #REF!
B39: Ajuste estoque e valor diário (lucro embutido) | K39: 39 | M39: =(K42*M17/K17)-M17-M36 -> 1045.4329 | N39: -115 | P39: =(N42*P17/N17)-P17-P37 -> -95.024156 | AP39: =#REF! -> #REF!
AO40: =A18 -> 46024 | AP40: =#REF! -> #REF!
B41: Saldo Giro no dia | C41: =D42+E42+F42+G42+H42+I42+J42+M42+P42 -> 153688.02 | AO41: =SUM($Q17:AN41) -> -486385.31 | AS41: TERCEIROS
B42: Saldo Líquido do dia | C42: =AO42 -> -332697.29 | D42: =SUM(D17:D41) -> 7.05704 | E42: =SUM(E17:E41) -> -28751.76 | F42: =SUM(F17:F41) -> 45600.5 | G42: =SUM(G17:G41) -> 0 | H42: =SUM(H17:H41) -> 63977.863 | I42: =ROUND(SUM(I17:I41),2) -> 7441.24 | J42: =SUM(J17:J41) -> 0 | K42: =SUM(K17:K41) -> 4642 | L42: =M42/K42 -> 5.0846984 | M42: =ROUND(SUM(M17:M41),2) -> 23603.17 | N42: =SUM(N17:N41) -> 11246 | O42: =P42/N42 -> 3.7177619 | P42: =ROUND(SUM(P17:P41),2) -> 41809.95 | Q42: =SUM(Q17:Q41) -> -530185.23 | R42: =SUM(R17:R41) -> 50229.3 | S42: =SUM(S17:S41) -> 0 | T42: =SUM(T17:T41) -> -6429.38 | U42: =SUM(U17:U41) -> 0 | V42: =SUM(V17:V41) -> 0 | W42: =SUM(W17:W41) -> 0 | X42: =SUM(X17:X41) -> 0 | ... AN42: =SUM(AN17:AN41) -> 0 | AO42: =D42+E42+F42+G42+H42+I42+J42+M42+P42+SUM(Q42:AN42) -> -332697.29 | AS42: SALDO C/C
A43: =A18+1 -> 46025 | B43: Credito Vendas Cartão | D43: 7264.93 | I43: =-D43 -> -7264.93
B44: Desconto taxas Cartão | I44: =-I42-I43 -> -176.31
B51: Venda de Gasolina | J51: =-M51 -> 5158.65 | K51: -867 | L51: 5.95 | M51: =K51*L51 -> -5158.65 | AP51: =#REF! -> #REF!
B52: Venda de Etanol | J52: =-P52 -> 5981.94 | N52: -1503 | O52: 3.98 | P52: =N52*O52 -> -5981.94 | AP52: =#REF! -> #REF!
B53: Separação Cartão/Outros | H53: =-J53-I53 -> 3726.63 | I53: 7413.96 | J53: =-SUM(J51:J52) -> -11140.59 | AO53: =A26 -> 0 | AP53: =#REF! -> #REF!
B54: Ajuste de saldo e valor estoque diário | K54: -42 | M54: =(K57*((M42)/(K42)))-M42-M51 -> 536.65915 | N54: 6 | P54: =(N57*((P42)/(N42)))-P42-P52 -> 416.45048 | AO54: =A25 -> 0 | AP54: =#REF! -> #REF!
B56: Saldo Giro no dia | C56: =D57+E57+F57+G57+H57+I57+J57+M57+P57 -> 154464.82 | AO56: =SUM($Q42:AN56) -> -486385.31 | AS56: TERCEIROS
B57: Saldo Líquido do dia | C57: =AO57 -> -331920.49 | D57: =SUM(D42:D56) -> 7271.987 | E57: =SUM(E42:E56) -> -28751.76 | F57: =SUM(F42:F56) -> 45600.5 | G57: =SUM(G42:G56) -> 0 | H57: =SUM(H42:H56) -> 67704.493 | I57: =SUM(I42:I56) -> 7413.96 | J57: =SUM(J42:J56) -> 0 | K57: =SUM(K42:K56) -> 3733 | L57: =M57/K57 -> 5.0846986 | M57: =ROUND(SUM(M42:M56),2) -> 18981.18 | N57: =SUM(N42:N56) -> 9749 | O57: =P57/N57 -> 3.7177618 | P57: =ROUND(SUM(P42:P56),2) -> 36244.46 | Q57: =SUM(Q42:Q56) -> -530185.23 | R57: =SUM(R42:R56) -> 50229.3 | S57: =SUM(S42:S56) -> 0 | T57: =SUM(T42:T56) -> -6429.38 | U57: =SUM(U42:U56) -> 0 | V57: =SUM(V42:V56) -> 0 | W57: =SUM(W42:W56) -> 0 | X57: =SUM(X42:X56) -> 0 | ... AN57: =SUM(AN42:AN56) -> 0 | AO57: =D57+E57+F57+G57+H57+I57+J57+M57+P57+SUM(Q57:AN57) -> -331920.49 | AS57: SALDO C/C
A58: =A43+1 -> 46026 | B58: Credito Vendas Cartão | D58: 7243.61 | I58: =-D58 -> -7243.61
B59: Desconto taxas Cartão | I59: =-I57-I58 -> -170.35
B60: Transf. Lucila Regina Ceregato Correa | D60: -14500 | F60: =-D60 -> 14500 | AQ60: Saidas | AR60: #REF!
B63: Venda de Gasolina | J63: =-M63 -> 5099.15 | K63: -857 | L63: 5.95 | M63: =K63*L63 -> -5099.15 | AP63: =#REF! -> #REF!
B64: Venda de Etanol | J64: =-P64 -> 5333.2 | N64: -1340 | O64: 3.98 | P64: =N64*O64 -> -5333.2 | AP64: =#REF! -> #REF!
B65: Separação Cartão/Outros | H65: =-J65-I65 -> 3868.38 | I65: 6563.97 | J65: =-SUM(J63:J64) -> -10432.35 | AP65: =#REF! -> #REF!
B66: Ajuste de saldo e valor estoque diário | K66: -3 | M66: =(K69*((M57)/(K57)))-M57-M63 -> 726.30917 | N66: 3 | P66: =(N69*((P57)/(N57)))-P57-P64 -> 362.55244 | AO66: =A42 -> 0 | AP66: =#REF! -> #REF!
AO67: =A58 -> 46026
B68: Saldo Giro no dia | C68: =D69+E69+F69+G69+H69+I69+J69+M69+P69 -> 155383.33 | AO68: =SUM($Q57:AN68) -> -486385.31 | AS68: TERCEIROS
B69: Saldo Líquido do dia | C69: =AO69 -> -331001.98 | D69: =SUM(D57:D68) -> 15.59704 | E69: =SUM(E57:E68) -> -28751.76 | F69: =SUM(F57:F68) -> 60100.5 | G69: =SUM(G57:G68) -> 0 | H69: =SUM(H57:H68) -> 71572.873 | I69: =SUM(I57:I68) -> 6563.97 | J69: =SUM(J57:J68) -> 0 | K69: =SUM(K57:K68) -> 2873 | L69: =M69/K69 -> 5.0846989 | M69: =ROUND(SUM(M57:M68),2) -> 14608.34 | N69: =SUM(N57:N68) -> 8412 | O69: =P69/N69 -> 3.7177615 | P69: =ROUND(SUM(P57:P68),2) -> 31273.81 | Q69: =SUM(Q57:Q68) -> -530185.23 | R69: =SUM(R57:R68) -> 50229.3 | S69: =SUM(S57:S68) -> 0 | T69: =SUM(T57:T68) -> -6429.38 | U69: =SUM(U57:U68) -> 0 | V69: =SUM(V57:V68) -> 0 | W69: =SUM(W57:W68) -> 0 | X69: =SUM(X57:X68) -> 0 | ... AN69: =SUM(AN57:AN68) -> 0 | AO69: =D69+E69+F69+G69+H69+I69+J69+M69+P69+SUM(Q69:AN69) -> -331001.98 | AS69: SALDO C/C
A70: =A58+1 -> 46027 | B70: Credito Vendas Cartão | D70: 6406.88 | I70: =-D70 -> -6406.88
B71: Desconto taxas Cartão | I71: =-I69-I70 -> -157.09
B72: Pix recebido maquininha | D72: =20+146+100+80+11+30+45+15+100+25+100+12+40+100 -> 824 | I72: -824
B73: Tarifa pix recebido maquinha | D73: =-13*0.99-1.17 -> -14.04
B74: Transf. Lucila Regina Ceregato Correa | D74: 49000 | F74: =-D74 -> -49000 | AQ74: Saidas | AR74: #REF!
B75: Pix Eraldo Alves Macedo (reembolso) | D75: -50000 | Q75: =-D75 -> 50000
B76: Tarifa envio pix | D76: -4.9
B77: Pix e depósitos Banco Itaú | E77: =40+30+30+50+52.72+30+20+83+20+80+150+25+60+85+20+50+235+50+10+100+20+131+20+35+20+60+30+20+50+1082+804+69+10+1144+924+1337+20+60+574+20+589+206+674+638+376+100+10+194+50+30+20+50 -> 10587.72 | H77: =-E77 -> -10587.72
B78: Pix Eraldo Alves Macedo (reembolso) | E78: -5055 | Q78: =-E78 -> 5055
B79: Crediario Emprestimo 5/6 parcelas 3.214,69 | E79: =-1141.12-5-50-700-20.7-20-20-50-100-170-30-50-50-25-50-732.87 -> -3214.69 | M79: =K79*L79 -> 0 | P79: =N79*O79 -> 0 | T79: =-E79 -> 3214.69 | AQ79: Saidas | AR79: #REF!
B80: Tarifa pacote | E80: -92.5
B81: IOF | E81: -476.49
B82: Cesta básica (dinheiro) | H82: -791.28
B83: Vale refeição 5x767,00 | H83: -3835
B87: Venda de Gasolina | J87: =-M87 -> 7758.8 | K87: -1304 | L87: 5.95 | M87: =K87*L87 -> -7758.8 | AP87: =#REF! -> #REF!
B88: Venda de Etanol | J88: =-P88 -> 7315.24 | N88: -1838 | O88: 3.98 | P88: =N88*O88 -> -7315.24 | AP88: =#REF! -> #REF!
B89: Separação Cartão/Outros | H89: =-J89-I89 -> 3210.59 | I89: 11863.45 | J89: =-SUM(J87:J88) -> -15074.04 | AP89: =#REF! -> #REF!
B90: Ajuste de saldo e valor estoque diário | K90: 71 | M90: =(K93*((M69)/(K69)))-M69-M87 -> 1489.3662 | N90: -4 | P90: =(N93*((P69)/(N69)))-P69-P88 -> 467.12326 | AO90: =A59 -> 0 | AP90: =#REF! -> #REF!
AO91: =A70 -> 46027
B92: Saldo Giro no dia | C92: =D93+E93+F93+G93+H93+I93+J93+M93+P93 -> 93698.83 | AO92: =SUM($Q69:AN92) -> -428115.62 | AS92: TERCEIROS
B93: Saldo Líquido do dia | C93: =AO93 -> -334416.79 | D93: =SUM(D69:D92) -> 6227.537 | E93: =SUM(E69:E92) -> -27002.72 | F93: =SUM(F69:F92) -> 11100.5 | G93: =SUM(G69:G92) -> 0 | H93: =SUM(H69:H92) -> 59569.463 | I93: =SUM(I69:I92) -> 11039.45 | J93: =SUM(J69:J92) -> 0 | K93: =SUM(K69:K92) -> 1640 | L93: =M93/K93 -> 5.0847012 | M93: =ROUND(SUM(M69:M92),2) -> 8338.91 | N93: =SUM(N69:N92) -> 6570 | O93: =P93/N93 -> 3.717761 | P93: =ROUND(SUM(P69:P92),2) -> 24425.69 | Q93: =SUM(Q69:Q92) -> -475130.23 | R93: =SUM(R69:R92) -> 50229.3 | S93: =SUM(S69:S92) -> 0 | T93: =SUM(T69:T92) -> -3214.69 | U93: =SUM(U69:U92) -> 0 | V93: =SUM(V69:V92) -> 0 | W93: =SUM(W69:W92) -> 0 | X93: =SUM(X69:X92) -> 0 | ... AN93: =SUM(AN69:AN92) -> 0 | AO93: =D93+E93+F93+G93+H93+I93+J93+M93+P93+SUM(Q93:AN93) -> -334416.79 | AS93: SALDO C/C
A94: =A70+1 -> 46028 | B94: Credito Vendas Cartão | D94: =11595.65-824 -> 10771.65 | I94: =-D94 -> -10771.65
B95: Desconto taxas Cartão | I95: =-I93-I94 -> -267.8
B96: Pix recebido maquininha | D96: =59.5+8+180+100+30+144+15+8+100+143+10 -> 797.5 | I96: =-D96 -> -797.5
B97: Tarifa pix recebido maquinha | D97: =-8*0.99-1.44-1.15-1.14 -> -11.65
B98: Transf. Lucila Regina Ceregato Correa | D98: 11100 | F98: =-D98 -> -11100 | AQ98: Saidas | AR98: #REF!
B99: Pix Eraldo Alves Macedo p/ Spotbank | D99: 26000 | Q99: =-D99 -> -26000
B100: Tarifa pix recebido | D100: -208
B101: Tarifa envio pix | D101: -4.9
B102: Pix e depósitos Banco Itaú | E102: =100+30+150+50+25+50+50+100+230+1624+602+20+1039+1441+60 -> 5571 | H102: =-E102 -> -5571
B103: Pix Eraldo Alves Macedo (reembolso) | E103: -17000 | Q103: =-E103 -> 17000
B104: Pag Elektro | E104: -275.33
B105: Pag boleto Juliano Albino | E105: -498.36
B107: PAG NF 161496 GC 10x5,30 | D107: =-M107 -> -53000 | K107: 10000 | L107: 5.3 | M107: =K107*L107 -> 53000 | V107: =-P107 -> 0
B108: NF 568584 EH 10x3,76 | N108: 10000 | O108: 3.76 | P108: =N108*O108 -> 37600 | Q108: =-P108 -> -37600
B110: Venda de Gasolina | J110: =-M110 -> 6640.2 | K110: -1116 | L110: 5.95 | M110: =K110*L110 -> -6640.2 | AP110: =#REF! -> #REF!
B111: Venda de Etanol | J111: =-P111 -> 8847.54 | N111: -2223 | O111: 3.98 | P111: =N111*O111 -> -8847.54 | AP111: =#REF! -> #REF!
B112: Separação Cartão/Outros | H112: =-J112-I112 -> 4400.79 | I112: 11086.95 | J112: =-SUM(J110:J111) -> -15487.74 | AP112: =#REF! -> #REF!
B113: Ajuste de saldo e valor estoque diário | K113: -74 | M113: =(K116*((M93+M107)/(K93+K107)))-M93-M110-M107 -> 369.29769 | N113: 153 | P113: =(N116*((P93+P108)/(N93+N108)))-P93-P111-P108 -> 1099.0078 | AO113: =A74 -> 0 | AP113: =#REF! -> #REF!
AO114: =A94 -> 46028
...

Sheet Fev26
A1: PERÍODO 01 á 28/FEV/26 | C1: =D2+E2+F2+G2+H2+I2+J2+M2+P2 -> 212030.33 | D1: SPOT | E1: ITAU | F1: LUCILA | G1: HADEN | H1: CAIXA | I1: CARTAO | J1: VENDAS | K1: GASOLINA | N1: ETANOL | Q1: ERALDO | R1: LUIZ F. | S1: LUCILA | T1: DIVIDA | U1: AVANT | V1: WL | AO1: Total | AP1: Saldo Total | AQ1: Saldo Edson | AR1: Saldo Master
B2: Saldo Inicial do dia | C2: =D2+E2+F2+G2+H2+I2+J2+M2+P2+SUM(Q2:AN2) -> -355912.19 | D2: ='Jan26'!D578 -> 21384.817 | E2: ='Jan26'!E578 -> -22447.41 | F2: ='Jan26'!F578 -> 28395.65 | G2: ='Jan26'!G578 -> 0 | H2: ='Jan26'!H578 -> 66257.343 | I2: ='Jan26'!I578 -> 8772.28 | J2: ='Jan26'!J578 -> 0 | K2: ='Jan26'!K578 -> 2000 | ... AO2: ='Jan26'!AO578 -> -355912.19 | AP2: =#REF! -> #REF! | AQ2: =#REF! -> #REF! | AR2: =AP2-AQ2 -> #REF!
A3: 46054 | B3: Credito Vendas Cartão | D3: 8574.06 | I3: =-D3 -> -8574.06 | AQ3: Saidas | AR3: #REF!
B4: Desconto taxas Cartão | I4: =-I2-I3 -> -198.22 | AQ4: Saidas | AR4: #REF!
B5: Pix recebido maquininha | D5: =50+30+40+50+50+120+30+20+50.4+100+30+50+73 -> 693.4 | I5: =-D5 -> -693.4
B6: Tarifa pix recebido maquinha | D6: =-13*0.99 -> -12.87
AP7: =#REF! -> #REF!
B8: Venda de Gasolina | J8: =-M8 -> 5872.65 | K8: -987 | L8: 5.95 | M8: =K8*L8 -> -5872.65 | AP8: =#REF! -> #REF!
B9: Venda de Etanol | J9: =-P9 -> 6772.8 | N9: -1660 | O9: 4.08 | P9: =N9*O9 -> -6772.8 | AP9: =#REF! -> #REF!
B10: Separação Cartão/Outros | H10: =-J10-I10 -> 4740.78 | I10: 7904.67 | J10: =-SUM(J8:J9) -> -12645.45 | AO10: =A2 -> 0 | AP10: =#REF! -> #REF!
B11: Ajuste estoque e valor diário (lucro embutido) | K11: 36 | M11: =(K14*M2/K2)-M2-M8 -> 872.99099 | N11: -193 | P11: =(N14*((P2)/(N2))-P2-P9) -> -239.82333 | AP11: =#REF! -> #REF!
AO12: =A3 -> 46054 | AP12: =#REF! -> #REF!
B13: Saldo Giro no dia | C13: =D14+E14+F14+G14+H14+I14+J14+M14+P14 -> 212452.41 | M13: =K13*L13 -> 0 | P13: =N13*O13 -> 0 | AO13: =SUM($Q2:AN13) -> -567942.52 | AS13: TERCEIROS
B14: Saldo Líquido do dia | C14: =AO14 -> -355490.11 | D14: =SUM(D2:D13) -> 30639.407 | E14: =SUM(E2:E13) -> -22447.41 | F14: =SUM(F2:F13) -> 28395.65 | G14: =SUM(G2:G13) -> 0 | H14: =SUM(H2:H13) -> 70998.123 | I14: =SUM(I2:I13) -> 7211.27 | J14: =SUM(J2:J13) -> 0 | K14: =SUM(K2:K13) -> 1049 | L14: =M14/K14 -> 5.2572641 | M14: =ROUND(SUM(M2:M13),2) -> 5514.87 | N14: =SUM(N2:N13) -> 24347 | O14: =P14/N14 -> 3.7844704 | P14: =ROUND(SUM(P2:P13),2) -> 92140.5 | Q14: =SUM(Q2:Q13) -> -614957.13 | R14: =SUM(R2:R13) -> 50229.3 | S14: =SUM(S2:S13) -> 0 | T14: =SUM(T2:T13) -> -3214.69 | U14: =SUM(U2:U13) -> 0 | V14: =SUM(V2:V13) -> 0 | W14: =SUM(W2:W13) -> 0 | X14: =SUM(X2:X13) -> 0 | ... AH14: =SUM(AH2:AH13) -> 0 | AJ14: =SUM(AJ2:AJ13) -> 0 | AK14: =SUM(AK2:AK13) -> 0 | AL14: =SUM(AL2:AL13) -> 0 | AM14: =SUM(AM2:AM13) -> 0 | AN14: =SUM(AN2:AN13) -> 0 | AO14: =D14+E14+F14+G14+H14+I14+J14+M14+P14+SUM(Q14:AN14) -> -355490.11 | AS14: SALDO C/C
A15: =A3+1 -> 46055 | B15: Credito Vendas Cartão | D15: 7034.51 | I15: =-D15 -> -7034.51 | AP15: =#REF! -> #REF!
B16: Desconto taxas Cartão | I16: =-I14-I15 -> -176.76 | AP16: =#REF! -> #REF!
B17: Pix recebido maquininha | D17: =172+50+50+100+50+100+50+100+50+51.6+80+100 -> 953.6 | I17: =-D17 -> -953.6 | AP17: =#REF! -> #REF!
B18: Tarifa pix recebido maquinha | D18: =-11*0.99-1.38 -> -12.27 | AP18: =#REF! -> #REF!
B19: Transf. Lucila | D19: 28395 | F19: =-D19 -> -28395
B20: Pix e depósitos Banco Itaú | E20: =70+100+15+70+50+50+20+34+70+15+50+179+50+50+30+50+30+21+100+20+327+100+1130+1935+120+928+1168+752+1380+60 -> 8974 | H20: =-E20 -> -8974 | R20: =-D20 -> 0
B21: Pag Linx | E21: -184.86
B22: Pag Nexta NF 10705 | D22: -25575 | K22: 5000 | L22: 5.115 | M22: =K22*L22 -> 25575
B23: Pag Nexta NF 10706 | D23: -25575 | K23: 5000 | L23: 5.115 | M23: =K23*L23 -> 25575
B24: Tarifa pix enviado | D24: =-4.9-4.9 -> -9.8
AP25: =#REF! -> #REF!
B26: Venda de Gasolina | J26: =-M26 -> 7508.9 | K26: -1262 | L26: 5.95 | M26: =K26*L26 -> -7508.9 | AP26: =#REF! -> #REF!
B27: Venda de Etanol | J27: =-P27 -> 7433.76 | N27: -1822 | O27: 4.08 | P27: =N27*O27 -> -7433.76 | AP27: =#REF! -> #REF!
B28: Separação Cartão/Outros | H28: =-J28-I28 -> 4494.91 | I28: 10447.75 | J28: =-SUM(J26:J27) -> -14942.66 | AP28: =#REF! -> #REF!
B29: Ajuste estoque e valor diário (lucro embutido) | K29: 148 | M29: =(K32*(M14+M22+M23)/(K14+K22+K23))-M14-M26-M22-M23 -> 1795.7436 | N29: -40 | P29: =(N32*P14/N14)-P14-P27 -> 387.07618 | AP29: =#REF! -> #REF!
AO30: =A15 -> 46055 | AP30: =#REF! -> #REF!
B31: Saldo Giro no dia | C31: =D32+E32+F32+G32+H32+I32+J32+M32+P32 -> 214251.54 | AO31: =SUM($Q14:AN31) -> -567942.52 | AS31: TERCEIROS
B32: Saldo Líquido do dia | C32: =AO32 -> -353690.98 | D32: =SUM(D14:D31) -> 15850.447 | E32: =SUM(E14:E31) -> -13658.27 | F32: =SUM(F14:F31) -> 0.65 | G32: =SUM(G14:G31) -> 0 | H32: =SUM(H14:H31) -> 66519.033 | I32: =SUM(I14:I31) -> 9494.15 | J32: =SUM(J14:J31) -> 0 | K32: =SUM(K14:K31) -> 9935 | L32: =M32/K32 -> 5.1285063 | M32: =ROUND(SUM(M14:M31),2) -> 50951.71 | N32: =SUM(N14:N31) -> 22485 | O32: =P32/N32 -> 3.7844705 | P32: =ROUND(SUM(P14:P31),2) -> 85093.82 | Q32: =SUM(Q14:Q31) -> -614957.13 | R32: =SUM(R14:R31) -> 50229.3 | S32: =SUM(S14:S31) -> 0 | T32: =SUM(T14:T31) -> -3214.69 | U32: =SUM(U14:U31) -> 0 | V32: =SUM(V14:V31) -> 0 | W32: =SUM(W14:W31) -> 0 | X32: =SUM(X14:X31) -> 0 | ... AN32: =SUM(AN14:AN31) -> 0 | AO32: =D32+E32+F32+G32+H32+I32+J32+M32+P32+SUM(Q32:AN32) -> -353690.98 | AS32: SALDO C/C
A33: =A15+1 -> 46056 | B33: Credito Vendas Cartão | D33: 9494.15 | I33: =-D33 -> -9494.15
B34: Desconto taxas Cartão | I34: =-I32-I33 -> 0
B35: Pix recebido maquininha | D35: =50+15+9+30+20+50+40+30+20+31+20+50+100+25+13.48 -> 503.48 | I35: =-D35 -> -503.48
B36: Tarifa pix recebido maquinha | D36: =-15*0.99 -> -14.85
B37: Transf. Eraldo | D37: -25300 | Q37: =-D37 -> 25300
B38: Tarifa pix enviado | D38: -4.9
B39: Pix e depósitos Banco Itaú | E39: =125+100+70+60+50+80+70 -> 555 | H39: =-E39 -> -555 | R39: =-D39 -> 0
B40: Transf. Locaste | E40: -76
B41: IOF | E41: -268.84
B42: Transf. p/ Eraldo | E42: -24700 | Q42: =-E42 -> 24700
B44: Venda de Gasolina | J44: =-M44 -> 6491.45 | K44: -1091 | L44: 5.95 | M44: =K44*L44 -> -6491.45 | AP44: =#REF! -> #REF!
B45: Venda de Etanol | J45: =-P45 -> 7690.8 | N45: -1885 | O45: 4.08 | P45: =N45*O45 -> -7690.8 | AP45: =#REF! -> #REF!
B46: Separação Cartão/Outros | H46: =-J46-I46 -> 4061.69 | I46: 10120.56 | J46: =-SUM(J44:J45) -> -14182.25 | AO46: =A20 -> 0 | AP46: =#REF! -> #REF!
B47: Ajuste de saldo e valor estoque diário | K47: -69 | M47: =(K50*((M32)/(K32)))-M32-M44 -> 542.3827 | N47: -207 | P47: =(N50*((P32)/(N32)))-P32-P45 -> -226.31236 | AO47: =A19 -> 0 | AP47: =#REF! -> #REF!
B49: Saldo Giro no dia | C49: =D50+E50+F50+G50+H50+I50+J50+M50+P50 -> 164203.02 | AO49: =SUM($Q32:AN49) -> -517942.52 | AS49: TERCEIROS
B50: Saldo Líquido do dia | C50: =AO50 -> -353739.5 | D50: =SUM(D32:D49) -> 528.32704 | E50: =SUM(E32:E49) -> -38148.11 | F50: =SUM(F32:F49) -> 0.65 | G50: =SUM(G32:G49) -> 0 | H50: =SUM(H32:H49) -> 70025.723 | I50: =SUM(I32:I49) -> 9617.08 | J50: =SUM(J32:J49) -> 0 | K50: =SUM(K32:K49) -> 8775 | L50: =M50/K50 -> 5.128506 | M50: =ROUND(SUM(M32:M49),2) -> 45002.64 | N50: =SUM(N32:N49) -> 20393 | O50: =P50/N50 -> 3.7844707 | P50: =ROUND(SUM(P32:P49),2) -> 77176.71 | Q50: =SUM(Q32:Q49) -> -564957.13 | R50: =SUM(R32:R49) -> 50229.3 | S50: =SUM(S32:S49) -> 0 | T50: =SUM(T32:T49) -> -3214.69 | U50: =SUM(U32:U49) -> 0 | V50: =SUM(V32:V49) -> 0 | W50: =SUM(W32:W49) -> 0 | X50: =SUM(X32:X49) -> 0 | ... AN50: =SUM(AN32:AN49) -> 0 | AO50: =D50+E50+F50+G50+H50+I50+J50+M50+P50+SUM(Q50:AN50) -> -353739.5 | AS50: SALDO C/C
A51: =A33+1 -> 46057 | B51: Credito Vendas Cartão | D51: 9382.37 | I51: =-D51 -> -9382.37
B52: Desconto taxas Cartão | I52: =-I50-I51 -> -234.71
B53: Pix recebido maquininha | D53: =30+30+54+30+50+30+178.5+13.5+50+25+130.5+22+20 -> 663.5 | I53: =-D53 -> -663.5
B54: Tarifa pix recebido maquinha | D54: =-11*0.99-1.43-1.04 -> -13.36
B55: Pag boleto | D55: -291.95
B56: Pix e depósitos Banco Itaú | E56: =100+100+17.94+50+15+60+51+1085+1147+1268+1310 -> 5203.94 | H56: =-E56 -> -5203.94 | R56: =-D56 -> 0
B58: Venda de Gasolina | J58: =-M58 -> 6134.45 | K58: -1031 | L58: 5.95 | M58: =K58*L58 -> -6134.45 | AP58: =#REF! -> #REF!
B59: Venda de Etanol | J59: =-P59 -> 8898.48 | N59: -2181 | O59: 4.08 | P59: =N59*O59 -> -8898.48 | AP59: =#REF! -> #REF!
B60: Separação Cartão/Outros | H60: =-J60-I60 -> 4849.8 | I60: 10183.13 | J60: =-SUM(J58:J59) -> -15032.93 | AP60: =#REF! -> #REF!
B61: Ajuste de saldo e valor estoque diário | K61: 14 | M61: =(K64*((M50)/(K50)))-M50-M58 -> 918.75942 | N61: 30 | P61: =(N64*((P50)/(N50)))-P50-P59 -> 758.08363 | AO61: =A32 -> 0 | AP61: =#REF! -> #REF!
AO62: =A51 -> 46057
B63: Saldo Giro no dia | C63: =D64+E64+F64+G64+H64+I64+J64+M64+P64 -> 165339.84 | AO63: =SUM($Q50:AN63) -> -517942.52 | AS63: TERCEIROS
B64: Saldo Líquido do dia | C64: =AO64 -> -352602.68 | D64: =SUM(D50:D63) -> 10268.887 | E64: =SUM(E50:E63) -> -32944.17 | F64: =SUM(F50:F63) -> 0.65 | G64: =SUM(G50:G63) -> 0 | H64: =SUM(H50:H63) -> 69671.583 | I64: =SUM(I50:I63) -> 9519.63 | J64: =SUM(J50:J63) -> 0 | K64: =SUM(K50:K63) -> 7758 | L64: =M64/K64 -> 5.1285061 | M64: =ROUND(SUM(M50:M63),2) -> 39786.95 | N64: =SUM(N50:N63) -> 18242 | O64: =P64/N64 -> 3.7844705 | P64: =ROUND(SUM(P50:P63),2) -> 69036.31 | Q64: =SUM(Q50:Q63) -> -564957.13 | R64: =SUM(R50:R63) -> 50229.3 | S64: =SUM(S50:S63) -> 0 | T64: =SUM(T50:T63) -> -3214.69 | U64: =SUM(U50:U63) -> 0 | V64: =SUM(V50:V63) -> 0 | W64: =SUM(W50:W63) -> 0 | X64: =SUM(X50:X63) -> 0 | ... AN64: =SUM(AN50:AN63) -> 0 | AO64: =D64+E64+F64+G64+H64+I64+J64+M64+P64+SUM(Q64:AN64) -> -352602.68 | AS64: SALDO C/C
A65: =A51+1 -> 46058 | B65: Credito Vendas Cartão | D65: 9295.4 | I65: =-D65 -> -9295.4
B66: Desconto taxas Cartão | I66: =-I64-I65 -> -224.23
B67: Pix recebido maquininha | D67: =150+15+15+25+20+100+50+30+50+197+40 -> 692 | I67: =-D67 -> -692
B68: Tarifa pix recebido maquinha | D68: =-9*0.99-1.2-1.58 -> -11.69
B69: Pix e depósitos Banco Itaú | E69: =100+30+15+20+55.29+2714.2+30+100+20+40+20+15+50+1677+1505+75 -> 6466.49 | H69: =-E69 -> -6466.49 | R69: =-D69 -> 0
B70: Crediario Emprestimo 6/6 parcelas 3.214,69 | E70: =-1141.12-5-50-700-20.7-20-20-50-100-170-30-50-50-25-50-732.87 -> -3214.69 | M70: =K70*L70 -> 0 | P70: =N70*O70 -> 0 | T70: =-E70 -> 3214.69 | AQ70: Saidas | AR70: #REF!
B71: Cesta básica (dinheiro) | H71: -791.28
B72: Vale refeição 5x767,00 | H72: -3835
B74: Venda de Gasolina | J74: =-M74 -> 6241.55 | K74: -1049 | L74: 5.95 | M74: =K74*L74 -> -6241.55 | AP74: =#REF! -> #REF!
B75: Venda de Etanol | J75: =-P75 -> 7976.4 | N75: -1955 | O75: 4.08 | P75: =N75*O75 -> -7976.4 | AP75: =#REF! -> #REF!
B76: Separação Cartão/Outros | H76: =-J76-I76 -> 4034.82 | I76: 10183.13 | J76: =-SUM(J74:J75) -> -14217.95 | AP76: =#REF! -> #REF!
B77: Ajuste de saldo e valor estoque diário | K77: -54 | M77: =(K80*((M64)/(K64)))-M64-M74 -> 584.80782 | N77: -72 | P77: =(N80*((P64)/(N64)))-P64-P75 -> 305.27839 | AO77: =A52 -> 0 | AP77: =#REF! -> #REF!
AO78: =A65 -> 46058
B79: Saldo Giro no dia | C79: =D80+E80+F80+G80+H80+I80+J80+M80+P80 -> 158153.04 | AO79: =SUM($Q64:AN79) -> -514727.83 | AS79: TERCEIROS
B80: Saldo Líquido do dia | C80: =AO80 -> -356574.79 | D80: =SUM(D64:D79) -> 20244.597 | E80: =SUM(E64:E79) -> -29692.37 | F80: =SUM(F64:F79) -> 0.65 | G80: =SUM(G64:G79) -> 0 | H80: =SUM(H64:H79) -> 62613.633 | I80: =SUM(I64:I79) -> 9491.13 | J80: =SUM(J64:J79) -> 0 | K80: =SUM(K64:K79) -> 6655 | L80: =M80/K80 -> 5.1285064 | M80: =ROUND(SUM(M64:M79),2) -> 34130.21 | N80: =SUM(N64:N79) -> 16215 | O80: =P80/N80 -> 3.7844706 | P80: =ROUND(SUM(P64:P79),2) -> 61365.19 | Q80: =SUM(Q64:Q79) -> -564957.13 | R80: =SUM(R64:R79) -> 50229.3 | S80: =SUM(S64:S79) -> 0 | T80: =SUM(T64:T79) -> 0 | U80: =SUM(U64:U79) -> 0 | V80: =SUM(V64:V79) -> 0 | W80: =SUM(W64:W79) -> 0 | X80: =SUM(X64:X79) -> 0 | ... AN80: =SUM(AN64:AN79) -> 0 | AO80: =D80+E80+F80+G80+H80+I80+J80+M80+P80+SUM(Q80:AN80) -> -356574.79 | AS80: SALDO C/C
A81: =A65+1 -> 46059 | B81: Credito Vendas Cartão | D81: 8916.35 | I81: =-D81 -> -8916.35
B82: Desconto taxas Cartão | I82: =-I80-I81 -> -574.78
B83: Pix recebido maquininha | D83: =30+100+81+50+30+15+5+50+20+102+30+30+40+20+50 -> 653 | I83: =-D83 -> -653
B84: Tarifa pix recebido maquinha | D84: =-15*0.99 -> -14.85
B85: Transf. p/ Eraldo | D85: -29100 | Q85: =-D85 -> 29100
B86: Tarifa pix enviado | D86: -4.9
B87: Pix e depósitos Banco Itaú | E87: =20+20+100+80+8+30+50+60+1897+100+20+100+50+1126+1294.33 -> 4955.33 | H87: =-E87 -> -4955.33 | R87: =-D87 -> 0
B88: Transf. p/ Eraldo | E88: -16740 | Q88: =-E88 -> 16740
B89: Pix Jose Ju | E89: -230
B91: Venda de Gasolina | J91: =-M91 -> 6247.5 | K91: -1050 | L91: 5.95 | M91: =K91*L91 -> -6247.5 | AP91: =#REF! -> #REF!
B92: Venda de Etanol | J92: =-P92 -> 8164.08 | N92: -2001 | O92: 4.08 | P92: =N92*O92 -> -8164.08 | AP92: =#REF! -> #REF!
B93: Separação Cartão/Outros | H93: =-J93-I93 -> 3882.01 | I93: 10529.57 | J93: =-SUM(J91:J92) -> -14411.58 | AP93: =#REF! -> #REF!
B94: Ajuste de saldo e valor estoque diário | K94: -23 | M94: =(K97*((M80)/(K80)))-M80-M91 -> 744.61265 | N94: -31 | P94: =(N97*((P80)/(N80)))-P80-P92 -> 474.03584 | AO94: =A69 -> 0 | AP94: =#REF! -> #REF!
AO95: =A81 -> 46059
B96: Saldo Giro no dia | C96: =D97+E97+F97+G97+H97+I97+J97+M97+P97 -> 112707.16 | AO96: =SUM($Q80:AN96) -> -468887.83 | AS96: TERCEIROS
B97: Saldo Líquido do dia | C97: =AO97 -> -356180.67 | D97: =SUM(D80:D96) -> 694.19704 | E97: =SUM(E80:E96) -> -41707.04 | F97: =SUM(F80:F96) -> 0.65 | G97: =SUM(G80:G96) -> 0 | H97: =SUM(H80:H96) -> 61540.313 | I97: =SUM(I80:I96) -> 9876.57 | J97: =SUM(J80:J96) -> 0 | K97: =SUM(K80:K96) -> 5582 | L97: =M97/K97 -> 5.1285059 | M97: =ROUND(SUM(M80:M96),2) -> 28627.32 | N97: =SUM(N80:N96) -> 14183 | O97: =P97/N97 -> 3.7844708 | P97: =ROUND(SUM(P80:P96),2) -> 53675.15 | Q97: =SUM(Q80:Q96) -> -519117.13 | R97: =SUM(R80:R96) -> 50229.3 | S97: =SUM(S80:S96) -> 0 | T97: =SUM(T80:T96) -> 0 | U97: =SUM(U80:U96) -> 0 | V97: =SUM(V80:V96) -> 0 | W97: =SUM(W80:W96) -> 0 | X97: =SUM(X80:X96) -> 0 | ... AN97: =SUM(AN80:AN96) -> 0 | AO97: =D97+E97+F97+G97+H97+I97+J97+M97+P97+SUM(Q97:AN97) -> -356180.67 | AS97: SALDO C/C
A98: =A81+1 -> 46060 | B98: Credito Vendas Cartão | D98: 9668.93 | I98: =-D98 -> -9668.93
B99: Desconto taxas Cartão | I99: =-I97-I98 -> -207.64
B100: Pix recebido maquininha | D100: =10+200+20+50+50+30+50+100+12+22+96.2 -> 640.2 | I100: =-D100 -> -640.2
B101: Tarifa pix recebido maquinha | D101: =-10*0.99-1.6 -> -11.5
B103: Venda de Gasolina | J103: =-M103 -> 7592.2 | K103: -1276 | L103: 5.95 | M103: =K103*L103 -> -7592.2 | AP103: =#REF! -> #REF!
B104: Venda de Etanol | J104: =-P104 -> 8959.68 | N104: -2196 | O104: 4.08 | P104: =N104*O104 -> -8959.68 | AP104: =#REF! -> #REF!
B105: Separação Cartão/Outros | H105: =-J105-I105 -> 4141.85 | I105: 12410.03 | J105: =-SUM(J103:J104) -> -16551.88 | AP105: =#REF! -> #REF!
B106: Ajuste de saldo e valor estoque diário | K106: -26 | M106: =(K109*L97)-M97-M103 -> 914.8853 | N106: -139 | P106: =(N109*O97)-P97-P104 -> 122.94058 | AO106: =A94 -> 0 | AP106: =#REF! -> #REF!
...

Sheet Mar26
A1: PERÍODO 01 á 31/MAR/26 | C1: =D2+E2+F2+G2+H2+I2+J2+M2+P2 -> 117279.93 | D1: SPOT | E1: ITAU | F1: LUCILA | G1: HADEN | H1: CAIXA | I1: CARTAO | J1: VENDAS | K1: GASOLINA | N1: ETANOL | Q1: DIESEL | T1: ERALDO | U1: LUIZ F. | V1: LUCILA | W1: DIVIDA | X1: AVANT | Y1: WL | AR1: Total | AS1: Saldo Total | AT1: Saldo Edson | AU1: Saldo Master
B2: Saldo Inicial do dia | C2: =D2+E2+F2+G2+H2+I2+J2+M2+P2+SUM(T2:AQ2) -> -369807.9 | D2: ='Fev26'!D469 -> 12717.607 | E2: ='Fev26'!E469 -> -43287.79 | F2: ='Fev26'!F469 -> 0.65 | G2: ='Fev26'!G469 -> 0 | H2: ='Fev26'!H469 -> 65082.293 | I2: ='Fev26'!I469 -> 10004.65 | J2: ='Fev26'!J469 -> 0 | K2: ='Fev26'!K469 -> 12170 | ... P2: ='Fev26'!P469 -> 10128.49 | Q2: 214 | R2: 6.0995 | S2: =Q2*R2 -> 1305.293 | T2: ='Fev26'!Q469 -> -537317.13 | U2: ='Fev26'!R469 -> 50229.3 | V2: ='Fev26'!S469 -> 0 | W2: ='Fev26'!T469 -> 0 | X2: ='Fev26'!U469 -> 0 | Y2: ='Fev26'!V469 -> 0 | Z2: ='Fev26'!W469 -> 0 | AA2: ='Fev26'!X469 -> 0 | ... AR2: ='Fev26'!AO469 -> -369807.9 | AS2: =#REF! -> #REF! | AT2: =#REF! -> #REF! | AU2: =AS2-AT2 -> #REF!
A3: 46082 | B3: BLOCO SPOT
B4: Credito Vendas Cartão | AT4: Saidas | AU4: #REF!
B5: Desconto taxas Cartão | AT5: Saidas | AU5: #REF!
B6: Pix recebido maquininha
B7: Tarifa pix recebido maquinha
B8: BLOCO ITAU
B9: Pix e depositos Vendas
AS10: =#REF! -> #REF!
B11: BLOCO ESTOQUES
B12: Venda de Gasolina | AS12: =#REF! -> #REF!
B13: Venda de Etanol | AS13: =#REF! -> #REF!
B14: Venda de Diesel | AS14: =#REF! -> #REF!
B15: Separação Cartão/Outros | AS15: =#REF! -> #REF!
B16: Ajuste estoque e valor diário (lucro embutido) | AS16: =#REF! -> #REF!
AS17: =#REF! -> #REF!
B18: Saldo Giro no dia | C18: =D19+E19+F19+G19+H19+I19+J19+M19+P19+S19 -> 118585.22 | AR18: =SUM($T2:AQ18) -> -487087.83 | AV18: TERCEIROS
B19: Saldo Líquido do dia | C19: =AR19 -> -368502.61 | D19: =SUM(D2:D18) -> 12717.607 | E19: =SUM(E2:E18) -> -43287.79 | F19: =SUM(F2:F18) -> 0.65 | G19: =SUM(G2:G18) -> 0 | H19: =SUM(H2:H18) -> 65082.293 | I19: =SUM(I2:I18) -> 10004.65 | J19: =SUM(J2:J18) -> 0 | K19: =SUM(K2:K18) -> 12170 | L19: =M19/K19 -> 5.1465924 | M19: =ROUND(SUM(M2:M18),2) -> 62634.03 | N19: =SUM(N2:N18) -> 2783 | O19: =P19/N19 -> 3.6394143 | P19: =ROUND(SUM(P2:P18),2) -> 10128.49 | Q19: =SUM(Q2:Q18) -> 214 | R19: =S19/Q19 -> 6.099486 | S19: =ROUND(SUM(S2:S18),2) -> 1305.29 | T19: =SUM(T2:T18) -> -537317.13 | U19: =SUM(U2:U18) -> 50229.3 | V19: =SUM(V2:V18) -> 0 | W19: =SUM(W2:W18) -> 0 | X19: =SUM(X2:X18) -> 0 | Y19: =SUM(Y2:Y18) -> 0 | Z19: =SUM(Z2:Z18) -> 0 | AA19: =SUM(AA2:AA18) -> 0 | ... AK19: =SUM(AK2:AK18) -> 0 | AM19: =SUM(AM2:AM18) -> 0 | AN19: =SUM(AN2:AN18) -> 0 | AO19: =SUM(AO2:AO18) -> 0 | AP19: =SUM(AP2:AP18) -> 0 | AQ19: =SUM(AQ2:AQ18) -> 0 | AR19: =D19+E19+F19+G19+H19+I19+J19+M19+P19+S19+SUM(T19:AQ19) -> -368502.61 | AV19: CONSOLIDADO
A20: =A3+1 -> 46083 | B20: BLOCO SPOT
B21: Credito Vendas Cartão | AT21: Saidas | AU21: #REF!
B22: Desconto taxas Cartão | AT22: Saidas | AU22: #REF!
B23: Pix recebido maquininha
B24: Tarifa pix recebido maquinha
B25: BLOCO ITAU
B26: Pix e depositos Vendas
AS27: =#REF! -> #REF!
B28: BLOCO ESTOQUES
B29: Venda de Gasolina | AS29: =#REF! -> #REF!
B30: Venda de Etanol | AS30: =#REF! -> #REF!
B31: Venda de Diesel | AS31: =#REF! -> #REF!
B32: Separação Cartão/Outros | AS32: =#REF! -> #REF!
B33: Ajuste estoque e valor diário (lucro embutido) | AS33: =#REF! -> #REF!
AS34: =#REF! -> #REF!
B35: Saldo Giro no dia | C35: =D36+E36+F36+G36+H36+I36+J36+M36+P36 -> 117279.93 | AR35: =SUM($T19:AQ35) -> -487087.83 | AV35: TERCEIROS
B36: Saldo Líquido do dia | C36: =AR36 -> -368502.61 | D36: =SUM(D19:D35) -> 12717.607 | E36: =SUM(E19:E35) -> -43287.79 | F36: =SUM(F19:F35) -> 0.65 | G36: =SUM(G19:G35) -> 0 | H36: =SUM(H19:H35) -> 65082.293 | I36: =SUM(I19:I35) -> 10004.65 | J36: =SUM(J19:J35) -> 0 | K36: =SUM(K19:K35) -> 12170 | L36: =M36/K36 -> 5.1465924 | M36: =ROUND(SUM(M19:M35),2) -> 62634.03 | N36: =SUM(N19:N35) -> 2783 | O36: =P36/N36 -> 3.6394143 | P36: =ROUND(SUM(P19:P35),2) -> 10128.49 | Q36: =SUM(Q19:Q35) -> 214 | R36: =S36/Q36 -> 6.099486 | S36: =ROUND(SUM(S19:S35),2) -> 1305.29 | T36: =SUM(T19:T35) -> -537317.13 | U36: =SUM(U19:U35) -> 50229.3 | V36: =SUM(V19:V35) -> 0 | W36: =SUM(W19:W35) -> 0 | X36: =SUM(X19:X35) -> 0 | Y36: =SUM(Y19:Y35) -> 0 | Z36: =SUM(Z19:Z35) -> 0 | AA36: =SUM(AA19:AA35) -> 0 | ... AQ36: =SUM(AQ19:AQ35) -> 0 | AR36: =D36+E36+F36+G36+H36+I36+J36+M36+P36+S36+SUM(T36:AQ36) -> -368502.61 | AV36: CONSOLIDADO
A37: =A20+1 -> 46084 | B37: BLOCO SPOT
B38: Credito Vendas Cartão | AT38: Saidas | AU38: #REF!
B39: Desconto taxas Cartão | AT39: Saidas | AU39: #REF!
B40: Pix recebido maquininha
B41: Tarifa pix recebido maquinha
B42: BLOCO ITAU
B43: Pix e depositos Vendas
AS44: =#REF! -> #REF!
B45: BLOCO ESTOQUES
B46: Venda de Gasolina | AS46: =#REF! -> #REF!
B47: Venda de Etanol | AS47: =#REF! -> #REF!
B48: Venda de Diesel | AS48: =#REF! -> #REF!
B49: Separação Cartão/Outros | AS49: =#REF! -> #REF!
B50: Ajuste estoque e valor diário (lucro embutido) | AS50: =#REF! -> #REF!
AS51: =#REF! -> #REF!
B52: Saldo Giro no dia | C52: =D53+E53+F53+G53+H53+I53+J53+M53+P53 -> 117279.93 | AR52: =SUM($T36:AQ52) -> -487087.83 | AV52: TERCEIROS
B53: Saldo Líquido do dia | C53: =AR53 -> -368502.61 | D53: =SUM(D36:D52) -> 12717.607 | E53: =SUM(E36:E52) -> -43287.79 | F53: =SUM(F36:F52) -> 0.65 | G53: =SUM(G36:G52) -> 0 | H53: =SUM(H36:H52) -> 65082.293 | I53: =SUM(I36:I52) -> 10004.65 | J53: =SUM(J36:J52) -> 0 | K53: =SUM(K36:K52) -> 12170 | L53: =M53/K53 -> 5.1465924 | M53: =ROUND(SUM(M36:M52),2) -> 62634.03 | N53: =SUM(N36:N52) -> 2783 | O53: =P53/N53 -> 3.6394143 | P53: =ROUND(SUM(P36:P52),2) -> 10128.49 | Q53: =SUM(Q36:Q52) -> 214 | R53: =S53/Q53 -> 6.099486 | S53: =ROUND(SUM(S36:S52),2) -> 1305.29 | T53: =SUM(T36:T52) -> -537317.13 | U53: =SUM(U36:U52) -> 50229.3 | V53: =SUM(V36:V52) -> 0 | W53: =SUM(W36:W52) -> 0 | X53: =SUM(X36:X52) -> 0 | Y53: =SUM(Y36:Y52) -> 0 | Z53: =SUM(Z36:Z52) -> 0 | AA53: =SUM(AA36:AA52) -> 0 | ... AQ53: =SUM(AQ36:AQ52) -> 0 | AR53: =D53+E53+F53+G53+H53+I53+J53+M53+P53+S53+SUM(T53:AQ53) -> -368502.61 | AV53: CONSOLIDADO
A54: =A37+1 -> 46085 | B54: BLOCO SPOT
B55: Credito Vendas Cartão | AT55: Saidas | AU55: #REF!
B56: Desconto taxas Cartão | AT56: Saidas | AU56: #REF!
B57: Pix recebido maquininha
B58: Tarifa pix recebido maquinha
B59: BLOCO ITAU
B60: Pix e depositos Vendas
AS61: =#REF! -> #REF!
B62: BLOCO ESTOQUES
B63: Venda de Gasolina | AS63: =#REF! -> #REF!
B64: Venda de Etanol | AS64: =#REF! -> #REF!
B65: Venda de Diesel | AS65: =#REF! -> #REF!
B66: Separação Cartão/Outros | AS66: =#REF! -> #REF!
B67: Ajuste estoque e valor diário (lucro embutido) | AS67: =#REF! -> #REF!
AS68: =#REF! -> #REF!
B69: Saldo Giro no dia | C69: =D70+E70+F70+G70+H70+I70+J70+M70+P70 -> 117279.93 | AR69: =SUM($T53:AQ69) -> -487087.83 | AV69: TERCEIROS
B70: Saldo Líquido do dia | C70: =AR70 -> -368502.61 | D70: =SUM(D53:D69) -> 12717.607 | E70: =SUM(E53:E69) -> -43287.79 | F70: =SUM(F53:F69) -> 0.65 | G70: =SUM(G53:G69) -> 0 | H70: =SUM(H53:H69) -> 65082.293 | I70: =SUM(I53:I69) -> 10004.65 | J70: =SUM(J53:J69) -> 0 | K70: =SUM(K53:K69) -> 12170 | L70: =M70/K70 -> 5.1465924 | M70: =ROUND(SUM(M53:M69),2) -> 62634.03 | N70: =SUM(N53:N69) -> 2783 | O70: =P70/N70 -> 3.6394143 | P70: =ROUND(SUM(P53:P69),2) -> 10128.49 | Q70: =SUM(Q53:Q69) -> 214 | R70: =S70/Q70 -> 6.099486 | S70: =ROUND(SUM(S53:S69),2) -> 1305.29 | T70: =SUM(T53:T69) -> -537317.13 | U70: =SUM(U53:U69) -> 50229.3 | V70: =SUM(V53:V69) -> 0 | W70: =SUM(W53:W69) -> 0 | X70: =SUM(X53:X69) -> 0 | Y70: =SUM(Y53:Y69) -> 0 | Z70: =SUM(Z53:Z69) -> 0 | AA70: =SUM(AA53:AA69) -> 0 | ... AQ70: =SUM(AQ53:AQ69) -> 0 | AR70: =D70+E70+F70+G70+H70+I70+J70+M70+P70+S70+SUM(T70:AQ70) -> -368502.61 | AV70: CONSOLIDADO
A71: =A54+1 -> 46086 | B71: BLOCO SPOT
B72: Credito Vendas Cartão | AT72: Saidas | AU72: #REF!
B73: Desconto taxas Cartão | AT73: Saidas | AU73: #REF!
B74: Pix recebido maquininha
B75: Tarifa pix recebido maquinha
B76: BLOCO ITAU
B77: Pix e depositos Vendas
AS78: =#REF! -> #REF!
B79: BLOCO ESTOQUES
B80: Venda de Gasolina | AS80: =#REF! -> #REF!
B81: Venda de Etanol | AS81: =#REF! -> #REF!
B82: Venda de Diesel | AS82: =#REF! -> #REF!
B83: Separação Cartão/Outros | AS83: =#REF! -> #REF!
B84: Ajuste estoque e valor diário (lucro embutido) | AS84: =#REF! -> #REF!
AS85: =#REF! -> #REF!
B86: Saldo Giro no dia | C86: =D87+E87+F87+G87+H87+I87+J87+M87+P87 -> 117279.93 | AR86: =SUM($T70:AQ86) -> -487087.83 | AV86: TERCEIROS
B87: Saldo Líquido do dia | C87: =AR87 -> -368502.61 | D87: =SUM(D70:D86) -> 12717.607 | E87: =SUM(E70:E86) -> -43287.79 | F87: =SUM(F70:F86) -> 0.65 | G87: =SUM(G70:G86) -> 0 | H87: =SUM(H70:H86) -> 65082.293 | I87: =SUM(I70:I86) -> 10004.65 | J87: =SUM(J70:J86) -> 0 | K87: =SUM(K70:K86) -> 12170 | L87: =M87/K87 -> 5.1465924 | M87: =ROUND(SUM(M70:M86),2) -> 62634.03 | N87: =SUM(N70:N86) -> 2783 | O87: =P87/N87 -> 3.6394143 | P87: =ROUND(SUM(P70:P86),2) -> 10128.49 | Q87: =SUM(Q70:Q86) -> 214 | R87: =S87/Q87 -> 6.099486 | S87: =ROUND(SUM(S70:S86),2) -> 1305.29 | T87: =SUM(T70:T86) -> -537317.13 | U87: =SUM(U70:U86) -> 50229.3 | V87: =SUM(V70:V86) -> 0 | W87: =SUM(W70:W86) -> 0 | X87: =SUM(X70:X86) -> 0 | Y87: =SUM(Y70:Y86) -> 0 | Z87: =SUM(Z70:Z86) -> 0 | AA87: =SUM(AA70:AA86) -> 0 | ... AQ87: =SUM(AQ70:AQ86) -> 0 | AR87: =D87+E87+F87+G87+H87+I87+J87+M87+P87+S87+SUM(T87:AQ87) -> -368502.61 | AV87: CONSOLIDADO
A88: =A71+1 -> 46087 | B88: BLOCO SPOT
B89: Credito Vendas Cartão | AT89: Saidas | AU89: #REF!
B90: Desconto taxas Cartão | AT90: Saidas | AU90: #REF!
B91: Pix recebido maquininha
B92: Tarifa pix recebido maquinha
B93: BLOCO ITAU
B94: Pix e depositos Vendas
AS95: =#REF! -> #REF!
B96: BLOCO ESTOQUES
B97: Venda de Gasolina | AS97: =#REF! -> #REF!
B98: Venda de Etanol | AS98: =#REF! -> #REF!
B99: Venda de Diesel | AS99: =#REF! -> #REF!
B100: Separação Cartão/Outros | AS100: =#REF! -> #REF!
...

Sheet Abr26
A1: PERÍODO 01 á 30/ABR/26 | C1: =D2+E2+F2+G2+H2+I2+J2+M2+P2 -> 117279.93 | D1: SPOT | E1: ITAU | F1: LUCILA | G1: HADEN | H1: CAIXA | I1: CARTAO | J1: VENDAS | K1: GASOLINA | N1: ETANOL | Q1: DIESEL | T1: ERALDO | U1: LUIZ F. | V1: LUCILA | W1: DIVIDA | X1: AVANT | Y1: WL | AR1: Total | AS1: Saldo Total | AT1: Saldo Edson | AU1: Saldo Master
B2: Saldo Inicial do dia | C2: =D2+E2+F2+G2+H2+I2+J2+M2+P2+SUM(T2:AQ2) -> -369807.9 | D2: ='Mar26'!D529 -> 12717.607 | E2: ='Mar26'!E529 -> -43287.79 | F2: ='Mar26'!F529 -> 0.65 | G2: ='Mar26'!G529 -> 0 | H2: ='Mar26'!H529 -> 65082.293 | I2: ='Mar26'!I529 -> 10004.65 | J2: ='Mar26'!J529 -> 0 | K2: ='Mar26'!K529 -> 12170 | ... AR2: ='Mar26'!AR529 -> -368502.61 | AS2: =#REF! -> #REF! | AT2: =#REF! -> #REF! | AU2: =AS2-AT2 -> #REF!
A3: 46113 | B3: BLOCO SPOT
B4: Credito Vendas Cartão | AT4: Saidas | AU4: #REF!
B5: Desconto taxas Cartão | AT5: Saidas | AU5: #REF!
B6: Pix recebido maquininha
B7: Tarifa pix recebido maquinha
B8: BLOCO ITAU
B9: Pix e depositos Vendas
AS10: =#REF! -> #REF!
B11: BLOCO ESTOQUES
B12: Venda de Gasolina | AS12: =#REF! -> #REF!
B13: Venda de Etanol | AS13: =#REF! -> #REF!
B14: Venda de Diesel | AS14: =#REF! -> #REF!
B15: Separação Cartão/Outros | AS15: =#REF! -> #REF!
B16: Ajuste estoque e valor diário (lucro embutido) | AS16: =#REF! -> #REF!
AS17: =#REF! -> #REF!
B18: Saldo Giro no dia | C18: =D19+E19+F19+G19+H19+I19+J19+M19+P19+S19 -> 118585.22 | AR18: =SUM($T2:AQ18) -> -487087.83 | AV18: TERCEIROS
B19: Saldo Líquido do dia | C19: =AR19 -> -368502.61 | D19: =SUM(D2:D18) -> 12717.607 | E19: =SUM(E2:E18) -> -43287.79 | F19: =SUM(F2:F18) -> 0.65 | G19: =SUM(G2:G18) -> 0 | H19: =SUM(H2:H18) -> 65082.293 | I19: =SUM(I2:I18) -> 10004.65 | J19: =SUM(J2:J18) -> 0 | K19: =SUM(K2:K18) -> 12170 | L19: =M19/K19 -> 5.1465924 | M19: =ROUND(SUM(M2:M18),2) -> 62634.03 | N19: =SUM(N2:N18) -> 2783 | O19: =P19/N19 -> 3.6394143 | P19: =ROUND(SUM(P2:P18),2) -> 10128.49 | Q19: =SUM(Q2:Q18) -> 214 | R19: =S19/Q19 -> 6.099486 | S19: =ROUND(SUM(S2:S18),2) -> 1305.29 | T19: =SUM(T2:T18) -> -537317.13 | U19: =SUM(U2:U18) -> 50229.3 | V19: =SUM(V2:V18) -> 0 | W19: =SUM(W2:W18) -> 0 | X19: =SUM(X2:X18) -> 0 | Y19: =SUM(Y2:Y18) -> 0 | Z19: =SUM(Z2:Z18) -> 0 | AA19: =SUM(AA2:AA18) -> 0 | ... AK19: =SUM(AK2:AK18) -> 0 | AM19: =SUM(AM2:AM18) -> 0 | AN19: =SUM(AN2:AN18) -> 0 | AO19: =SUM(AO2:AO18) -> 0 | AP19: =SUM(AP2:AP18) -> 0 | AQ19: =SUM(AQ2:AQ18) -> 0 | AR19: =D19+E19+F19+G19+H19+I19+J19+M19+P19+S19+SUM(T19:AQ19) -> -368502.61 | AV19: CONSOLIDADO
A20: =A3+1 -> 46114 | B20: BLOCO SPOT
B21: Credito Vendas Cartão | AT21: Saidas | AU21: #REF!
B22: Desconto taxas Cartão | AT22: Saidas | AU22: #REF!
B23: Pix recebido maquininha
B24: Tarifa pix recebido maquinha
B25: BLOCO ITAU
B26: Pix e depositos Vendas
AS27: =#REF! -> #REF!
B28: BLOCO ESTOQUES
B29: Venda de Gasolina | AS29: =#REF! -> #REF!
B30: Venda de Etanol | AS30: =#REF! -> #REF!
B31: Venda de Diesel | AS31: =#REF! -> #REF!
B32: Separação Cartão/Outros | AS32: =#REF! -> #REF!
B33: Ajuste estoque e valor diário (lucro embutido) | AS33: =#REF! -> #REF!
AS34: =#REF! -> #REF!
B35: Saldo Giro no dia | C35: =D36+E36+F36+G36+H36+I36+J36+M36+P36 -> 117279.93 | AR35: =SUM($T19:AQ35) -> -487087.83 | AV35: TERCEIROS
B36: Saldo Líquido do dia | C36: =AR36 -> -368502.61 | D36: =SUM(D19:D35) -> 12717.607 | E36: =SUM(E19:E35) -> -43287.79 | F36: =SUM(F19:F35) -> 0.65 | G36: =SUM(G19:G35) -> 0 | H36: =SUM(H19:H35) -> 65082.293 | I36: =SUM(I19:I35) -> 10004.65 | J36: =SUM(J19:J35) -> 0 | K36: =SUM(K19:K35) -> 12170 | L36: =M36/K36 -> 5.1465924 | M36: =ROUND(SUM(M19:M35),2) -> 62634.03 | N36: =SUM(N19:N35) -> 2783 | O36: =P36/N36 -> 3.6394143 | P36: =ROUND(SUM(P19:P35),2) -> 10128.49 | Q36: =SUM(Q19:Q35) -> 214 | R36: =S36/Q36 -> 6.099486 | S36: =ROUND(SUM(S19:S35),2) -> 1305.29 | T36: =SUM(T19:T35) -> -537317.13 | U36: =SUM(U19:U35) -> 50229.3 | V36: =SUM(V19:V35) -> 0 | W36: =SUM(W19:W35) -> 0 | X36: =SUM(X19:X35) -> 0 | Y36: =SUM(Y19:Y35) -> 0 | Z36: =SUM(Z19:Z35) -> 0 | AA36: =SUM(AA19:AA35) -> 0 | ... AQ36: =SUM(AQ19:AQ35) -> 0 | AR36: =D36+E36+F36+G36+H36+I36+J36+M36+P36+S36+SUM(T36:AQ36) -> -368502.61 | AV36: CONSOLIDADO
A37: =A20+1 -> 46115 | B37: BLOCO SPOT
B38: Credito Vendas Cartão | AT38: Saidas | AU38: #REF!
B39: Desconto taxas Cartão | AT39: Saidas | AU39: #REF!
B40: Pix recebido maquininha
B41: Tarifa pix recebido maquinha
B42: BLOCO ITAU
B43: Pix e depositos Vendas
AS44: =#REF! -> #REF!
B45: BLOCO ESTOQUES
B46: Venda de Gasolina | AS46: =#REF! -> #REF!
B47: Venda de Etanol | AS47: =#REF! -> #REF!
B48: Venda de Diesel | AS48: =#REF! -> #REF!
B49: Separação Cartão/Outros | AS49: =#REF! -> #REF!
B50: Ajuste estoque e valor diário (lucro embutido) | AS50: =#REF! -> #REF!
AS51: =#REF! -> #REF!
B52: Saldo Giro no dia | C52: =D53+E53+F53+G53+H53+I53+J53+M53+P53 -> 117279.93 | AR52: =SUM($T36:AQ52) -> -487087.83 | AV52: TERCEIROS
B53: Saldo Líquido do dia | C53: =AR53 -> -368502.61 | D53: =SUM(D36:D52) -> 12717.607 | E53: =SUM(E36:E52) -> -43287.79 | F53: =SUM(F36:F52) -> 0.65 | G53: =SUM(G36:G52) -> 0 | H53: =SUM(H36:H52) -> 65082.293 | I53: =SUM(I36:I52) -> 10004.65 | J53: =SUM(J36:J52) -> 0 | K53: =SUM(K36:K52) -> 12170 | L53: =M53/K53 -> 5.1465924 | M53: =ROUND(SUM(M36:M52),2) -> 62634.03 | N53: =SUM(N36:N52) -> 2783 | O53: =P53/N53 -> 3.6394143 | P53: =ROUND(SUM(P36:P52),2) -> 10128.49 | Q53: =SUM(Q36:Q52) -> 214 | R53: =S53/Q53 -> 6.099486 | S53: =ROUND(SUM(S36:S52),2) -> 1305.29 | T53: =SUM(T36:T52) -> -537317.13 | U53: =SUM(U36:U52) -> 50229.3 | V53: =SUM(V36:V52) -> 0 | W53: =SUM(W36:W52) -> 0 | X53: =SUM(X36:X52) -> 0 | Y53: =SUM(Y36:Y52) -> 0 | Z53: =SUM(Z36:Z52) -> 0 | AA53: =SUM(AA36:AA52) -> 0 | ... AQ53: =SUM(AQ36:AQ52) -> 0 | AR53: =D53+E53+F53+G53+H53+I53+J53+M53+P53+S53+SUM(T53:AQ53) -> -368502.61 | AV53: CONSOLIDADO
A54: =A37+1 -> 46116 | B54: BLOCO SPOT
B55: Credito Vendas Cartão | AT55: Saidas | AU55: #REF!
B56: Desconto taxas Cartão | AT56: Saidas | AU56: #REF!
B57: Pix recebido maquininha
B58: Tarifa pix recebido maquinha
B59: BLOCO ITAU
B60: Pix e depositos Vendas
AS61: =#REF! -> #REF!
B62: BLOCO ESTOQUES
B63: Venda de Gasolina | AS63: =#REF! -> #REF!
B64: Venda de Etanol | AS64: =#REF! -> #REF!
B65: Venda de Diesel | AS65: =#REF! -> #REF!
B66: Separação Cartão/Outros | AS66: =#REF! -> #REF!
B67: Ajuste estoque e valor diário (lucro embutido) | AS67: =#REF! -> #REF!
AS68: =#REF! -> #REF!
B69: Saldo Giro no dia | C69: =D70+E70+F70+G70+H70+I70+J70+M70+P70 -> 117279.93 | AR69: =SUM($T53:AQ69) -> -487087.83 | AV69: TERCEIROS
B70: Saldo Líquido do dia | C70: =AR70 -> -368502.61 | D70: =SUM(D53:D69) -> 12717.607 | E70: =SUM(E53:E69) -> -43287.79 | F70: =SUM(F53:F69) -> 0.65 | G70: =SUM(G53:G69) -> 0 | H70: =SUM(H53:H69) -> 65082.293 | I70: =SUM(I53:I69) -> 10004.65 | J70: =SUM(J53:J69) -> 0 | K70: =SUM(K53:K69) -> 12170 | L70: =M70/K70 -> 5.1465924 | M70: =ROUND(SUM(M53:M69),2) -> 62634.03 | N70: =SUM(N53:N69) -> 2783 | O70: =P70/N70 -> 3.6394143 | P70: =ROUND(SUM(P53:P69),2) -> 10128.49 | Q70: =SUM(Q53:Q69) -> 214 | R70: =S70/Q70 -> 6.099486 | S70: =ROUND(SUM(S53:S69),2) -> 1305.29 | T70: =SUM(T53:T69) -> -537317.13 | U70: =SUM(U53:U69) -> 50229.3 | V70: =SUM(V53:V69) -> 0 | W70: =SUM(W53:W69) -> 0 | X70: =SUM(X53:X69) -> 0 | Y70: =SUM(Y53:Y69) -> 0 | Z70: =SUM(Z53:Z69) -> 0 | AA70: =SUM(AA53:AA69) -> 0 | ... AQ70: =SUM(AQ53:AQ69) -> 0 | AR70: =D70+E70+F70+G70+H70+I70+J70+M70+P70+S70+SUM(T70:AQ70) -> -368502.61 | AV70: CONSOLIDADO
A71: =A54+1 -> 46117 | B71: BLOCO SPOT
B72: Credito Vendas Cartão | AT72: Saidas | AU72: #REF!
B73: Desconto taxas Cartão | AT73: Saidas | AU73: #REF!
B74: Pix recebido maquininha
B75: Tarifa pix recebido maquinha
B76: BLOCO ITAU
B77: Pix e depositos Vendas
AS78: =#REF! -> #REF!
B79: BLOCO ESTOQUES
B80: Venda de Gasolina | AS80: =#REF! -> #REF!
B81: Venda de Etanol | AS81: =#REF! -> #REF!
B82: Venda de Diesel | AS82: =#REF! -> #REF!
B83: Separação Cartão/Outros | AS83: =#REF! -> #REF!
B84: Ajuste estoque e valor diário (lucro embutido) | AS84: =#REF! -> #REF!
AS85: =#REF! -> #REF!
B86: Saldo Giro no dia | C86: =D87+E87+F87+G87+H87+I87+J87+M87+P87 -> 117279.93 | AR86: =SUM($T70:AQ86) -> -487087.83 | AV86: TERCEIROS
B87: Saldo Líquido do dia | C87: =AR87 -> -368502.61 | D87: =SUM(D70:D86) -> 12717.607 | E87: =SUM(E70:E86) -> -43287.79 | F87: =SUM(F70:F86) -> 0.65 | G87: =SUM(G70:G86) -> 0 | H87: =SUM(H70:H86) -> 65082.293 | I87: =SUM(I70:I86) -> 10004.65 | J87: =SUM(J70:J86) -> 0 | K87: =SUM(K70:K86) -> 12170 | L87: =M87/K87 -> 5.1465924 | M87: =ROUND(SUM(M70:M86),2) -> 62634.03 | N87: =SUM(N70:N86) -> 2783 | O87: =P87/N87 -> 3.6394143 | P87: =ROUND(SUM(P70:P86),2) -> 10128.49 | Q87: =SUM(Q70:Q86) -> 214 | R87: =S87/Q87 -> 6.099486 | S87: =ROUND(SUM(S70:S86),2) -> 1305.29 | T87: =SUM(T70:T86) -> -537317.13 | U87: =SUM(U70:U86) -> 50229.3 | V87: =SUM(V70:V86) -> 0 | W87: =SUM(W70:W86) -> 0 | X87: =SUM(X70:X86) -> 0 | Y87: =SUM(Y70:Y86) -> 0 | Z87: =SUM(Z70:Z86) -> 0 | AA87: =SUM(AA70:AA86) -> 0 | ... AQ87: =SUM(AQ70:AQ86) -> 0 | AR87: =D87+E87+F87+G87+H87+I87+J87+M87+P87+S87+SUM(T87:AQ87) -> -368502.61 | AV87: CONSOLIDADO
A88: =A71+1 -> 46118 | B88: BLOCO SPOT
B89: Credito Vendas Cartão | AT89: Saidas | AU89: #REF!
B90: Desconto taxas Cartão | AT90: Saidas | AU90: #REF!
B91: Pix recebido maquininha
B92: Tarifa pix recebido maquinha
B93: BLOCO ITAU
B94: Pix e depositos Vendas
AS95: =#REF! -> #REF!
B96: BLOCO ESTOQUES
B97: Venda de Gasolina | AS97: =#REF! -> #REF!
B98: Venda de Etanol | AS98: =#REF! -> #REF!
B99: Venda de Diesel | AS99: =#REF! -> #REF!
B100: Separação Cartão/Outros | AS100: =#REF! -> #REF!
...

Sheet Mai26
A1: PERÍODO 01 á 31/MAI/26 | C1: =D2+E2+F2+G2+H2+I2+J2+M2+P2 -> 117279.93 | D1: SPOT | E1: ITAU | F1: LUCILA | G1: HADEN | H1: CAIXA | I1: CARTAO | J1: VENDAS | K1: GASOLINA | N1: ETANOL | Q1: DIESEL | T1: ERALDO | U1: LUIZ F. | V1: LUCILA | W1: DIVIDA | X1: AVANT | Y1: WL | AR1: Total | AS1: Saldo Total | AT1: Saldo Edson | AU1: Saldo Master
B2: Saldo Inicial do dia | C2: =D2+E2+F2+G2+H2+I2+J2+M2+P2+SUM(T2:AQ2) -> -369807.9 | D2: ='Abr26'!D529 -> 12717.607 | E2: ='Abr26'!E529 -> -43287.79 | F2: ='Abr26'!F529 -> 0.65 | G2: ='Abr26'!G529 -> 0 | H2: ='Abr26'!H529 -> 65082.293 | I2: ='Abr26'!I529 -> 10004.65 | J2: ='Abr26'!J529 -> 0 | K2: ='Abr26'!K529 -> 12170 | ... AR2: ='Abr26'!AR529 -> -368502.61 | AS2: =#REF! -> #REF! | AT2: =#REF! -> #REF! | AU2: =AS2-AT2 -> #REF!
A3: 46143 | B3: BLOCO SPOT
B4: Credito Vendas Cartão | AT4: Saidas | AU4: #REF!
B5: Desconto taxas Cartão | AT5: Saidas | AU5: #REF!
B6: Pix recebido maquininha
B7: Tarifa pix recebido maquinha
B8: BLOCO ITAU
B9: Pix e depositos Vendas
AS10: =#REF! -> #REF!
B11: BLOCO ESTOQUES
B12: Venda de Gasolina | AS12: =#REF! -> #REF!
B13: Venda de Etanol | AS13: =#REF! -> #REF!
B14: Venda de Diesel | AS14: =#REF! -> #REF!
B15: Separação Cartão/Outros | AS15: =#REF! -> #REF!
B16: Ajuste estoque e valor diário (lucro embutido) | AS16: =#REF! -> #REF!
AS17: =#REF! -> #REF!
B18: Saldo Giro no dia | C18: =D19+E19+F19+G19+H19+I19+J19+M19+P19+S19 -> 118585.22 | AR18: =SUM($T2:AQ18) -> -487087.83 | AV18: TERCEIROS
B19: Saldo Líquido do dia | C19: =AR19 -> -368502.61 | D19: =SUM(D2:D18) -> 12717.607 | E19: =SUM(E2:E18) -> -43287.79 | F19: =SUM(F2:F18) -> 0.65 | G19: =SUM(G2:G18) -> 0 | H19: =SUM(H2:H18) -> 65082.293 | I19: =SUM(I2:I18) -> 10004.65 | J19: =SUM(J2:J18) -> 0 | K19: =SUM(K2:K18) -> 12170 | L19: =M19/K19 -> 5.1465924 | M19: =ROUND(SUM(M2:M18),2) -> 62634.03 | N19: =SUM(N2:N18) -> 2783 | O19: =P19/N19 -> 3.6394143 | P19: =ROUND(SUM(P2:P18),2) -> 10128.49 | Q19: =SUM(Q2:Q18) -> 214 | R19: =S19/Q19 -> 6.099486 | S19: =ROUND(SUM(S2:S18),2) -> 1305.29 | T19: =SUM(T2:T18) -> -537317.13 | U19: =SUM(U2:U18) -> 50229.3 | V19: =SUM(V2:V18) -> 0 | W19: =SUM(W2:W18) -> 0 | X19: =SUM(X2:X18) -> 0 | Y19: =SUM(Y2:Y18) -> 0 | Z19: =SUM(Z2:Z18) -> 0 | AA19: =SUM(AA2:AA18) -> 0 | ... AK19: =SUM(AK2:AK18) -> 0 | AM19: =SUM(AM2:AM18) -> 0 | AN19: =SUM(AN2:AN18) -> 0 | AO19: =SUM(AO2:AO18) -> 0 | AP19: =SUM(AP2:AP18) -> 0 | AQ19: =SUM(AQ2:AQ18) -> 0 | AR19: =D19+E19+F19+G19+H19+I19+J19+M19+P19+S19+SUM(T19:AQ19) -> -368502.61 | AV19: CONSOLIDADO
A20: =A3+1 -> 46144 | B20: BLOCO SPOT
B21: Credito Vendas Cartão | AT21: Saidas | AU21: #REF!
B22: Desconto taxas Cartão | AT22: Saidas | AU22: #REF!
B23: Pix recebido maquininha
B24: Tarifa pix recebido maquinha
B25: BLOCO ITAU
B26: Pix e depositos Vendas
AS27: =#REF! -> #REF!
B28: BLOCO ESTOQUES
B29: Venda de Gasolina | AS29: =#REF! -> #REF!
B30: Venda de Etanol | AS30: =#REF! -> #REF!
B31: Venda de Diesel | AS31: =#REF! -> #REF!
B32: Separação Cartão/Outros | AS32: =#REF! -> #REF!
B33: Ajuste estoque e valor diário (lucro embutido) | AS33: =#REF! -> #REF!
AS34: =#REF! -> #REF!
B35: Saldo Giro no dia | C35: =D36+E36+F36+G36+H36+I36+J36+M36+P36 -> 117279.93 | AR35: =SUM($T19:AQ35) -> -487087.83 | AV35: TERCEIROS
B36: Saldo Líquido do dia | C36: =AR36 -> -368502.61 | D36: =SUM(D19:D35) -> 12717.607 | E36: =SUM(E19:E35) -> -43287.79 | F36: =SUM(F19:F35) -> 0.65 | G36: =SUM(G19:G35) -> 0 | H36: =SUM(H19:H35) -> 65082.293 | I36: =SUM(I19:I35) -> 10004.65 | J36: =SUM(J19:J35) -> 0 | K36: =SUM(K19:K35) -> 12170 | L36: =M36/K36 -> 5.1465924 | M36: =ROUND(SUM(M19:M35),2) -> 62634.03 | N36: =SUM(N19:N35) -> 2783 | O36: =P36/N36 -> 3.6394143 | P36: =ROUND(SUM(P19:P35),2) -> 10128.49 | Q36: =SUM(Q19:Q35) -> 214 | R36: =S36/Q36 -> 6.099486 | S36: =ROUND(SUM(S19:S35),2) -> 1305.29 | T36: =SUM(T19:T35) -> -537317.13 | U36: =SUM(U19:U35) -> 50229.3 | V36: =SUM(V19:V35) -> 0 | W36: =SUM(W19:W35) -> 0 | X36: =SUM(X19:X35) -> 0 | Y36: =SUM(Y19:Y35) -> 0 | Z36: =SUM(Z19:Z35) -> 0 | AA36: =SUM(AA19:AA35) -> 0 | ... AQ36: =SUM(AQ19:AQ35) -> 0 | AR36: =D36+E36+F36+G36+H36+I36+J36+M36+P36+S36+SUM(T36:AQ36) -> -368502.61 | AV36: CONSOLIDADO
A37: =A20+1 -> 46145 | B37: BLOCO SPOT
B38: Credito Vendas Cartão | AT38: Saidas | AU38: #REF!
B39: Desconto taxas Cartão | AT39: Saidas | AU39: #REF!
B40: Pix recebido maquininha
B41: Tarifa pix recebido maquinha
B42: BLOCO ITAU
B43: Pix e depositos Vendas
AS44: =#REF! -> #REF!
B45: BLOCO ESTOQUES
B46: Venda de Gasolina | AS46: =#REF! -> #REF!
B47: Venda de Etanol | AS47: =#REF! -> #REF!
B48: Venda de Diesel | AS48: =#REF! -> #REF!
B49: Separação Cartão/Outros | AS49: =#REF! -> #REF!
B50: Ajuste estoque e valor diário (lucro embutido) | AS50: =#REF! -> #REF!
AS51: =#REF! -> #REF!
B52: Saldo Giro no dia | C52: =D53+E53+F53+G53+H53+I53+J53+M53+P53 -> 117279.93 | AR52: =SUM($T36:AQ52) -> -487087.83 | AV52: TERCEIROS
B53: Saldo Líquido do dia | C53: =AR53 -> -368502.61 | D53: =SUM(D36:D52) -> 12717.607 | E53: =SUM(E36:E52) -> -43287.79 | F53: =SUM(F36:F52) -> 0.65 | G53: =SUM(G36:G52) -> 0 | H53: =SUM(H36:H52) -> 65082.293 | I53: =SUM(I36:I52) -> 10004.65 | J53: =SUM(J36:J52) -> 0 | K53: =SUM(K36:K52) -> 12170 | L53: =M53/K53 -> 5.1465924 | M53: =ROUND(SUM(M36:M52),2) -> 62634.03 | N53: =SUM(N36:N52) -> 2783 | O53: =P53/N53 -> 3.6394143 | P53: =ROUND(SUM(P36:P52),2) -> 10128.49 | Q53: =SUM(Q36:Q52) -> 214 | R53: =S53/Q53 -> 6.099486 | S53: =ROUND(SUM(S36:S52),2) -> 1305.29 | T53: =SUM(T36:T52) -> -537317.13 | U53: =SUM(U36:U52) -> 50229.3 | V53: =SUM(V36:V52) -> 0 | W53: =SUM(W36:W52) -> 0 | X53: =SUM(X36:X52) -> 0 | Y53: =SUM(Y36:Y52) -> 0 | Z53: =SUM(Z36:Z52) -> 0 | AA53: =SUM(AA36:AA52) -> 0 | ... AQ53: =SUM(AQ36:AQ52) -> 0 | AR53: =D53+E53+F53+G53+H53+I53+J53+M53+P53+S53+SUM(T53:AQ53) -> -368502.61 | AV53: CONSOLIDADO
A54: =A37+1 -> 46146 | B54: BLOCO SPOT
B55: Credito Vendas Cartão | AT55: Saidas | AU55: #REF!
B56: Desconto taxas Cartão | AT56: Saidas | AU56: #REF!
B57: Pix recebido maquininha
B58: Tarifa pix recebido maquinha
B59: BLOCO ITAU
B60: Pix e depositos Vendas
AS61: =#REF! -> #REF!
B62: BLOCO ESTOQUES
B63: Venda de Gasolina | AS63: =#REF! -> #REF!
B64: Venda de Etanol | AS64: =#REF! -> #REF!
B65: Venda de Diesel | AS65: =#REF! -> #REF!
B66: Separação Cartão/Outros | AS66: =#REF! -> #REF!
B67: Ajuste estoque e valor diário (lucro embutido) | AS67: =#REF! -> #REF!
AS68: =#REF! -> #REF!
B69: Saldo Giro no dia | C69: =D70+E70+F70+G70+H70+I70+J70+M70+P70 -> 117279.93 | AR69: =SUM($T53:AQ69) -> -487087.83 | AV69: TERCEIROS
B70: Saldo Líquido do dia | C70: =AR70 -> -368502.61 | D70: =SUM(D53:D69) -> 12717.607 | E70: =SUM(E53:E69) -> -43287.79 | F70: =SUM(F53:F69) -> 0.65 | G70: =SUM(G53:G69) -> 0 | H70: =SUM(H53:H69) -> 65082.293 | I70: =SUM(I53:I69) -> 10004.65 | J70: =SUM(J53:J69) -> 0 | K70: =SUM(K53:K69) -> 12170 | L70: =M70/K70 -> 5.1465924 | M70: =ROUND(SUM(M53:M69),2) -> 62634.03 | N70: =SUM(N53:N69) -> 2783 | O70: =P70/N70 -> 3.6394143 | P70: =ROUND(SUM(P53:P69),2) -> 10128.49 | Q70: =SUM(Q53:Q69) -> 214 | R70: =S70/Q70 -> 6.099486 | S70: =ROUND(SUM(S53:S69),2) -> 1305.29 | T70: =SUM(T53:T69) -> -537317.13 | U70: =SUM(U53:U69) -> 50229.3 | V70: =SUM(V53:V69) -> 0 | W70: =SUM(W53:W69) -> 0 | X70: =SUM(X53:X69) -> 0 | Y70: =SUM(Y53:Y69) -> 0 | Z70: =SUM(Z53:Z69) -> 0 | AA70: =SUM(AA53:AA69) -> 0 | ... AQ70: =SUM(AQ53:AQ69) -> 0 | AR70: =D70+E70+F70+G70+H70+I70+J70+M70+P70+S70+SUM(T70:AQ70) -> -368502.61 | AV70: CONSOLIDADO
A71: =A54+1 -> 46147 | B71: BLOCO SPOT
B72: Credito Vendas Cartão | AT72: Saidas | AU72: #REF!
B73: Desconto taxas Cartão | AT73: Saidas | AU73: #REF!
B74: Pix recebido maquininha
B75: Tarifa pix recebido maquinha
B76: BLOCO ITAU
B77: Pix e depositos Vendas
AS78: =#REF! -> #REF!
B79: BLOCO ESTOQUES
B80: Venda de Gasolina | AS80: =#REF! -> #REF!
B81: Venda de Etanol | AS81: =#REF! -> #REF!
B82: Venda de Diesel | AS82: =#REF! -> #REF!
B83: Separação Cartão/Outros | AS83: =#REF! -> #REF!
B84: Ajuste estoque e valor diário (lucro embutido) | AS84: =#REF! -> #REF!
AS85: =#REF! -> #REF!
B86: Saldo Giro no dia | C86: =D87+E87+F87+G87+H87+I87+J87+M87+P87 -> 117279.93 | AR86: =SUM($T70:AQ86) -> -487087.83 | AV86: TERCEIROS
B87: Saldo Líquido do dia | C87: =AR87 -> -368502.61 | D87: =SUM(D70:D86) -> 12717.607 | E87: =SUM(E70:E86) -> -43287.79 | F87: =SUM(F70:F86) -> 0.65 | G87: =SUM(G70:G86) -> 0 | H87: =SUM(H70:H86) -> 65082.293 | I87: =SUM(I70:I86) -> 10004.65 | J87: =SUM(J70:J86) -> 0 | K87: =SUM(K70:K86) -> 12170 | L87: =M87/K87 -> 5.1465924 | M87: =ROUND(SUM(M70:M86),2) -> 62634.03 | N87: =SUM(N70:N86) -> 2783 | O87: =P87/N87 -> 3.6394143 | P87: =ROUND(SUM(P70:P86),2) -> 10128.49 | Q87: =SUM(Q70:Q86) -> 214 | R87: =S87/Q87 -> 6.099486 | S87: =ROUND(SUM(S70:S86),2) -> 1305.29 | T87: =SUM(T70:T86) -> -537317.13 | U87: =SUM(U70:U86) -> 50229.3 | V87: =SUM(V70:V86) -> 0 | W87: =SUM(W70:W86) -> 0 | X87: =SUM(X70:X86) -> 0 | Y87: =SUM(Y70:Y86) -> 0 | Z87: =SUM(Z70:Z86) -> 0 | AA87: =SUM(AA70:AA86) -> 0 | ... AQ87: =SUM(AQ70:AQ86) -> 0 | AR87: =D87+E87+F87+G87+H87+I87+J87+M87+P87+S87+SUM(T87:AQ87) -> -368502.61 | AV87: CONSOLIDADO
A88: =A71+1 -> 46148 | B88: BLOCO SPOT
B89: Credito Vendas Cartão | AT89: Saidas | AU89: #REF!
B90: Desconto taxas Cartão | AT90: Saidas | AU90: #REF!
B91: Pix recebido maquininha
B92: Tarifa pix recebido maquinha
B93: BLOCO ITAU
B94: Pix e depositos Vendas
AS95: =#REF! -> #REF!
B96: BLOCO ESTOQUES
B97: Venda de Gasolina | AS97: =#REF! -> #REF!
B98: Venda de Etanol | AS98: =#REF! -> #REF!
B99: Venda de Diesel | AS99: =#REF! -> #REF!
B100: Separação Cartão/Outros | AS100: =#REF! -> #REF!
...

Sheet Jun26
A1: PERÍODO 01 á 30/JUN/26 | C1: =D2+E2+F2+G2+H2+I2+J2+M2+P2 -> 117279.93 | D1: SPOT | E1: ITAU | F1: LUCILA | G1: HADEN | H1: CAIXA | I1: CARTAO | J1: VENDAS | K1: GASOLINA | N1: ETANOL | Q1: DIESEL | T1: ERALDO | U1: LUIZ F. | V1: LUCILA | W1: DIVIDA | X1: AVANT | Y1: WL | AR1: Total | AS1: Saldo Total | AT1: Saldo Edson | AU1: Saldo Master
B2: Saldo Inicial do dia | C2: =D2+E2+F2+G2+H2+I2+J2+M2+P2+SUM(T2:AQ2) -> -369807.9 | D2: ='Mai26'!D529 -> 12717.607 | E2: ='Mai26'!E529 -> -43287.79 | F2: ='Mai26'!F529 -> 0.65 | G2: ='Mai26'!G529 -> 0 | H2: ='Mai26'!H529 -> 65082.293 | I2: ='Mai26'!I529 -> 10004.65 | J2: ='Mai26'!J529 -> 0 | K2: ='Mai26'!K529 -> 12170 | ... AR2: ='Mai26'!AR529 -> -368502.61 | AS2: =#REF! -> #REF! | AT2: =#REF! -> #REF! | AU2: =AS2-AT2 -> #REF!
A3: 46174 | B3: BLOCO SPOT
B4: Credito Vendas Cartão | AT4: Saidas | AU4: #REF!
B5: Desconto taxas Cartão | AT5: Saidas | AU5: #REF!
B6: Pix recebido maquininha
B7: Tarifa pix recebido maquinha
B8: BLOCO ITAU
B9: Pix e depositos Vendas
AS10: =#REF! -> #REF!
B11: BLOCO ESTOQUES
B12: Venda de Gasolina | AS12: =#REF! -> #REF!
B13: Venda de Etanol | AS13: =#REF! -> #REF!
B14: Venda de Diesel | AS14: =#REF! -> #REF!
B15: Separação Cartão/Outros | AS15: =#REF! -> #REF!
B16: Ajuste estoque e valor diário (lucro embutido) | AS16: =#REF! -> #REF!
AS17: =#REF! -> #REF!
B18: Saldo Giro no dia | C18: =D19+E19+F19+G19+H19+I19+J19+M19+P19+S19 -> 118585.22 | AR18: =SUM($T2:AQ18) -> -487087.83 | AV18: TERCEIROS
B19: Saldo Líquido do dia | C19: =AR19 -> -368502.61 | D19: =SUM(D2:D18) -> 12717.607 | E19: =SUM(E2:E18) -> -43287.79 | F19: =SUM(F2:F18) -> 0.65 | G19: =SUM(G2:G18) -> 0 | H19: =SUM(H2:H18) -> 65082.293 | I19: =SUM(I2:I18) -> 10004.65 | J19: =SUM(J2:J18) -> 0 | K19: =SUM(K2:K18) -> 12170 | L19: =M19/K19 -> 5.1465924 | M19: =ROUND(SUM(M2:M18),2) -> 62634.03 | N19: =SUM(N2:N18) -> 2783 | O19: =P19/N19 -> 3.6394143 | P19: =ROUND(SUM(P2:P18),2) -> 10128.49 | Q19: =SUM(Q2:Q18) -> 214 | R19: =S19/Q19 -> 6.099486 | S19: =ROUND(SUM(S2:S18),2) -> 1305.29 | T19: =SUM(T2:T18) -> -537317.13 | U19: =SUM(U2:U18) -> 50229.3 | V19: =SUM(V2:V18) -> 0 | W19: =SUM(W2:W18) -> 0 | X19: =SUM(X2:X18) -> 0 | Y19: =SUM(Y2:Y18) -> 0 | Z19: =SUM(Z2:Z18) -> 0 | AA19: =SUM(AA2:AA18) -> 0 | ... AK19: =SUM(AK2:AK18) -> 0 | AM19: =SUM(AM2:AM18) -> 0 | AN19: =SUM(AN2:AN18) -> 0 | AO19: =SUM(AO2:AO18) -> 0 | AP19: =SUM(AP2:AP18) -> 0 | AQ19: =SUM(AQ2:AQ18) -> 0 | AR19: =D19+E19+F19+G19+H19+I19+J19+M19+P19+S19+SUM(T19:AQ19) -> -368502.61 | AV19: CONSOLIDADO
A20: =A3+1 -> 46175 | B20: BLOCO SPOT
B21: Credito Vendas Cartão | AT21: Saidas | AU21: #REF!
B22: Desconto taxas Cartão | AT22: Saidas | AU22: #REF!
B23: Pix recebido maquininha
B24: Tarifa pix recebido maquinha
B25: BLOCO ITAU
B26: Pix e depositos Vendas
AS27: =#REF! -> #REF!
B28: BLOCO ESTOQUES
B29: Venda de Gasolina | AS29: =#REF! -> #REF!
B30: Venda de Etanol | AS30: =#REF! -> #REF!
B31: Venda de Diesel | AS31: =#REF! -> #REF!
B32: Separação Cartão/Outros | AS32: =#REF! -> #REF!
B33: Ajuste estoque e valor diário (lucro embutido) | AS33: =#REF! -> #REF!
AS34: =#REF! -> #REF!
B35: Saldo Giro no dia | C35: =D36+E36+F36+G36+H36+I36+J36+M36+P36 -> 117279.93 | AR35: =SUM($T19:AQ35) -> -487087.83 | AV35: TERCEIROS
B36: Saldo Líquido do dia | C36: =AR36 -> -368502.61 | D36: =SUM(D19:D35) -> 12717.607 | E36: =SUM(E19:E35) -> -43287.79 | F36: =SUM(F19:F35) -> 0.65 | G36: =SUM(G19:G35) -> 0 | H36: =SUM(H19:H35) -> 65082.293 | I36: =SUM(I19:I35) -> 10004.65 | J36: =SUM(J19:J35) -> 0 | K36: =SUM(K19:K35) -> 12170 | L36: =M36/K36 -> 5.1465924 | M36: =ROUND(SUM(M19:M35),2) -> 62634.03 | N36: =SUM(N19:N35) -> 2783 | O36: =P36/N36 -> 3.6394143 | P36: =ROUND(SUM(P19:P35),2) -> 10128.49 | Q36: =SUM(Q19:Q35) -> 214 | R36: =S36/Q36 -> 6.099486 | S36: =ROUND(SUM(S19:S35),2) -> 1305.29 | T36: =SUM(T19:T35) -> -537317.13 | U36: =SUM(U19:U35) -> 50229.3 | V36: =SUM(V19:V35) -> 0 | W36: =SUM(W19:W35) -> 0 | X36: =SUM(X19:X35) -> 0 | Y36: =SUM(Y19:Y35) -> 0 | Z36: =SUM(Z19:Z35) -> 0 | AA36: =SUM(AA19:AA35) -> 0 | ... AQ36: =SUM(AQ19:AQ35) -> 0 | AR36: =D36+E36+F36+G36+H36+I36+J36+M36+P36+S36+SUM(T36:AQ36) -> -368502.61 | AV36: CONSOLIDADO
A37: =A20+1 -> 46176 | B37: BLOCO SPOT
B38: Credito Vendas Cartão | AT38: Saidas | AU38: #REF!
B39: Desconto taxas Cartão | AT39: Saidas | AU39: #REF!
B40: Pix recebido maquininha
B41: Tarifa pix recebido maquinha
B42: BLOCO ITAU
B43: Pix e depositos Vendas
AS44: =#REF! -> #REF!
B45: BLOCO ESTOQUES
B46: Venda de Gasolina | AS46: =#REF! -> #REF!
B47: Venda de Etanol | AS47: =#REF! -> #REF!
B48: Venda de Diesel | AS48: =#REF! -> #REF!
B49: Separação Cartão/Outros | AS49: =#REF! -> #REF!
B50: Ajuste estoque e valor diário (lucro embutido) | AS50: =#REF! -> #REF!
AS51: =#REF! -> #REF!
B52: Saldo Giro no dia | C52: =D53+E53+F53+G53+H53+I53+J53+M53+P53 -> 117279.93 | AR52: =SUM($T36:AQ52) -> -487087.83 | AV52: TERCEIROS
B53: Saldo Líquido do dia | C53: =AR53 -> -368502.61 | D53: =SUM(D36:D52) -> 12717.607 | E53: =SUM(E36:E52) -> -43287.79 | F53: =SUM(F36:F52) -> 0.65 | G53: =SUM(G36:G52) -> 0 | H53: =SUM(H36:H52) -> 65082.293 | I53: =SUM(I36:I52) -> 10004.65 | J53: =SUM(J36:J52) -> 0 | K53: =SUM(K36:K52) -> 12170 | L53: =M53/K53 -> 5.1465924 | M53: =ROUND(SUM(M36:M52),2) -> 62634.03 | N53: =SUM(N36:N52) -> 2783 | O53: =P53/N53 -> 3.6394143 | P53: =ROUND(SUM(P36:P52),2) -> 10128.49 | Q53: =SUM(Q36:Q52) -> 214 | R53: =S53/Q53 -> 6.099486 | S53: =ROUND(SUM(S36:S52),2) -> 1305.29 | T53: =SUM(T36:T52) -> -537317.13 | U53: =SUM(U36:U52) -> 50229.3 | V53: =SUM(V36:V52) -> 0 | W53: =SUM(W36:W52) -> 0 | X53: =SUM(X36:X52) -> 0 | Y53: =SUM(Y36:Y52) -> 0 | Z53: =SUM(Z36:Z52) -> 0 | AA53: =SUM(AA36:AA52) -> 0 | ... AQ53: =SUM(AQ36:AQ52) -> 0 | AR53: =D53+E53+F53+G53+H53+I53+J53+M53+P53+S53+SUM(T53:AQ53) -> -368502.61 | AV53: CONSOLIDADO
A54: =A37+1 -> 46177 | B54: BLOCO SPOT
B55: Credito Vendas Cartão | AT55: Saidas | AU55: #REF!
B56: Desconto taxas Cartão | AT56: Saidas | AU56: #REF!
B57: Pix recebido maquininha
B58: Tarifa pix recebido maquinha
B59: BLOCO ITAU
B60: Pix e depositos Vendas
AS61: =#REF! -> #REF!
B62: BLOCO ESTOQUES
B63: Venda de Gasolina | AS63: =#REF! -> #REF!
B64: Venda de Etanol | AS64: =#REF! -> #REF!
B65: Venda de Diesel | AS65: =#REF! -> #REF!
B66: Separação Cartão/Outros | AS66: =#REF! -> #REF!
B67: Ajuste estoque e valor diário (lucro embutido) | AS67: =#REF! -> #REF!
AS68: =#REF! -> #REF!
B69: Saldo Giro no dia | C69: =D70+E70+F70+G70+H70+I70+J70+M70+P70 -> 117279.93 | AR69: =SUM($T53:AQ69) -> -487087.83 | AV69: TERCEIROS
B70: Saldo Líquido do dia | C70: =AR70 -> -368502.61 | D70: =SUM(D53:D69) -> 12717.607 | E70: =SUM(E53:E69) -> -43287.79 | F70: =SUM(F53:F69) -> 0.65 | G70: =SUM(G53:G69) -> 0 | H70: =SUM(H53:H69) -> 65082.293 | I70: =SUM(I53:I69) -> 10004.65 | J70: =SUM(J53:J69) -> 0 | K70: =SUM(K53:K69) -> 12170 | L70: =M70/K70 -> 5.1465924 | M70: =ROUND(SUM(M53:M69),2) -> 62634.03 | N70: =SUM(N53:N69) -> 2783 | O70: =P70/N70 -> 3.6394143 | P70: =ROUND(SUM(P53:P69),2) -> 10128.49 | Q70: =SUM(Q53:Q69) -> 214 | R70: =S70/Q70 -> 6.099486 | S70: =ROUND(SUM(S53:S69),2) -> 1305.29 | T70: =SUM(T53:T69) -> -537317.13 | U70: =SUM(U53:U69) -> 50229.3 | V70: =SUM(V53:V69) -> 0 | W70: =SUM(W53:W69) -> 0 | X70: =SUM(X53:X69) -> 0 | Y70: =SUM(Y53:Y69) -> 0 | Z70: =SUM(Z53:Z69) -> 0 | AA70: =SUM(AA53:AA69) -> 0 | ... AQ70: =SUM(AQ53:AQ69) -> 0 | AR70: =D70+E70+F70+G70+H70+I70+J70+M70+P70+S70+SUM(T70:AQ70) -> -368502.61 | AV70: CONSOLIDADO
A71: =A54+1 -> 46178 | B71: BLOCO SPOT
B72: Credito Vendas Cartão | AT72: Saidas | AU72: #REF!
B73: Desconto taxas Cartão | AT73: Saidas | AU73: #REF!
B74: Pix recebido maquininha
B75: Tarifa pix recebido maquinha
B76: BLOCO ITAU
B77: Pix e depositos Vendas
AS78: =#REF! -> #REF!
B79: BLOCO ESTOQUES
B80: Venda de Gasolina | AS80: =#REF! -> #REF!
B81: Venda de Etanol | AS81: =#REF! -> #REF!
B82: Venda de Diesel | AS82: =#REF! -> #REF!
B83: Separação Cartão/Outros | AS83: =#REF! -> #REF!
B84: Ajuste estoque e valor diário (lucro embutido) | AS84: =#REF! -> #REF!
AS85: =#REF! -> #REF!
B86: Saldo Giro no dia | C86: =D87+E87+F87+G87+H87+I87+J87+M87+P87 -> 117279.93 | AR86: =SUM($T70:AQ86) -> -487087.83 | AV86: TERCEIROS
B87: Saldo Líquido do dia | C87: =AR87 -> -368502.61 | D87: =SUM(D70:D86) -> 12717.607 | E87: =SUM(E70:E86) -> -43287.79 | F87: =SUM(F70:F86) -> 0.65 | G87: =SUM(G70:G86) -> 0 | H87: =SUM(H70:H86) -> 65082.293 | I87: =SUM(I70:I86) -> 10004.65 | J87: =SUM(J70:J86) -> 0 | K87: =SUM(K70:K86) -> 12170 | L87: =M87/K87 -> 5.1465924 | M87: =ROUND(SUM(M70:M86),2) -> 62634.03 | N87: =SUM(N70:N86) -> 2783 | O87: =P87/N87 -> 3.6394143 | P87: =ROUND(SUM(P70:P86),2) -> 10128.49 | Q87: =SUM(Q70:Q86) -> 214 | R87: =S87/Q87 -> 6.099486 | S87: =ROUND(SUM(S70:S86),2) -> 1305.29 | T87: =SUM(T70:T86) -> -537317.13 | U87: =SUM(U70:U86) -> 50229.3 | V87: =SUM(V70:V86) -> 0 | W87: =SUM(W70:W86) -> 0 | X87: =SUM(X70:X86) -> 0 | Y87: =SUM(Y70:Y86) -> 0 | Z87: =SUM(Z70:Z86) -> 0 | AA87: =SUM(AA70:AA86) -> 0 | ... AQ87: =SUM(AQ70:AQ86) -> 0 | AR87: =D87+E87+F87+G87+H87+I87+J87+M87+P87+S87+SUM(T87:AQ87) -> -368502.61 | AV87: CONSOLIDADO
A88: =A71+1 -> 46179 | B88: BLOCO SPOT
B89: Credito Vendas Cartão | AT89: Saidas | AU89: #REF!
B90: Desconto taxas Cartão | AT90: Saidas | AU90: #REF!
B91: Pix recebido maquininha
B92: Tarifa pix recebido maquinha
B93: BLOCO ITAU
B94: Pix e depositos Vendas
AS95: =#REF! -> #REF!
B96: BLOCO ESTOQUES
B97: Venda de Gasolina | AS97: =#REF! -> #REF!
B98: Venda de Etanol | AS98: =#REF! -> #REF!
B99: Venda de Diesel | AS99: =#REF! -> #REF!
B100: Separação Cartão/Outros | AS100: =#REF! -> #REF!
...

Sheet Jul26
A1: PERÍODO 01 á 31/JUL/26 | C1: =D2+E2+F2+G2+H2+I2+J2+M2+P2 -> 117279.93 | D1: SPOT | E1: ITAU | F1: LUCILA | G1: HADEN | H1: CAIXA | I1: CARTAO | J1: VENDAS | K1: GASOLINA | N1: ETANOL | Q1: DIESEL | T1: ERALDO | U1: LUIZ F. | V1: LUCILA | W1: DIVIDA | X1: AVANT | Y1: WL | AR1: Total | AS1: Saldo Total | AT1: Saldo Edson | AU1: Saldo Master
B2: Saldo Inicial do dia | C2: =D2+E2+F2+G2+H2+I2+J2+M2+P2+SUM(T2:AQ2) -> -369807.9 | D2: ='Jun26'!D529 -> 12717.607 | E2: ='Jun26'!E529 -> -43287.79 | F2: ='Jun26'!F529 -> 0.65 | G2: ='Jun26'!G529 -> 0 | H2: ='Jun26'!H529 -> 65082.293 | I2: ='Jun26'!I529 -> 10004.65 | J2: ='Jun26'!J529 -> 0 | K2: ='Jun26'!K529 -> 12170 | ... AR2: ='Jun26'!AR529 -> -368502.61 | AS2: =#REF! -> #REF! | AT2: =#REF! -> #REF! | AU2: =AS2-AT2 -> #REF!
A3: 46204 | B3: BLOCO SPOT
B4: Credito Vendas Cartão | AT4: Saidas | AU4: #REF!
B5: Desconto taxas Cartão | AT5: Saidas | AU5: #REF!
B6: Pix recebido maquininha
B7: Tarifa pix recebido maquinha
B8: BLOCO ITAU
B9: Pix e depositos Vendas
AS10: =#REF! -> #REF!
B11: BLOCO ESTOQUES
B12: Venda de Gasolina | AS12: =#REF! -> #REF!
B13: Venda de Etanol | AS13: =#REF! -> #REF!
B14: Venda de Diesel | AS14: =#REF! -> #REF!
B15: Separação Cartão/Outros | AS15: =#REF! -> #REF!
B16: Ajuste estoque e valor diário (lucro embutido) | AS16: =#REF! -> #REF!
AS17: =#REF! -> #REF!
B18: Saldo Giro no dia | C18: =D19+E19+F19+G19+H19+I19+J19+M19+P19+S19 -> 118585.22 | AR18: =SUM($T2:AQ18) -> -487087.83 | AV18: TERCEIROS
B19: Saldo Líquido do dia | C19: =AR19 -> -368502.61 | D19: =SUM(D2:D18) -> 12717.607 | E19: =SUM(E2:E18) -> -43287.79 | F19: =SUM(F2:F18) -> 0.65 | G19: =SUM(G2:G18) -> 0 | H19: =SUM(H2:H18) -> 65082.293 | I19: =SUM(I2:I18) -> 10004.65 | J19: =SUM(J2:J18) -> 0 | K19: =SUM(K2:K18) -> 12170 | L19: =M19/K19 -> 5.1465924 | M19: =ROUND(SUM(M2:M18),2) -> 62634.03 | N19: =SUM(N2:N18) -> 2783 | O19: =P19/N19 -> 3.6394143 | P19: =ROUND(SUM(P2:P18),2) -> 10128.49 | Q19: =SUM(Q2:Q18) -> 214 | R19: =S19/Q19 -> 6.099486 | S19: =ROUND(SUM(S2:S18),2) -> 1305.29 | T19: =SUM(T2:T18) -> -537317.13 | U19: =SUM(U2:U18) -> 50229.3 | V19: =SUM(V2:V18) -> 0 | W19: =SUM(W2:W18) -> 0 | X19: =SUM(X2:X18) -> 0 | Y19: =SUM(Y2:Y18) -> 0 | Z19: =SUM(Z2:Z18) -> 0 | AA19: =SUM(AA2:AA18) -> 0 | ... AK19: =SUM(AK2:AK18) -> 0 | AM19: =SUM(AM2:AM18) -> 0 | AN19: =SUM(AN2:AN18) -> 0 | AO19: =SUM(AO2:AO18) -> 0 | AP19: =SUM(AP2:AP18) -> 0 | AQ19: =SUM(AQ2:AQ18) -> 0 | AR19: =D19+E19+F19+G19+H19+I19+J19+M19+P19+S19+SUM(T19:AQ19) -> -368502.61 | AV19: CONSOLIDADO
A20: =A3+1 -> 46205 | B20: BLOCO SPOT
B21: Credito Vendas Cartão | AT21: Saidas | AU21: #REF!
B22: Desconto taxas Cartão | AT22: Saidas | AU22: #REF!
B23: Pix recebido maquininha
B24: Tarifa pix recebido maquinha
B25: BLOCO ITAU
B26: Pix e depositos Vendas
AS27: =#REF! -> #REF!
B28: BLOCO ESTOQUES
B29: Venda de Gasolina | AS29: =#REF! -> #REF!
B30: Venda de Etanol | AS30: =#REF! -> #REF!
B31: Venda de Diesel | AS31: =#REF! -> #REF!
B32: Separação Cartão/Outros | AS32: =#REF! -> #REF!
B33: Ajuste estoque e valor diário (lucro embutido) | AS33: =#REF! -> #REF!
AS34: =#REF! -> #REF!
B35: Saldo Giro no dia | C35: =D36+E36+F36+G36+H36+I36+J36+M36+P36 -> 117279.93 | AR35: =SUM($T19:AQ35) -> -487087.83 | AV35: TERCEIROS
B36: Saldo Líquido do dia | C36: =AR36 -> -368502.61 | D36: =SUM(D19:D35) -> 12717.607 | E36: =SUM(E19:E35) -> -43287.79 | F36: =SUM(F19:F35) -> 0.65 | G36: =SUM(G19:G35) -> 0 | H36: =SUM(H19:H35) -> 65082.293 | I36: =SUM(I19:I35) -> 10004.65 | J36: =SUM(J19:J35) -> 0 | K36: =SUM(K19:K35) -> 12170 | L36: =M36/K36 -> 5.1465924 | M36: =ROUND(SUM(M19:M35),2) -> 62634.03 | N36: =SUM(N19:N35) -> 2783 | O36: =P36/N36 -> 3.6394143 | P36: =ROUND(SUM(P19:P35),2) -> 10128.49 | Q36: =SUM(Q19:Q35) -> 214 | R36: =S36/Q36 -> 6.099486 | S36: =ROUND(SUM(S19:S35),2) -> 1305.29 | T36: =SUM(T19:T35) -> -537317.13 | U36: =SUM(U19:U35) -> 50229.3 | V36: =SUM(V19:V35) -> 0 | W36: =SUM(W19:W35) -> 0 | X36: =SUM(X19:X35) -> 0 | Y36: =SUM(Y19:Y35) -> 0 | Z36: =SUM(Z19:Z35) -> 0 | AA36: =SUM(AA19:AA35) -> 0 | ... AQ36: =SUM(AQ19:AQ35) -> 0 | AR36: =D36+E36+F36+G36+H36+I36+J36+M36+P36+S36+SUM(T36:AQ36) -> -368502.61 | AV36: CONSOLIDADO
A37: =A20+1 -> 46206 | B37: BLOCO SPOT
B38: Credito Vendas Cartão | AT38: Saidas | AU38: #REF!
B39: Desconto taxas Cartão | AT39: Saidas | AU39: #REF!
B40: Pix recebido maquininha
B41: Tarifa pix recebido maquinha
B42: BLOCO ITAU
B43: Pix e depositos Vendas
AS44: =#REF! -> #REF!
B45: BLOCO ESTOQUES
B46: Venda de Gasolina | AS46: =#REF! -> #REF!
B47: Venda de Etanol | AS47: =#REF! -> #REF!
B48: Venda de Diesel | AS48: =#REF! -> #REF!
B49: Separação Cartão/Outros | AS49: =#REF! -> #REF!
B50: Ajuste estoque e valor diário (lucro embutido) | AS50: =#REF! -> #REF!
AS51: =#REF! -> #REF!
B52: Saldo Giro no dia | C52: =D53+E53+F53+G53+H53+I53+J53+M53+P53 -> 117279.93 | AR52: =SUM($T36:AQ52) -> -487087.83 | AV52: TERCEIROS
B53: Saldo Líquido do dia | C53: =AR53 -> -368502.61 | D53: =SUM(D36:D52) -> 12717.607 | E53: =SUM(E36:E52) -> -43287.79 | F53: =SUM(F36:F52) -> 0.65 | G53: =SUM(G36:G52) -> 0 | H53: =SUM(H36:H52) -> 65082.293 | I53: =SUM(I36:I52) -> 10004.65 | J53: =SUM(J36:J52) -> 0 | K53: =SUM(K36:K52) -> 12170 | L53: =M53/K53 -> 5.1465924 | M53: =ROUND(SUM(M36:M52),2) -> 62634.03 | N53: =SUM(N36:N52) -> 2783 | O53: =P53/N53 -> 3.6394143 | P53: =ROUND(SUM(P36:P52),2) -> 10128.49 | Q53: =SUM(Q36:Q52) -> 214 | R53: =S53/Q53 -> 6.099486 | S53: =ROUND(SUM(S36:S52),2) -> 1305.29 | T53: =SUM(T36:T52) -> -537317.13 | U53: =SUM(U36:U52) -> 50229.3 | V53: =SUM(V36:V52) -> 0 | W53: =SUM(W36:W52) -> 0 | X53: =SUM(X36:X52) -> 0 | Y53: =SUM(Y36:Y52) -> 0 | Z53: =SUM(Z36:Z52) -> 0 | AA53: =SUM(AA36:AA52) -> 0 | ... AQ53: =SUM(AQ36:AQ52) -> 0 | AR53: =D53+E53+F53+G53+H53+I53+J53+M53+P53+S53+SUM(T53:AQ53) -> -368502.61 | AV53: CONSOLIDADO
A54: =A37+1 -> 46207 | B54: BLOCO SPOT
B55: Credito Vendas Cartão | AT55: Saidas | AU55: #REF!
B56: Desconto taxas Cartão | AT56: Saidas | AU56: #REF!
B57: Pix recebido maquininha
B58: Tarifa pix recebido maquinha
B59: BLOCO ITAU
B60: Pix e depositos Vendas
AS61: =#REF! -> #REF!
B62: BLOCO ESTOQUES
B63: Venda de Gasolina | AS63: =#REF! -> #REF!
B64: Venda de Etanol | AS64: =#REF! -> #REF!
B65: Venda de Diesel | AS65: =#REF! -> #REF!
B66: Separação Cartão/Outros | AS66: =#REF! -> #REF!
B67: Ajuste estoque e valor diário (lucro embutido) | AS67: =#REF! -> #REF!
AS68: =#REF! -> #REF!
B69: Saldo Giro no dia | C69: =D70+E70+F70+G70+H70+I70+J70+M70+P70 -> 117279.93 | AR69: =SUM($T53:AQ69) -> -487087.83 | AV69: TERCEIROS
B70: Saldo Líquido do dia | C70: =AR70 -> -368502.61 | D70: =SUM(D53:D69) -> 12717.607 | E70: =SUM(E53:E69) -> -43287.79 | F70: =SUM(F53:F69) -> 0.65 | G70: =SUM(G53:G69) -> 0 | H70: =SUM(H53:H69) -> 65082.293 | I70: =SUM(I53:I69) -> 10004.65 | J70: =SUM(J53:J69) -> 0 | K70: =SUM(K53:K69) -> 12170 | L70: =M70/K70 -> 5.1465924 | M70: =ROUND(SUM(M53:M69),2) -> 62634.03 | N70: =SUM(N53:N69) -> 2783 | O70: =P70/N70 -> 3.6394143 | P70: =ROUND(SUM(P53:P69),2) -> 10128.49 | Q70: =SUM(Q53:Q69) -> 214 | R70: =S70/Q70 -> 6.099486 | S70: =ROUND(SUM(S53:S69),2) -> 1305.29 | T70: =SUM(T53:T69) -> -537317.13 | U70: =SUM(U53:U69) -> 50229.3 | V70: =SUM(V53:V69) -> 0 | W70: =SUM(W53:W69) -> 0 | X70: =SUM(X53:X69) -> 0 | Y70: =SUM(Y53:Y69) -> 0 | Z70: =SUM(Z53:Z69) -> 0 | AA70: =SUM(AA53:AA69) -> 0 | ... AQ70: =SUM(AQ53:AQ69) -> 0 | AR70: =D70+E70+F70+G70+H70+I70+J70+M70+P70+S70+SUM(T70:AQ70) -> -368502.61 | AV70: CONSOLIDADO
A71: =A54+1 -> 46208 | B71: BLOCO SPOT
B72: Credito Vendas Cartão | AT72: Saidas | AU72: #REF!
B73: Desconto taxas Cartão | AT73: Saidas | AU73: #REF!
B74: Pix recebido maquininha
B75: Tarifa pix recebido maquinha
B76: BLOCO ITAU
B77: Pix e depositos Vendas
AS78: =#REF! -> #REF!
B79: BLOCO ESTOQUES
B80: Venda de Gasolina | AS80: =#REF! -> #REF!
B81: Venda de Etanol | AS81: =#REF! -> #REF!
B82: Venda de Diesel | AS82: =#REF! -> #REF!
B83: Separação Cartão/Outros | AS83: =#REF! -> #REF!
B84: Ajuste estoque e valor diário (lucro embutido) | AS84: =#REF! -> #REF!
AS85: =#REF! -> #REF!
B86: Saldo Giro no dia | C86: =D87+E87+F87+G87+H87+I87+J87+M87+P87 -> 117279.93 | AR86: =SUM($T70:AQ86) -> -487087.83 | AV86: TERCEIROS
B87: Saldo Líquido do dia | C87: =AR87 -> -368502.61 | D87: =SUM(D70:D86) -> 12717.607 | E87: =SUM(E70:E86) -> -43287.79 | F87: =SUM(F70:F86) -> 0.65 | G87: =SUM(G70:G86) -> 0 | H87: =SUM(H70:H86) -> 65082.293 | I87: =SUM(I70:I86) -> 10004.65 | J87: =SUM(J70:J86) -> 0 | K87: =SUM(K70:K86) -> 12170 | L87: =M87/K87 -> 5.1465924 | M87: =ROUND(SUM(M70:M86),2) -> 62634.03 | N87: =SUM(N70:N86) -> 2783 | O87: =P87/N87 -> 3.6394143 | P87: =ROUND(SUM(P70:P86),2) -> 10128.49 | Q87: =SUM(Q70:Q86) -> 214 | R87: =S87/Q87 -> 6.099486 | S87: =ROUND(SUM(S70:S86),2) -> 1305.29 | T87: =SUM(T70:T86) -> -537317.13 | U87: =SUM(U70:U86) -> 50229.3 | V87: =SUM(V70:V86) -> 0 | W87: =SUM(W70:W86) -> 0 | X87: =SUM(X70:X86) -> 0 | Y87: =SUM(Y70:Y86) -> 0 | Z87: =SUM(Z70:Z86) -> 0 | AA87: =SUM(AA70:AA86) -> 0 | ... AQ87: =SUM(AQ70:AQ86) -> 0 | AR87: =D87+E87+F87+G87+H87+I87+J87+M87+P87+S87+SUM(T87:AQ87) -> -368502.61 | AV87: CONSOLIDADO
A88: =A71+1 -> 46209 | B88: BLOCO SPOT
B89: Credito Vendas Cartão | AT89: Saidas | AU89: #REF!
B90: Desconto taxas Cartão | AT90: Saidas | AU90: #REF!
B91: Pix recebido maquininha
B92: Tarifa pix recebido maquinha
B93: BLOCO ITAU
B94: Pix e depositos Vendas
AS95: =#REF! -> #REF!
B96: BLOCO ESTOQUES
B97: Venda de Gasolina | AS97: =#REF! -> #REF!
B98: Venda de Etanol | AS98: =#REF! -> #REF!
B99: Venda de Diesel | AS99: =#REF! -> #REF!
B100: Separação Cartão/Outros | AS100: =#REF! -> #REF!
...

Sheet Ago26
A1: PERÍODO 01 á 31/AGO/26 | C1: =D2+E2+F2+G2+H2+I2+J2+M2+P2 -> 117279.93 | D1: SPOT | E1: ITAU | F1: LUCILA | G1: HADEN | H1: CAIXA | I1: CARTAO | J1: VENDAS | K1: GASOLINA | N1: ETANOL | Q1: DIESEL | T1: ERALDO | U1: LUIZ F. | V1: LUCILA | W1: DIVIDA | X1: AVANT | Y1: WL | AR1: Total | AS1: Saldo Total | AT1: Saldo Edson | AU1: Saldo Master
B2: Saldo Inicial do dia | C2: =D2+E2+F2+G2+H2+I2+J2+M2+P2+SUM(T2:AQ2) -> -369807.9 | D2: ='Jul26'!D529 -> 12717.607 | E2: ='Jul26'!E529 -> -43287.79 | F2: ='Jul26'!F529 -> 0.65 | G2: ='Jul26'!G529 -> 0 | H2: ='Jul26'!H529 -> 65082.293 | I2: ='Jul26'!I529 -> 10004.65 | J2: ='Jul26'!J529 -> 0 | K2: ='Jul26'!K529 -> 12170 | ... AR2: ='Jul26'!AR529 -> -368502.61 | AS2: =#REF! -> #REF! | AT2: =#REF! -> #REF! | AU2: =AS2-AT2 -> #REF!
A3: 46235 | B3: BLOCO SPOT
B4: Credito Vendas Cartão | AT4: Saidas | AU4: #REF!
B5: Desconto taxas Cartão | AT5: Saidas | AU5: #REF!
B6: Pix recebido maquininha
B7: Tarifa pix recebido maquinha
B8: BLOCO ITAU
B9: Pix e depositos Vendas
AS10: =#REF! -> #REF!
B11: BLOCO ESTOQUES
B12: Venda de Gasolina | AS12: =#REF! -> #REF!
B13: Venda de Etanol | AS13: =#REF! -> #REF!
B14: Venda de Diesel | AS14: =#REF! -> #REF!
B15: Separação Cartão/Outros | AS15: =#REF! -> #REF!
B16: Ajuste estoque e valor diário (lucro embutido) | AS16: =#REF! -> #REF!
AS17: =#REF! -> #REF!
B18: Saldo Giro no dia | C18: =D19+E19+F19+G19+H19+I19+J19+M19+P19+S19 -> 118585.22 | AR18: =SUM($T2:AQ18) -> -487087.83 | AV18: TERCEIROS
B19: Saldo Líquido do dia | C19: =AR19 -> -368502.61 | D19: =SUM(D2:D18) -> 12717.607 | E19: =SUM(E2:E18) -> -43287.79 | F19: =SUM(F2:F18) -> 0.65 | G19: =SUM(G2:G18) -> 0 | H19: =SUM(H2:H18) -> 65082.293 | I19: =SUM(I2:I18) -> 10004.65 | J19: =SUM(J2:J18) -> 0 | K19: =SUM(K2:K18) -> 12170 | L19: =M19/K19 -> 5.1465924 | M19: =ROUND(SUM(M2:M18),2) -> 62634.03 | N19: =SUM(N2:N18) -> 2783 | O19: =P19/N19 -> 3.6394143 | P19: =ROUND(SUM(P2:P18),2) -> 10128.49 | Q19: =SUM(Q2:Q18) -> 214 | R19: =S19/Q19 -> 6.099486 | S19: =ROUND(SUM(S2:S18),2) -> 1305.29 | T19: =SUM(T2:T18) -> -537317.13 | U19: =SUM(U2:U18) -> 50229.3 | V19: =SUM(V2:V18) -> 0 | W19: =SUM(W2:W18) -> 0 | X19: =SUM(X2:X18) -> 0 | Y19: =SUM(Y2:Y18) -> 0 | Z19: =SUM(Z2:Z18) -> 0 | AA19: =SUM(AA2:AA18) -> 0 | ... AK19: =SUM(AK2:AK18) -> 0 | AM19: =SUM(AM2:AM18) -> 0 | AN19: =SUM(AN2:AN18) -> 0 | AO19: =SUM(AO2:AO18) -> 0 | AP19: =SUM(AP2:AP18) -> 0 | AQ19: =SUM(AQ2:AQ18) -> 0 | AR19: =D19+E19+F19+G19+H19+I19+J19+M19+P19+S19+SUM(T19:AQ19) -> -368502.61 | AV19: CONSOLIDADO
A20: =A3+1 -> 46236 | B20: BLOCO SPOT
B21: Credito Vendas Cartão | AT21: Saidas | AU21: #REF!
B22: Desconto taxas Cartão | AT22: Saidas | AU22: #REF!
B23: Pix recebido maquininha
B24: Tarifa pix recebido maquinha
B25: BLOCO ITAU
B26: Pix e depositos Vendas
AS27: =#REF! -> #REF!
B28: BLOCO ESTOQUES
B29: Venda de Gasolina | AS29: =#REF! -> #REF!
B30: Venda de Etanol | AS30: =#REF! -> #REF!
B31: Venda de Diesel | AS31: =#REF! -> #REF!
B32: Separação Cartão/Outros | AS32: =#REF! -> #REF!
B33: Ajuste estoque e valor diário (lucro embutido) | AS33: =#REF! -> #REF!
AS34: =#REF! -> #REF!
B35: Saldo Giro no dia | C35: =D36+E36+F36+G36+H36+I36+J36+M36+P36 -> 117279.93 | AR35: =SUM($T19:AQ35) -> -487087.83 | AV35: TERCEIROS
B36: Saldo Líquido do dia | C36: =AR36 -> -368502.61 | D36: =SUM(D19:D35) -> 12717.607 | E36: =SUM(E19:E35) -> -43287.79 | F36: =SUM(F19:F35) -> 0.65 | G36: =SUM(G19:G35) -> 0 | H36: =SUM(H19:H35) -> 65082.293 | I36: =SUM(I19:I35) -> 10004.65 | J36: =SUM(J19:J35) -> 0 | K36: =SUM(K19:K35) -> 12170 | L36: =M36/K36 -> 5.1465924 | M36: =ROUND(SUM(M19:M35),2) -> 62634.03 | N36: =SUM(N19:N35) -> 2783 | O36: =P36/N36 -> 3.6394143 | P36: =ROUND(SUM(P19:P35),2) -> 10128.49 | Q36: =SUM(Q19:Q35) -> 214 | R36: =S36/Q36 -> 6.099486 | S36: =ROUND(SUM(S19:S35),2) -> 1305.29 | T36: =SUM(T19:T35) -> -537317.13 | U36: =SUM(U19:U35) -> 50229.3 | V36: =SUM(V19:V35) -> 0 | W36: =SUM(W19:W35) -> 0 | X36: =SUM(X19:X35) -> 0 | Y36: =SUM(Y19:Y35) -> 0 | Z36: =SUM(Z19:Z35) -> 0 | AA36: =SUM(AA19:AA35) -> 0 | ... AQ36: =SUM(AQ19:AQ35) -> 0 | AR36: =D36+E36+F36+G36+H36+I36+J36+M36+P36+S36+SUM(T36:AQ36) -> -368502.61 | AV36: CONSOLIDADO
A37: =A20+1 -> 46237 | B37: BLOCO SPOT
B38: Credito Vendas Cartão | AT38: Saidas | AU38: #REF!
B39: Desconto taxas Cartão | AT39: Saidas | AU39: #REF!
B40: Pix recebido maquininha
B41: Tarifa pix recebido maquinha
B42: BLOCO ITAU
B43: Pix e depositos Vendas
AS44: =#REF! -> #REF!
B45: BLOCO ESTOQUES
B46: Venda de Gasolina | AS46: =#REF! -> #REF!
B47: Venda de Etanol | AS47: =#REF! -> #REF!
B48: Venda de Diesel | AS48: =#REF! -> #REF!
B49: Separação Cartão/Outros | AS49: =#REF! -> #REF!
B50: Ajuste estoque e valor diário (lucro embutido) | AS50: =#REF! -> #REF!
AS51: =#REF! -> #REF!
B52: Saldo Giro no dia | C52: =D53+E53+F53+G53+H53+I53+J53+M53+P53 -> 117279.93 | AR52: =SUM($T36:AQ52) -> -487087.83 | AV52: TERCEIROS
B53: Saldo Líquido do dia | C53: =AR53 -> -368502.61 | D53: =SUM(D36:D52) -> 12717.607 | E53: =SUM(E36:E52) -> -43287.79 | F53: =SUM(F36:F52) -> 0.65 | G53: =SUM(G36:G52) -> 0 | H53: =SUM(H36:H52) -> 65082.293 | I53: =SUM(I36:I52) -> 10004.65 | J53: =SUM(J36:J52) -> 0 | K53: =SUM(K36:K52) -> 12170 | L53: =M53/K53 -> 5.1465924 | M53: =ROUND(SUM(M36:M52),2) -> 62634.03 | N53: =SUM(N36:N52) -> 2783 | O53: =P53/N53 -> 3.6394143 | P53: =ROUND(SUM(P36:P52),2) -> 10128.49 | Q53: =SUM(Q36:Q52) -> 214 | R53: =S53/Q53 -> 6.099486 | S53: =ROUND(SUM(S36:S52),2) -> 1305.29 | T53: =SUM(T36:T52) -> -537317.13 | U53: =SUM(U36:U52) -> 50229.3 | V53: =SUM(V36:V52) -> 0 | W53: =SUM(W36:W52) -> 0 | X53: =SUM(X36:X52) -> 0 | Y53: =SUM(Y36:Y52) -> 0 | Z53: =SUM(Z36:Z52) -> 0 | AA53: =SUM(AA36:AA52) -> 0 | ... AQ53: =SUM(AQ36:AQ52) -> 0 | AR53: =D53+E53+F53+G53+H53+I53+J53+M53+P53+S53+SUM(T53:AQ53) -> -368502.61 | AV53: CONSOLIDADO
A54: =A37+1 -> 46238 | B54: BLOCO SPOT
B55: Credito Vendas Cartão | AT55: Saidas | AU55: #REF!
B56: Desconto taxas Cartão | AT56: Saidas | AU56: #REF!
B57: Pix recebido maquininha
B58: Tarifa pix recebido maquinha
B59: BLOCO ITAU
B60: Pix e depositos Vendas
AS61: =#REF! -> #REF!
B62: BLOCO ESTOQUES
B63: Venda de Gasolina | AS63: =#REF! -> #REF!
B64: Venda de Etanol | AS64: =#REF! -> #REF!
B65: Venda de Diesel | AS65: =#REF! -> #REF!
B66: Separação Cartão/Outros | AS66: =#REF! -> #REF!
B67: Ajuste estoque e valor diário (lucro embutido) | AS67: =#REF! -> #REF!
AS68: =#REF! -> #REF!
B69: Saldo Giro no dia | C69: =D70+E70+F70+G70+H70+I70+J70+M70+P70 -> 117279.93 | AR69: =SUM($T53:AQ69) -> -487087.83 | AV69: TERCEIROS
B70: Saldo Líquido do dia | C70: =AR70 -> -368502.61 | D70: =SUM(D53:D69) -> 12717.607 | E70: =SUM(E53:E69) -> -43287.79 | F70: =SUM(F53:F69) -> 0.65 | G70: =SUM(G53:G69) -> 0 | H70: =SUM(H53:H69) -> 65082.293 | I70: =SUM(I53:I69) -> 10004.65 | J70: =SUM(J53:J69) -> 0 | K70: =SUM(K53:K69) -> 12170 | L70: =M70/K70 -> 5.1465924 | M70: =ROUND(SUM(M53:M69),2) -> 62634.03 | N70: =SUM(N53:N69) -> 2783 | O70: =P70/N70 -> 3.6394143 | P70: =ROUND(SUM(P53:P69),2) -> 10128.49 | Q70: =SUM(Q53:Q69) -> 214 | R70: =S70/Q70 -> 6.099486 | S70: =ROUND(SUM(S53:S69),2) -> 1305.29 | T70: =SUM(T53:T69) -> -537317.13 | U70: =SUM(U53:U69) -> 50229.3 | V70: =SUM(V53:V69) -> 0 | W70: =SUM(W53:W69) -> 0 | X70: =SUM(X53:X69) -> 0 | Y70: =SUM(Y53:Y69) -> 0 | Z70: =SUM(Z53:Z69) -> 0 | AA70: =SUM(AA53:AA69) -> 0 | ... AQ70: =SUM(AQ53:AQ69) -> 0 | AR70: =D70+E70+F70+G70+H70+I70+J70+M70+P70+S70+SUM(T70:AQ70) -> -368502.61 | AV70: CONSOLIDADO
A71: =A54+1 -> 46239 | B71: BLOCO SPOT
B72: Credito Vendas Cartão | AT72: Saidas | AU72: #REF!
B73: Desconto taxas Cartão | AT73: Saidas | AU73: #REF!
B74: Pix recebido maquininha
B75: Tarifa pix recebido maquinha
B76: BLOCO ITAU
B77: Pix e depositos Vendas
AS78: =#REF! -> #REF!
B79: BLOCO ESTOQUES
B80: Venda de Gasolina | AS80: =#REF! -> #REF!
B81: Venda de Etanol | AS81: =#REF! -> #REF!
B82: Venda de Diesel | AS82: =#REF! -> #REF!
B83: Separação Cartão/Outros | AS83: =#REF! -> #REF!
B84: Ajuste estoque e valor diário (lucro embutido) | AS84: =#REF! -> #REF!
AS85: =#REF! -> #REF!
B86: Saldo Giro no dia | C86: =D87+E87+F87+G87+H87+I87+J87+M87+P87 -> 117279.93 | AR86: =SUM($T70:AQ86) -> -487087.83 | AV86: TERCEIROS
B87: Saldo Líquido do dia | C87: =AR87 -> -368502.61 | D87: =SUM(D70:D86) -> 12717.607 | E87: =SUM(E70:E86) -> -43287.79 | F87: =SUM(F70:F86) -> 0.65 | G87: =SUM(G70:G86) -> 0 | H87: =SUM(H70:H86) -> 65082.293 | I87: =SUM(I70:I86) -> 10004.65 | J87: =SUM(J70:J86) -> 0 | K87: =SUM(K70:K86) -> 12170 | L87: =M87/K87 -> 5.1465924 | M87: =ROUND(SUM(M70:M86),2) -> 62634.03 | N87: =SUM(N70:N86) -> 2783 | O87: =P87/N87 -> 3.6394143 | P87: =ROUND(SUM(P70:P86),2) -> 10128.49 | Q87: =SUM(Q70:Q86) -> 214 | R87: =S87/Q87 -> 6.099486 | S87: =ROUND(SUM(S70:S86),2) -> 1305.29 | T87: =SUM(T70:T86) -> -537317.13 | U87: =SUM(U70:U86) -> 50229.3 | V87: =SUM(V70:V86) -> 0 | W87: =SUM(W70:W86) -> 0 | X87: =SUM(X70:X86) -> 0 | Y87: =SUM(Y70:Y86) -> 0 | Z87: =SUM(Z70:Z86) -> 0 | AA87: =SUM(AA70:AA86) -> 0 | ... AQ87: =SUM(AQ70:AQ86) -> 0 | AR87: =D87+E87+F87+G87+H87+I87+J87+M87+P87+S87+SUM(T87:AQ87) -> -368502.61 | AV87: CONSOLIDADO
A88: =A71+1 -> 46240 | B88: BLOCO SPOT
B89: Credito Vendas Cartão | AT89: Saidas | AU89: #REF!
B90: Desconto taxas Cartão | AT90: Saidas | AU90: #REF!
B91: Pix recebido maquininha
B92: Tarifa pix recebido maquinha
B93: BLOCO ITAU
B94: Pix e depositos Vendas
AS95: =#REF! -> #REF!
B96: BLOCO ESTOQUES
B97: Venda de Gasolina | AS97: =#REF! -> #REF!
B98: Venda de Etanol | AS98: =#REF! -> #REF!
B99: Venda de Diesel | AS99: =#REF! -> #REF!
B100: Separação Cartão/Outros | AS100: =#REF! -> #REF!
...

Sheet Set26
A1: PERÍODO 01 á 30/SET/26 | C1: =D2+E2+F2+G2+H2+I2+J2+M2+P2 -> 117279.93 | D1: SPOT | E1: ITAU | F1: LUCILA | G1: HADEN | H1: CAIXA | I1: CARTAO | J1: VENDAS | K1: GASOLINA | N1: ETANOL | Q1: DIESEL | T1: ERALDO | U1: LUIZ F. | V1: LUCILA | W1: DIVIDA | X1: AVANT | Y1: WL | AR1: Total | AS1: Saldo Total | AT1: Saldo Edson | AU1: Saldo Master
B2: Saldo Inicial do dia | C2: =D2+E2+F2+G2+H2+I2+J2+M2+P2+SUM(T2:AQ2) -> -369807.9 | D2: ='Ago26'!D529 -> 12717.607 | E2: ='Ago26'!E529 -> -43287.79 | F2: ='Ago26'!F529 -> 0.65 | G2: ='Ago26'!G529 -> 0 | H2: ='Ago26'!H529 -> 65082.293 | I2: ='Ago26'!I529 -> 10004.65 | J2: ='Ago26'!J529 -> 0 | K2: ='Ago26'!K529 -> 12170 | ... AR2: ='Ago26'!AR529 -> -368502.61 | AS2: =#REF! -> #REF! | AT2: =#REF! -> #REF! | AU2: =AS2-AT2 -> #REF!
A3: 46266 | B3: BLOCO SPOT
B4: Credito Vendas Cartão | AT4: Saidas | AU4: #REF!
B5: Desconto taxas Cartão | AT5: Saidas | AU5: #REF!
B6: Pix recebido maquininha
B7: Tarifa pix recebido maquinha
B8: BLOCO ITAU
B9: Pix e depositos Vendas
AS10: =#REF! -> #REF!
B11: BLOCO ESTOQUES
B12: Venda de Gasolina | AS12: =#REF! -> #REF!
B13: Venda de Etanol | AS13: =#REF! -> #REF!
B14: Venda de Diesel | AS14: =#REF! -> #REF!
B15: Separação Cartão/Outros | AS15: =#REF! -> #REF!
B16: Ajuste estoque e valor diário (lucro embutido) | AS16: =#REF! -> #REF!
AS17: =#REF! -> #REF!
B18: Saldo Giro no dia | C18: =D19+E19+F19+G19+H19+I19+J19+M19+P19+S19 -> 118585.22 | AR18: =SUM($T2:AQ18) -> -487087.83 | AV18: TERCEIROS
B19: Saldo Líquido do dia | C19: =AR19 -> -368502.61 | D19: =SUM(D2:D18) -> 12717.607 | E19: =SUM(E2:E18) -> -43287.79 | F19: =SUM(F2:F18) -> 0.65 | G19: =SUM(G2:G18) -> 0 | H19: =SUM(H2:H18) -> 65082.293 | I19: =SUM(I2:I18) -> 10004.65 | J19: =SUM(J2:J18) -> 0 | K19: =SUM(K2:K18) -> 12170 | L19: =M19/K19 -> 5.1465924 | M19: =ROUND(SUM(M2:M18),2) -> 62634.03 | N19: =SUM(N2:N18) -> 2783 | O19: =P19/N19 -> 3.6394143 | P19: =ROUND(SUM(P2:P18),2) -> 10128.49 | Q19: =SUM(Q2:Q18) -> 214 | R19: =S19/Q19 -> 6.099486 | S19: =ROUND(SUM(S2:S18),2) -> 1305.29 | T19: =SUM(T2:T18) -> -537317.13 | U19: =SUM(U2:U18) -> 50229.3 | V19: =SUM(V2:V18) -> 0 | W19: =SUM(W2:W18) -> 0 | X19: =SUM(X2:X18) -> 0 | Y19: =SUM(Y2:Y18) -> 0 | Z19: =SUM(Z2:Z18) -> 0 | AA19: =SUM(AA2:AA18) -> 0 | ... AK19: =SUM(AK2:AK18) -> 0 | AM19: =SUM(AM2:AM18) -> 0 | AN19: =SUM(AN2:AN18) -> 0 | AO19: =SUM(AO2:AO18) -> 0 | AP19: =SUM(AP2:AP18) -> 0 | AQ19: =SUM(AQ2:AQ18) -> 0 | AR19: =D19+E19+F19+G19+H19+I19+J19+M19+P19+S19+SUM(T19:AQ19) -> -368502.61 | AV19: CONSOLIDADO
A20: =A3+1 -> 46267 | B20: BLOCO SPOT
B21: Credito Vendas Cartão | AT21: Saidas | AU21: #REF!
B22: Desconto taxas Cartão | AT22: Saidas | AU22: #REF!
B23: Pix recebido maquininha
B24: Tarifa pix recebido maquinha
B25: BLOCO ITAU
B26: Pix e depositos Vendas
AS27: =#REF! -> #REF!
B28: BLOCO ESTOQUES
B29: Venda de Gasolina | AS29: =#REF! -> #REF!
B30: Venda de Etanol | AS30: =#REF! -> #REF!
B31: Venda de Diesel | AS31: =#REF! -> #REF!
B32: Separação Cartão/Outros | AS32: =#REF! -> #REF!
B33: Ajuste estoque e valor diário (lucro embutido) | AS33: =#REF! -> #REF!
AS34: =#REF! -> #REF!
B35: Saldo Giro no dia | C35: =D36+E36+F36+G36+H36+I36+J36+M36+P36 -> 117279.93 | AR35: =SUM($T19:AQ35) -> -487087.83 | AV35: TERCEIROS
B36: Saldo Líquido do dia | C36: =AR36 -> -368502.61 | D36: =SUM(D19:D35) -> 12717.607 | E36: =SUM(E19:E35) -> -43287.79 | F36: =SUM(F19:F35) -> 0.65 | G36: =SUM(G19:G35) -> 0 | H36: =SUM(H19:H35) -> 65082.293 | I36: =SUM(I19:I35) -> 10004.65 | J36: =SUM(J19:J35) -> 0 | K36: =SUM(K19:K35) -> 12170 | L36: =M36/K36 -> 5.1465924 | M36: =ROUND(SUM(M19:M35),2) -> 62634.03 | N36: =SUM(N19:N35) -> 2783 | O36: =P36/N36 -> 3.6394143 | P36: =ROUND(SUM(P19:P35),2) -> 10128.49 | Q36: =SUM(Q19:Q35) -> 214 | R36: =S36/Q36 -> 6.099486 | S36: =ROUND(SUM(S19:S35),2) -> 1305.29 | T36: =SUM(T19:T35) -> -537317.13 | U36: =SUM(U19:U35) -> 50229.3 | V36: =SUM(V19:V35) -> 0 | W36: =SUM(W19:W35) -> 0 | X36: =SUM(X19:X35) -> 0 | Y36: =SUM(Y19:Y35) -> 0 | Z36: =SUM(Z19:Z35) -> 0 | AA36: =SUM(AA19:AA35) -> 0 | ... AQ36: =SUM(AQ19:AQ35) -> 0 | AR36: =D36+E36+F36+G36+H36+I36+J36+M36+P36+S36+SUM(T36:AQ36) -> -368502.61 | AV36: CONSOLIDADO
A37: =A20+1 -> 46268 | B37: BLOCO SPOT
B38: Credito Vendas Cartão | AT38: Saidas | AU38: #REF!
B39: Desconto taxas Cartão | AT39: Saidas | AU39: #REF!
B40: Pix recebido maquininha
B41: Tarifa pix recebido maquinha
B42: BLOCO ITAU
B43: Pix e depositos Vendas
AS44: =#REF! -> #REF!
B45: BLOCO ESTOQUES
B46: Venda de Gasolina | AS46: =#REF! -> #REF!
B47: Venda de Etanol | AS47: =#REF! -> #REF!
B48: Venda de Diesel | AS48: =#REF! -> #REF!
B49: Separação Cartão/Outros | AS49: =#REF! -> #REF!
B50: Ajuste estoque e valor diário (lucro embutido) | AS50: =#REF! -> #REF!
AS51: =#REF! -> #REF!
B52: Saldo Giro no dia | C52: =D53+E53+F53+G53+H53+I53+J53+M53+P53 -> 117279.93 | AR52: =SUM($T36:AQ52) -> -487087.83 | AV52: TERCEIROS
B53: Saldo Líquido do dia | C53: =AR53 -> -368502.61 | D53: =SUM(D36:D52) -> 12717.607 | E53: =SUM(E36:E52) -> -43287.79 | F53: =SUM(F36:F52) -> 0.65 | G53: =SUM(G36:G52) -> 0 | H53: =SUM(H36:H52) -> 65082.293 | I53: =SUM(I36:I52) -> 10004.65 | J53: =SUM(J36:J52) -> 0 | K53: =SUM(K36:K52) -> 12170 | L53: =M53/K53 -> 5.1465924 | M53: =ROUND(SUM(M36:M52),2) -> 62634.03 | N53: =SUM(N36:N52) -> 2783 | O53: =P53/N53 -> 3.6394143 | P53: =ROUND(SUM(P36:P52),2) -> 10128.49 | Q53: =SUM(Q36:Q52) -> 214 | R53: =S53/Q53 -> 6.099486 | S53: =ROUND(SUM(S36:S52),2) -> 1305.29 | T53: =SUM(T36:T52) -> -537317.13 | U53: =SUM(U36:U52) -> 50229.3 | V53: =SUM(V36:V52) -> 0 | W53: =SUM(W36:W52) -> 0 | X53: =SUM(X36:X52) -> 0 | Y53: =SUM(Y36:Y52) -> 0 | Z53: =SUM(Z36:Z52) -> 0 | AA53: =SUM(AA36:AA52) -> 0 | ... AQ53: =SUM(AQ36:AQ52) -> 0 | AR53: =D53+E53+F53+G53+H53+I53+J53+M53+P53+S53+SUM(T53:AQ53) -> -368502.61 | AV53: CONSOLIDADO
A54: =A37+1 -> 46269 | B54: BLOCO SPOT
B55: Credito Vendas Cartão | AT55: Saidas | AU55: #REF!
B56: Desconto taxas Cartão | AT56: Saidas | AU56: #REF!
B57: Pix recebido maquininha
B58: Tarifa pix recebido maquinha
B59: BLOCO ITAU
B60: Pix e depositos Vendas
AS61: =#REF! -> #REF!
B62: BLOCO ESTOQUES
B63: Venda de Gasolina | AS63: =#REF! -> #REF!
B64: Venda de Etanol | AS64: =#REF! -> #REF!
B65: Venda de Diesel | AS65: =#REF! -> #REF!
B66: Separação Cartão/Outros | AS66: =#REF! -> #REF!
B67: Ajuste estoque e valor diário (lucro embutido) | AS67: =#REF! -> #REF!
AS68: =#REF! -> #REF!
B69: Saldo Giro no dia | C69: =D70+E70+F70+G70+H70+I70+J70+M70+P70 -> 117279.93 | AR69: =SUM($T53:AQ69) -> -487087.83 | AV69: TERCEIROS
B70: Saldo Líquido do dia | C70: =AR70 -> -368502.61 | D70: =SUM(D53:D69) -> 12717.607 | E70: =SUM(E53:E69) -> -43287.79 | F70: =SUM(F53:F69) -> 0.65 | G70: =SUM(G53:G69) -> 0 | H70: =SUM(H53:H69) -> 65082.293 | I70: =SUM(I53:I69) -> 10004.65 | J70: =SUM(J53:J69) -> 0 | K70: =SUM(K53:K69) -> 12170 | L70: =M70/K70 -> 5.1465924 | M70: =ROUND(SUM(M53:M69),2) -> 62634.03 | N70: =SUM(N53:N69) -> 2783 | O70: =P70/N70 -> 3.6394143 | P70: =ROUND(SUM(P53:P69),2) -> 10128.49 | Q70: =SUM(Q53:Q69) -> 214 | R70: =S70/Q70 -> 6.099486 | S70: =ROUND(SUM(S53:S69),2) -> 1305.29 | T70: =SUM(T53:T69) -> -537317.13 | U70: =SUM(U53:U69) -> 50229.3 | V70: =SUM(V53:V69) -> 0 | W70: =SUM(W53:W69) -> 0 | X70: =SUM(X53:X69) -> 0 | Y70: =SUM(Y53:Y69) -> 0 | Z70: =SUM(Z53:Z69) -> 0 | AA70: =SUM(AA53:AA69) -> 0 | ... AQ70: =SUM(AQ53:AQ69) -> 0 | AR70: =D70+E70+F70+G70+H70+I70+J70+M70+P70+S70+SUM(T70:AQ70) -> -368502.61 | AV70: CONSOLIDADO
A71: =A54+1 -> 46270 | B71: BLOCO SPOT
B72: Credito Vendas Cartão | AT72: Saidas | AU72: #REF!
B73: Desconto taxas Cartão | AT73: Saidas | AU73: #REF!
B74: Pix recebido maquininha
B75: Tarifa pix recebido maquinha
B76: BLOCO ITAU
B77: Pix e depositos Vendas
AS78: =#REF! -> #REF!
B79: BLOCO ESTOQUES
B80: Venda de Gasolina | AS80: =#REF! -> #REF!
B81: Venda de Etanol | AS81: =#REF! -> #REF!
B82: Venda de Diesel | AS82: =#REF! -> #REF!
B83: Separação Cartão/Outros | AS83: =#REF! -> #REF!
B84: Ajuste estoque e valor diário (lucro embutido) | AS84: =#REF! -> #REF!
AS85: =#REF! -> #REF!
B86: Saldo Giro no dia | C86: =D87+E87+F87+G87+H87+I87+J87+M87+P87 -> 117279.93 | AR86: =SUM($T70:AQ86) -> -487087.83 | AV86: TERCEIROS
B87: Saldo Líquido do dia | C87: =AR87 -> -368502.61 | D87: =SUM(D70:D86) -> 12717.607 | E87: =SUM(E70:E86) -> -43287.79 | F87: =SUM(F70:F86) -> 0.65 | G87: =SUM(G70:G86) -> 0 | H87: =SUM(H70:H86) -> 65082.293 | I87: =SUM(I70:I86) -> 10004.65 | J87: =SUM(J70:J86) -> 0 | K87: =SUM(K70:K86) -> 12170 | L87: =M87/K87 -> 5.1465924 | M87: =ROUND(SUM(M70:M86),2) -> 62634.03 | N87: =SUM(N70:N86) -> 2783 | O87: =P87/N87 -> 3.6394143 | P87: =ROUND(SUM(P70:P86),2) -> 10128.49 | Q87: =SUM(Q70:Q86) -> 214 | R87: =S87/Q87 -> 6.099486 | S87: =ROUND(SUM(S70:S86),2) -> 1305.29 | T87: =SUM(T70:T86) -> -537317.13 | U87: =SUM(U70:U86) -> 50229.3 | V87: =SUM(V70:V86) -> 0 | W87: =SUM(W70:W86) -> 0 | X87: =SUM(X70:X86) -> 0 | Y87: =SUM(Y70:Y86) -> 0 | Z87: =SUM(Z70:Z86) -> 0 | AA87: =SUM(AA70:AA86) -> 0 | ... AQ87: =SUM(AQ70:AQ86) -> 0 | AR87: =D87+E87+F87+G87+H87+I87+J87+M87+P87+S87+SUM(T87:AQ87) -> -368502.61 | AV87: CONSOLIDADO
A88: =A71+1 -> 46271 | B88: BLOCO SPOT
B89: Credito Vendas Cartão | AT89: Saidas | AU89: #REF!
B90: Desconto taxas Cartão | AT90: Saidas | AU90: #REF!
B91: Pix recebido maquininha
B92: Tarifa pix recebido maquinha
B93: BLOCO ITAU
B94: Pix e depositos Vendas
AS95: =#REF! -> #REF!
B96: BLOCO ESTOQUES
B97: Venda de Gasolina | AS97: =#REF! -> #REF!
B98: Venda de Etanol | AS98: =#REF! -> #REF!
B99: Venda de Diesel | AS99: =#REF! -> #REF!
B100: Separação Cartão/Outros | AS100: =#REF! -> #REF!
...

Sheet Out26
A1: PERÍODO 01 á 31/OUT/26 | C1: =D2+E2+F2+G2+H2+I2+J2+M2+P2 -> 117279.93 | D1: SPOT | E1: ITAU | F1: LUCILA | G1: HADEN | H1: CAIXA | I1: CARTAO | J1: VENDAS | K1: GASOLINA | N1: ETANOL | Q1: DIESEL | T1: ERALDO | U1: LUIZ F. | V1: LUCILA | W1: DIVIDA | X1: AVANT | Y1: WL | AR1: Total | AS1: Saldo Total | AT1: Saldo Edson | AU1: Saldo Master
B2: Saldo Inicial do dia | C2: =D2+E2+F2+G2+H2+I2+J2+M2+P2+SUM(T2:AQ2) -> -369807.9 | D2: ='Set26'!D529 -> 12717.607 | E2: ='Set26'!E529 -> -43287.79 | F2: ='Set26'!F529 -> 0.65 | G2: ='Set26'!G529 -> 0 | H2: ='Set26'!H529 -> 65082.293 | I2: ='Set26'!I529 -> 10004.65 | J2: ='Set26'!J529 -> 0 | K2: ='Set26'!K529 -> 12170 | ... AR2: ='Set26'!AR529 -> -368502.61 | AS2: =#REF! -> #REF! | AT2: =#REF! -> #REF! | AU2: =AS2-AT2 -> #REF!
A3: 46296 | B3: BLOCO SPOT
B4: Credito Vendas Cartão | AT4: Saidas | AU4: #REF!
B5: Desconto taxas Cartão | AT5: Saidas | AU5: #REF!
B6: Pix recebido maquininha
B7: Tarifa pix recebido maquinha
B8: BLOCO ITAU
B9: Pix e depositos Vendas
AS10: =#REF! -> #REF!
B11: BLOCO ESTOQUES
B12: Venda de Gasolina | AS12: =#REF! -> #REF!
B13: Venda de Etanol | AS13: =#REF! -> #REF!
B14: Venda de Diesel | AS14: =#REF! -> #REF!
B15: Separação Cartão/Outros | AS15: =#REF! -> #REF!
B16: Ajuste estoque e valor diário (lucro embutido) | AS16: =#REF! -> #REF!
AS17: =#REF! -> #REF!
B18: Saldo Giro no dia | C18: =D19+E19+F19+G19+H19+I19+J19+M19+P19+S19 -> 118585.22 | AR18: =SUM($T2:AQ18) -> -487087.83 | AV18: TERCEIROS
B19: Saldo Líquido do dia | C19: =AR19 -> -368502.61 | D19: =SUM(D2:D18) -> 12717.607 | E19: =SUM(E2:E18) -> -43287.79 | F19: =SUM(F2:F18) -> 0.65 | G19: =SUM(G2:G18) -> 0 | H19: =SUM(H2:H18) -> 65082.293 | I19: =SUM(I2:I18) -> 10004.65 | J19: =SUM(J2:J18) -> 0 | K19: =SUM(K2:K18) -> 12170 | L19: =M19/K19 -> 5.1465924 | M19: =ROUND(SUM(M2:M18),2) -> 62634.03 | N19: =SUM(N2:N18) -> 2783 | O19: =P19/N19 -> 3.6394143 | P19: =ROUND(SUM(P2:P18),2) -> 10128.49 | Q19: =SUM(Q2:Q18) -> 214 | R19: =S19/Q19 -> 6.099486 | S19: =ROUND(SUM(S2:S18),2) -> 1305.29 | T19: =SUM(T2:T18) -> -537317.13 | U19: =SUM(U2:U18) -> 50229.3 | V19: =SUM(V2:V18) -> 0 | W19: =SUM(W2:W18) -> 0 | X19: =SUM(X2:X18) -> 0 | Y19: =SUM(Y2:Y18) -> 0 | Z19: =SUM(Z2:Z18) -> 0 | AA19: =SUM(AA2:AA18) -> 0 | ... AK19: =SUM(AK2:AK18) -> 0 | AM19: =SUM(AM2:AM18) -> 0 | AN19: =SUM(AN2:AN18) -> 0 | AO19: =SUM(AO2:AO18) -> 0 | AP19: =SUM(AP2:AP18) -> 0 | AQ19: =SUM(AQ2:AQ18) -> 0 | AR19: =D19+E19+F19+G19+H19+I19+J19+M19+P19+S19+SUM(T19:AQ19) -> -368502.61 | AV19: CONSOLIDADO
A20: =A3+1 -> 46297 | B20: BLOCO SPOT
B21: Credito Vendas Cartão | AT21: Saidas | AU21: #REF!
B22: Desconto taxas Cartão | AT22: Saidas | AU22: #REF!
B23: Pix recebido maquininha
B24: Tarifa pix recebido maquinha
B25: BLOCO ITAU
B26: Pix e depositos Vendas
AS27: =#REF! -> #REF!
B28: BLOCO ESTOQUES
B29: Venda de Gasolina | AS29: =#REF! -> #REF!
B30: Venda de Etanol | AS30: =#REF! -> #REF!
B31: Venda de Diesel | AS31: =#REF! -> #REF!
B32: Separação Cartão/Outros | AS32: =#REF! -> #REF!
B33: Ajuste estoque e valor diário (lucro embutido) | AS33: =#REF! -> #REF!
AS34: =#REF! -> #REF!
B35: Saldo Giro no dia | C35: =D36+E36+F36+G36+H36+I36+J36+M36+P36 -> 117279.93 | AR35: =SUM($T19:AQ35) -> -487087.83 | AV35: TERCEIROS
B36: Saldo Líquido do dia | C36: =AR36 -> -368502.61 | D36: =SUM(D19:D35) -> 12717.607 | E36: =SUM(E19:E35) -> -43287.79 | F36: =SUM(F19:F35) -> 0.65 | G36: =SUM(G19:G35) -> 0 | H36: =SUM(H19:H35) -> 65082.293 | I36: =SUM(I19:I35) -> 10004.65 | J36: =SUM(J19:J35) -> 0 | K36: =SUM(K19:K35) -> 12170 | L36: =M36/K36 -> 5.1465924 | M36: =ROUND(SUM(M19:M35),2) -> 62634.03 | N36: =SUM(N19:N35) -> 2783 | O36: =P36/N36 -> 3.6394143 | P36: =ROUND(SUM(P19:P35),2) -> 10128.49 | Q36: =SUM(Q19:Q35) -> 214 | R36: =S36/Q36 -> 6.099486 | S36: =ROUND(SUM(S19:S35),2) -> 1305.29 | T36: =SUM(T19:T35) -> -537317.13 | U36: =SUM(U19:U35) -> 50229.3 | V36: =SUM(V19:V35) -> 0 | W36: =SUM(W19:W35) -> 0 | X36: =SUM(X19:X35) -> 0 | Y36: =SUM(Y19:Y35) -> 0 | Z36: =SUM(Z19:Z35) -> 0 | AA36: =SUM(AA19:AA35) -> 0 | ... AQ36: =SUM(AQ19:AQ35) -> 0 | AR36: =D36+E36+F36+G36+H36+I36+J36+M36+P36+S36+SUM(T36:AQ36) -> -368502.61 | AV36: CONSOLIDADO
A37: =A20+1 -> 46298 | B37: BLOCO SPOT
B38: Credito Vendas Cartão | AT38: Saidas | AU38: #REF!
B39: Desconto taxas Cartão | AT39: Saidas | AU39: #REF!
B40: Pix recebido maquininha
B41: Tarifa pix recebido maquinha
B42: BLOCO ITAU
B43: Pix e depositos Vendas
AS44: =#REF! -> #REF!
B45: BLOCO ESTOQUES
B46: Venda de Gasolina | AS46: =#REF! -> #REF!
B47: Venda de Etanol | AS47: =#REF! -> #REF!
B48: Venda de Diesel | AS48: =#REF! -> #REF!
B49: Separação Cartão/Outros | AS49: =#REF! -> #REF!
B50: Ajuste estoque e valor diário (lucro embutido) | AS50: =#REF! -> #REF!
AS51: =#REF! -> #REF!
B52: Saldo Giro no dia | C52: =D53+E53+F53+G53+H53+I53+J53+M53+P53 -> 117279.93 | AR52: =SUM($T36:AQ52) -> -487087.83 | AV52: TERCEIROS
B53: Saldo Líquido do dia | C53: =AR53 -> -368502.61 | D53: =SUM(D36:D52) -> 12717.607 | E53: =SUM(E36:E52) -> -43287.79 | F53: =SUM(F36:F52) -> 0.65 | G53: =SUM(G36:G52) -> 0 | H53: =SUM(H36:H52) -> 65082.293 | I53: =SUM(I36:I52) -> 10004.65 | J53: =SUM(J36:J52) -> 0 | K53: =SUM(K36:K52) -> 12170 | L53: =M53/K53 -> 5.1465924 | M53: =ROUND(SUM(M36:M52),2) -> 62634.03 | N53: =SUM(N36:N52) -> 2783 | O53: =P53/N53 -> 3.6394143 | P53: =ROUND(SUM(P36:P52),2) -> 10128.49 | Q53: =SUM(Q36:Q52) -> 214 | R53: =S53/Q53 -> 6.099486 | S53: =ROUND(SUM(S36:S52),2) -> 1305.29 | T53: =SUM(T36:T52) -> -537317.13 | U53: =SUM(U36:U52) -> 50229.3 | V53: =SUM(V36:V52) -> 0 | W53: =SUM(W36:W52) -> 0 | X53: =SUM(X36:X52) -> 0 | Y53: =SUM(Y36:Y52) -> 0 | Z53: =SUM(Z36:Z52) -> 0 | AA53: =SUM(AA36:AA52) -> 0 | ... AQ53: =SUM(AQ36:AQ52) -> 0 | AR53: =D53+E53+F53+G53+H53+I53+J53+M53+P53+S53+SUM(T53:AQ53) -> -368502.61 | AV53: CONSOLIDADO
A54: =A37+1 -> 46299 | B54: BLOCO SPOT
B55: Credito Vendas Cartão | AT55: Saidas | AU55: #REF!
B56: Desconto taxas Cartão | AT56: Saidas | AU56: #REF!
B57: Pix recebido maquininha
B58: Tarifa pix recebido maquinha
B59: BLOCO ITAU
B60: Pix e depositos Vendas
AS61: =#REF! -> #REF!
B62: BLOCO ESTOQUES
B63: Venda de Gasolina | AS63: =#REF! -> #REF!
B64: Venda de Etanol | AS64: =#REF! -> #REF!
B65: Venda de Diesel | AS65: =#REF! -> #REF!
B66: Separação Cartão/Outros | AS66: =#REF! -> #REF!
B67: Ajuste estoque e valor diário (lucro embutido) | AS67: =#REF! -> #REF!
AS68: =#REF! -> #REF!
B69: Saldo Giro no dia | C69: =D70+E70+F70+G70+H70+I70+J70+M70+P70 -> 117279.93 | AR69: =SUM($T53:AQ69) -> -487087.83 | AV69: TERCEIROS
B70: Saldo Líquido do dia | C70: =AR70 -> -368502.61 | D70: =SUM(D53:D69) -> 12717.607 | E70: =SUM(E53:E69) -> -43287.79 | F70: =SUM(F53:F69) -> 0.65 | G70: =SUM(G53:G69) -> 0 | H70: =SUM(H53:H69) -> 65082.293 | I70: =SUM(I53:I69) -> 10004.65 | J70: =SUM(J53:J69) -> 0 | K70: =SUM(K53:K69) -> 12170 | L70: =M70/K70 -> 5.1465924 | M70: =ROUND(SUM(M53:M69),2) -> 62634.03 | N70: =SUM(N53:N69) -> 2783 | O70: =P70/N70 -> 3.6394143 | P70: =ROUND(SUM(P53:P69),2) -> 10128.49 | Q70: =SUM(Q53:Q69) -> 214 | R70: =S70/Q70 -> 6.099486 | S70: =ROUND(SUM(S53:S69),2) -> 1305.29 | T70: =SUM(T53:T69) -> -537317.13 | U70: =SUM(U53:U69) -> 50229.3 | V70: =SUM(V53:V69) -> 0 | W70: =SUM(W53:W69) -> 0 | X70: =SUM(X53:X69) -> 0 | Y70: =SUM(Y53:Y69) -> 0 | Z70: =SUM(Z53:Z69) -> 0 | AA70: =SUM(AA53:AA69) -> 0 | ... AQ70: =SUM(AQ53:AQ69) -> 0 | AR70: =D70+E70+F70+G70+H70+I70+J70+M70+P70+S70+SUM(T70:AQ70) -> -368502.61 | AV70: CONSOLIDADO
A71: =A54+1 -> 46300 | B71: BLOCO SPOT
B72: Credito Vendas Cartão | AT72: Saidas | AU72: #REF!
B73: Desconto taxas Cartão | AT73: Saidas | AU73: #REF!
B74: Pix recebido maquininha
B75: Tarifa pix recebido maquinha
B76: BLOCO ITAU
B77: Pix e depositos Vendas
AS78: =#REF! -> #REF!
B79: BLOCO ESTOQUES
B80: Venda de Gasolina | AS80: =#REF! -> #REF!
B81: Venda de Etanol | AS81: =#REF! -> #REF!
B82: Venda de Diesel | AS82: =#REF! -> #REF!
B83: Separação Cartão/Outros | AS83: =#REF! -> #REF!
B84: Ajuste estoque e valor diário (lucro embutido) | AS84: =#REF! -> #REF!
AS85: =#REF! -> #REF!
B86: Saldo Giro no dia | C86: =D87+E87+F87+G87+H87+I87+J87+M87+P87 -> 117279.93 | AR86: =SUM($T70:AQ86) -> -487087.83 | AV86: TERCEIROS
B87: Saldo Líquido do dia | C87: =AR87 -> -368502.61 | D87: =SUM(D70:D86) -> 12717.607 | E87: =SUM(E70:E86) -> -43287.79 | F87: =SUM(F70:F86) -> 0.65 | G87: =SUM(G70:G86) -> 0 | H87: =SUM(H70:H86) -> 65082.293 | I87: =SUM(I70:I86) -> 10004.65 | J87: =SUM(J70:J86) -> 0 | K87: =SUM(K70:K86) -> 12170 | L87: =M87/K87 -> 5.1465924 | M87: =ROUND(SUM(M70:M86),2) -> 62634.03 | N87: =SUM(N70:N86) -> 2783 | O87: =P87/N87 -> 3.6394143 | P87: =ROUND(SUM(P70:P86),2) -> 10128.49 | Q87: =SUM(Q70:Q86) -> 214 | R87: =S87/Q87 -> 6.099486 | S87: =ROUND(SUM(S70:S86),2) -> 1305.29 | T87: =SUM(T70:T86) -> -537317.13 | U87: =SUM(U70:U86) -> 50229.3 | V87: =SUM(V70:V86) -> 0 | W87: =SUM(W70:W86) -> 0 | X87: =SUM(X70:X86) -> 0 | Y87: =SUM(Y70:Y86) -> 0 | Z87: =SUM(Z70:Z86) -> 0 | AA87: =SUM(AA70:AA86) -> 0 | ... AQ87: =SUM(AQ70:AQ86) -> 0 | AR87: =D87+E87+F87+G87+H87+I87+J87+M87+P87+S87+SUM(T87:AQ87) -> -368502.61 | AV87: CONSOLIDADO
A88: =A71+1 -> 46301 | B88: BLOCO SPOT
B89: Credito Vendas Cartão | AT89: Saidas | AU89: #REF!
B90: Desconto taxas Cartão | AT90: Saidas | AU90: #REF!
B91: Pix recebido maquininha
B92: Tarifa pix recebido maquinha
B93: BLOCO ITAU
B94: Pix e depositos Vendas
AS95: =#REF! -> #REF!
B96: BLOCO ESTOQUES
B97: Venda de Gasolina | AS97: =#REF! -> #REF!
B98: Venda de Etanol | AS98: =#REF! -> #REF!
B99: Venda de Diesel | AS99: =#REF! -> #REF!
B100: Separação Cartão/Outros | AS100: =#REF! -> #REF!
...

Sheet Nov26
A1: PERÍODO 01 á 30/NOV/26 | C1: =D2+E2+F2+G2+H2+I2+J2+M2+P2 -> 117279.93 | D1: SPOT | E1: ITAU | F1: LUCILA | G1: HADEN | H1: CAIXA | I1: CARTAO | J1: VENDAS | K1: GASOLINA | N1: ETANOL | Q1: DIESEL | T1: ERALDO | U1: LUIZ F. | V1: LUCILA | W1: DIVIDA | X1: AVANT | Y1: WL | AR1: Total | AS1: Saldo Total | AT1: Saldo Edson | AU1: Saldo Master
B2: Saldo Inicial do dia | C2: =D2+E2+F2+G2+H2+I2+J2+M2+P2+SUM(T2:AQ2) -> -369807.9 | D2: ='Out26'!D529 -> 12717.607 | E2: ='Out26'!E529 -> -43287.79 | F2: ='Out26'!F529 -> 0.65 | G2: ='Out26'!G529 -> 0 | H2: ='Out26'!H529 -> 65082.293 | I2: ='Out26'!I529 -> 10004.65 | J2: ='Out26'!J529 -> 0 | K2: ='Out26'!K529 -> 12170 | ... AR2: ='Out26'!AR529 -> -368502.61 | AS2: =#REF! -> #REF! | AT2: =#REF! -> #REF! | AU2: =AS2-AT2 -> #REF!
A3: 46327 | B3: BLOCO SPOT
B4: Credito Vendas Cartão | AT4: Saidas | AU4: #REF!
B5: Desconto taxas Cartão | AT5: Saidas | AU5: #REF!
B6: Pix recebido maquininha
B7: Tarifa pix recebido maquinha
B8: BLOCO ITAU
B9: Pix e depositos Vendas
AS10: =#REF! -> #REF!
B11: BLOCO ESTOQUES
B12: Venda de Gasolina | AS12: =#REF! -> #REF!
B13: Venda de Etanol | AS13: =#REF! -> #REF!
B14: Venda de Diesel | AS14: =#REF! -> #REF!
B15: Separação Cartão/Outros | AS15: =#REF! -> #REF!
B16: Ajuste estoque e valor diário (lucro embutido) | AS16: =#REF! -> #REF!
AS17: =#REF! -> #REF!
B18: Saldo Giro no dia | C18: =D19+E19+F19+G19+H19+I19+J19+M19+P19+S19 -> 118585.22 | AR18: =SUM($T2:AQ18) -> -487087.83 | AV18: TERCEIROS
B19: Saldo Líquido do dia | C19: =AR19 -> -368502.61 | D19: =SUM(D2:D18) -> 12717.607 | E19: =SUM(E2:E18) -> -43287.79 | F19: =SUM(F2:F18) -> 0.65 | G19: =SUM(G2:G18) -> 0 | H19: =SUM(H2:H18) -> 65082.293 | I19: =SUM(I2:I18) -> 10004.65 | J19: =SUM(J2:J18) -> 0 | K19: =SUM(K2:K18) -> 12170 | L19: =M19/K19 -> 5.1465924 | M19: =ROUND(SUM(M2:M18),2) -> 62634.03 | N19: =SUM(N2:N18) -> 2783 | O19: =P19/N19 -> 3.6394143 | P19: =ROUND(SUM(P2:P18),2) -> 10128.49 | Q19: =SUM(Q2:Q18) -> 214 | R19: =S19/Q19 -> 6.099486 | S19: =ROUND(SUM(S2:S18),2) -> 1305.29 | T19: =SUM(T2:T18) -> -537317.13 | U19: =SUM(U2:U18) -> 50229.3 | V19: =SUM(V2:V18) -> 0 | W19: =SUM(W2:W18) -> 0 | X19: =SUM(X2:X18) -> 0 | Y19: =SUM(Y2:Y18) -> 0 | Z19: =SUM(Z2:Z18) -> 0 | AA19: =SUM(AA2:AA18) -> 0 | ... AK19: =SUM(AK2:AK18) -> 0 | AM19: =SUM(AM2:AM18) -> 0 | AN19: =SUM(AN2:AN18) -> 0 | AO19: =SUM(AO2:AO18) -> 0 | AP19: =SUM(AP2:AP18) -> 0 | AQ19: =SUM(AQ2:AQ18) -> 0 | AR19: =D19+E19+F19+G19+H19+I19+J19+M19+P19+S19+SUM(T19:AQ19) -> -368502.61 | AV19: CONSOLIDADO
A20: =A3+1 -> 46328 | B20: BLOCO SPOT
B21: Credito Vendas Cartão | AT21: Saidas | AU21: #REF!
B22: Desconto taxas Cartão | AT22: Saidas | AU22: #REF!
B23: Pix recebido maquininha
B24: Tarifa pix recebido maquinha
B25: BLOCO ITAU
B26: Pix e depositos Vendas
AS27: =#REF! -> #REF!
B28: BLOCO ESTOQUES
B29: Venda de Gasolina | AS29: =#REF! -> #REF!
B30: Venda de Etanol | AS30: =#REF! -> #REF!
B31: Venda de Diesel | AS31: =#REF! -> #REF!
B32: Separação Cartão/Outros | AS32: =#REF! -> #REF!
B33: Ajuste estoque e valor diário (lucro embutido) | AS33: =#REF! -> #REF!
AS34: =#REF! -> #REF!
B35: Saldo Giro no dia | C35: =D36+E36+F36+G36+H36+I36+J36+M36+P36 -> 117279.93 | AR35: =SUM($T19:AQ35) -> -487087.83 | AV35: TERCEIROS
B36: Saldo Líquido do dia | C36: =AR36 -> -368502.61 | D36: =SUM(D19:D35) -> 12717.607 | E36: =SUM(E19:E35) -> -43287.79 | F36: =SUM(F19:F35) -> 0.65 | G36: =SUM(G19:G35) -> 0 | H36: =SUM(H19:H35) -> 65082.293 | I36: =SUM(I19:I35) -> 10004.65 | J36: =SUM(J19:J35) -> 0 | K36: =SUM(K19:K35) -> 12170 | L36: =M36/K36 -> 5.1465924 | M36: =ROUND(SUM(M19:M35),2) -> 62634.03 | N36: =SUM(N19:N35) -> 2783 | O36: =P36/N36 -> 3.6394143 | P36: =ROUND(SUM(P19:P35),2) -> 10128.49 | Q36: =SUM(Q19:Q35) -> 214 | R36: =S36/Q36 -> 6.099486 | S36: =ROUND(SUM(S19:S35),2) -> 1305.29 | T36: =SUM(T19:T35) -> -537317.13 | U36: =SUM(U19:U35) -> 50229.3 | V36: =SUM(V19:V35) -> 0 | W36: =SUM(W19:W35) -> 0 | X36: =SUM(X19:X35) -> 0 | Y36: =SUM(Y19:Y35) -> 0 | Z36: =SUM(Z19:Z35) -> 0 | AA36: =SUM(AA19:AA35) -> 0 | ... AQ36: =SUM(AQ19:AQ35) -> 0 | AR36: =D36+E36+F36+G36+H36+I36+J36+M36+P36+S36+SUM(T36:AQ36) -> -368502.61 | AV36: CONSOLIDADO
A37: =A20+1 -> 46329 | B37: BLOCO SPOT
B38: Credito Vendas Cartão | AT38: Saidas | AU38: #REF!
B39: Desconto taxas Cartão | AT39: Saidas | AU39: #REF!
B40: Pix recebido maquininha
B41: Tarifa pix recebido maquinha
B42: BLOCO ITAU
B43: Pix e depositos Vendas
AS44: =#REF! -> #REF!
B45: BLOCO ESTOQUES
B46: Venda de Gasolina | AS46: =#REF! -> #REF!
B47: Venda de Etanol | AS47: =#REF! -> #REF!
B48: Venda de Diesel | AS48: =#REF! -> #REF!
B49: Separação Cartão/Outros | AS49: =#REF! -> #REF!
B50: Ajuste estoque e valor diário (lucro embutido) | AS50: =#REF! -> #REF!
AS51: =#REF! -> #REF!
B52: Saldo Giro no dia | C52: =D53+E53+F53+G53+H53+I53+J53+M53+P53 -> 117279.93 | AR52: =SUM($T36:AQ52) -> -487087.83 | AV52: TERCEIROS
B53: Saldo Líquido do dia | C53: =AR53 -> -368502.61 | D53: =SUM(D36:D52) -> 12717.607 | E53: =SUM(E36:E52) -> -43287.79 | F53: =SUM(F36:F52) -> 0.65 | G53: =SUM(G36:G52) -> 0 | H53: =SUM(H36:H52) -> 65082.293 | I53: =SUM(I36:I52) -> 10004.65 | J53: =SUM(J36:J52) -> 0 | K53: =SUM(K36:K52) -> 12170 | L53: =M53/K53 -> 5.1465924 | M53: =ROUND(SUM(M36:M52),2) -> 62634.03 | N53: =SUM(N36:N52) -> 2783 | O53: =P53/N53 -> 3.6394143 | P53: =ROUND(SUM(P36:P52),2) -> 10128.49 | Q53: =SUM(Q36:Q52) -> 214 | R53: =S53/Q53 -> 6.099486 | S53: =ROUND(SUM(S36:S52),2) -> 1305.29 | T53: =SUM(T36:T52) -> -537317.13 | U53: =SUM(U36:U52) -> 50229.3 | V53: =SUM(V36:V52) -> 0 | W53: =SUM(W36:W52) -> 0 | X53: =SUM(X36:X52) -> 0 | Y53: =SUM(Y36:Y52) -> 0 | Z53: =SUM(Z36:Z52) -> 0 | AA53: =SUM(AA36:AA52) -> 0 | ... AQ53: =SUM(AQ36:AQ52) -> 0 | AR53: =D53+E53+F53+G53+H53+I53+J53+M53+P53+S53+SUM(T53:AQ53) -> -368502.61 | AV53: CONSOLIDADO
A54: =A37+1 -> 46330 | B54: BLOCO SPOT
B55: Credito Vendas Cartão | AT55: Saidas | AU55: #REF!
B56: Desconto taxas Cartão | AT56: Saidas | AU56: #REF!
B57: Pix recebido maquininha
B58: Tarifa pix recebido maquinha
B59: BLOCO ITAU
B60: Pix e depositos Vendas
AS61: =#REF! -> #REF!
B62: BLOCO ESTOQUES
B63: Venda de Gasolina | AS63: =#REF! -> #REF!
B64: Venda de Etanol | AS64: =#REF! -> #REF!
B65: Venda de Diesel | AS65: =#REF! -> #REF!
B66: Separação Cartão/Outros | AS66: =#REF! -> #REF!
B67: Ajuste estoque e valor diário (lucro embutido) | AS67: =#REF! -> #REF!
AS68: =#REF! -> #REF!
B69: Saldo Giro no dia | C69: =D70+E70+F70+G70+H70+I70+J70+M70+P70 -> 117279.93 | AR69: =SUM($T53:AQ69) -> -487087.83 | AV69: TERCEIROS
B70: Saldo Líquido do dia | C70: =AR70 -> -368502.61 | D70: =SUM(D53:D69) -> 12717.607 | E70: =SUM(E53:E69) -> -43287.79 | F70: =SUM(F53:F69) -> 0.65 | G70: =SUM(G53:G69) -> 0 | H70: =SUM(H53:H69) -> 65082.293 | I70: =SUM(I53:I69) -> 10004.65 | J70: =SUM(J53:J69) -> 0 | K70: =SUM(K53:K69) -> 12170 | L70: =M70/K70 -> 5.1465924 | M70: =ROUND(SUM(M53:M69),2) -> 62634.03 | N70: =SUM(N53:N69) -> 2783 | O70: =P70/N70 -> 3.6394143 | P70: =ROUND(SUM(P53:P69),2) -> 10128.49 | Q70: =SUM(Q53:Q69) -> 214 | R70: =S70/Q70 -> 6.099486 | S70: =ROUND(SUM(S53:S69),2) -> 1305.29 | T70: =SUM(T53:T69) -> -537317.13 | U70: =SUM(U53:U69) -> 50229.3 | V70: =SUM(V53:V69) -> 0 | W70: =SUM(W53:W69) -> 0 | X70: =SUM(X53:X69) -> 0 | Y70: =SUM(Y53:Y69) -> 0 | Z70: =SUM(Z53:Z69) -> 0 | AA70: =SUM(AA53:AA69) -> 0 | ... AQ70: =SUM(AQ53:AQ69) -> 0 | AR70: =D70+E70+F70+G70+H70+I70+J70+M70+P70+S70+SUM(T70:AQ70) -> -368502.61 | AV70: CONSOLIDADO
A71: =A54+1 -> 46331 | B71: BLOCO SPOT
B72: Credito Vendas Cartão | AT72: Saidas | AU72: #REF!
B73: Desconto taxas Cartão | AT73: Saidas | AU73: #REF!
B74: Pix recebido maquininha
B75: Tarifa pix recebido maquinha
B76: BLOCO ITAU
B77: Pix e depositos Vendas
AS78: =#REF! -> #REF!
B79: BLOCO ESTOQUES
B80: Venda de Gasolina | AS80: =#REF! -> #REF!
B81: Venda de Etanol | AS81: =#REF! -> #REF!
B82: Venda de Diesel | AS82: =#REF! -> #REF!
B83: Separação Cartão/Outros | AS83: =#REF! -> #REF!
B84: Ajuste estoque e valor diário (lucro embutido) | AS84: =#REF! -> #REF!
AS85: =#REF! -> #REF!
B86: Saldo Giro no dia | C86: =D87+E87+F87+G87+H87+I87+J87+M87+P87 -> 117279.93 | AR86: =SUM($T70:AQ86) -> -487087.83 | AV86: TERCEIROS
B87: Saldo Líquido do dia | C87: =AR87 -> -368502.61 | D87: =SUM(D70:D86) -> 12717.607 | E87: =SUM(E70:E86) -> -43287.79 | F87: =SUM(F70:F86) -> 0.65 | G87: =SUM(G70:G86) -> 0 | H87: =SUM(H70:H86) -> 65082.293 | I87: =SUM(I70:I86) -> 10004.65 | J87: =SUM(J70:J86) -> 0 | K87: =SUM(K70:K86) -> 12170 | L87: =M87/K87 -> 5.1465924 | M87: =ROUND(SUM(M70:M86),2) -> 62634.03 | N87: =SUM(N70:N86) -> 2783 | O87: =P87/N87 -> 3.6394143 | P87: =ROUND(SUM(P70:P86),2) -> 10128.49 | Q87: =SUM(Q70:Q86) -> 214 | R87: =S87/Q87 -> 6.099486 | S87: =ROUND(SUM(S70:S86),2) -> 1305.29 | T87: =SUM(T70:T86) -> -537317.13 | U87: =SUM(U70:U86) -> 50229.3 | V87: =SUM(V70:V86) -> 0 | W87: =SUM(W70:W86) -> 0 | X87: =SUM(X70:X86) -> 0 | Y87: =SUM(Y70:Y86) -> 0 | Z87: =SUM(Z70:Z86) -> 0 | AA87: =SUM(AA70:AA86) -> 0 | ... AQ87: =SUM(AQ70:AQ86) -> 0 | AR87: =D87+E87+F87+G87+H87+I87+J87+M87+P87+S87+SUM(T87:AQ87) -> -368502.61 | AV87: CONSOLIDADO
A88: =A71+1 -> 46332 | B88: BLOCO SPOT
B89: Credito Vendas Cartão | AT89: Saidas | AU89: #REF!
B90: Desconto taxas Cartão | AT90: Saidas | AU90: #REF!
B91: Pix recebido maquininha
B92: Tarifa pix recebido maquinha
B93: BLOCO ITAU
B94: Pix e depositos Vendas
AS95: =#REF! -> #REF!
B96: BLOCO ESTOQUES
B97: Venda de Gasolina | AS97: =#REF! -> #REF!
B98: Venda de Etanol | AS98: =#REF! -> #REF!
B99: Venda de Diesel | AS99: =#REF! -> #REF!
B100: Separação Cartão/Outros | AS100: =#REF! -> #REF!
...

Sheet Dez26
A1: PERÍODO 01 á 31/DEZ/26 | C1: =D2+E2+F2+G2+H2+I2+J2+M2+P2 -> 117279.93 | D1: SPOT | E1: ITAU | F1: LUCILA | G1: HADEN | H1: CAIXA | I1: CARTAO | J1: VENDAS | K1: GASOLINA | N1: ETANOL | Q1: DIESEL | T1: ERALDO | U1: LUIZ F. | V1: LUCILA | W1: DIVIDA | X1: AVANT | Y1: WL | AR1: Total | AS1: Saldo Total | AT1: Saldo Edson | AU1: Saldo Master
B2: Saldo Inicial do dia | C2: =D2+E2+F2+G2+H2+I2+J2+M2+P2+SUM(T2:AQ2) -> -369807.9 | D2: ='Nov26'!D529 -> 12717.607 | E2: ='Nov26'!E529 -> -43287.79 | F2: ='Nov26'!F529 -> 0.65 | G2: ='Nov26'!G529 -> 0 | H2: ='Nov26'!H529 -> 65082.293 | I2: ='Nov26'!I529 -> 10004.65 | J2: ='Nov26'!J529 -> 0 | K2: ='Nov26'!K529 -> 12170 | ... AR2: ='Nov26'!AR529 -> -368502.61 | AS2: =#REF! -> #REF! | AT2: =#REF! -> #REF! | AU2: =AS2-AT2 -> #REF!
A3: 46357 | B3: BLOCO SPOT
B4: Credito Vendas Cartão | AT4: Saidas | AU4: #REF!
B5: Desconto taxas Cartão | AT5: Saidas | AU5: #REF!
B6: Pix recebido maquininha
B7: Tarifa pix recebido maquinha
B8: BLOCO ITAU
B9: Pix e depositos Vendas
AS10: =#REF! -> #REF!
B11: BLOCO ESTOQUES
B12: Venda de Gasolina | AS12: =#REF! -> #REF!
B13: Venda de Etanol | AS13: =#REF! -> #REF!
B14: Venda de Diesel | AS14: =#REF! -> #REF!
B15: Separação Cartão/Outros | AS15: =#REF! -> #REF!
B16: Ajuste estoque e valor diário (lucro embutido) | AS16: =#REF! -> #REF!
AS17: =#REF! -> #REF!
B18: Saldo Giro no dia | C18: =D19+E19+F19+G19+H19+I19+J19+M19+P19+S19 -> 118585.22 | AR18: =SUM($T2:AQ18) -> -487087.83 | AV18: TERCEIROS
B19: Saldo Líquido do dia | C19: =AR19 -> -368502.61 | D19: =SUM(D2:D18) -> 12717.607 | E19: =SUM(E2:E18) -> -43287.79 | F19: =SUM(F2:F18) -> 0.65 | G19: =SUM(G2:G18) -> 0 | H19: =SUM(H2:H18) -> 65082.293 | I19: =SUM(I2:I18) -> 10004.65 | J19: =SUM(J2:J18) -> 0 | K19: =SUM(K2:K18) -> 12170 | L19: =M19/K19 -> 5.1465924 | M19: =ROUND(SUM(M2:M18),2) -> 62634.03 | N19: =SUM(N2:N18) -> 2783 | O19: =P19/N19 -> 3.6394143 | P19: =ROUND(SUM(P2:P18),2) -> 10128.49 | Q19: =SUM(Q2:Q18) -> 214 | R19: =S19/Q19 -> 6.099486 | S19: =ROUND(SUM(S2:S18),2) -> 1305.29 | T19: =SUM(T2:T18) -> -537317.13 | U19: =SUM(U2:U18) -> 50229.3 | V19: =SUM(V2:V18) -> 0 | W19: =SUM(W2:W18) -> 0 | X19: =SUM(X2:X18) -> 0 | Y19: =SUM(Y2:Y18) -> 0 | Z19: =SUM(Z2:Z18) -> 0 | AA19: =SUM(AA2:AA18) -> 0 | ... AK19: =SUM(AK2:AK18) -> 0 | AM19: =SUM(AM2:AM18) -> 0 | AN19: =SUM(AN2:AN18) -> 0 | AO19: =SUM(AO2:AO18) -> 0 | AP19: =SUM(AP2:AP18) -> 0 | AQ19: =SUM(AQ2:AQ18) -> 0 | AR19: =D19+E19+F19+G19+H19+I19+J19+M19+P19+S19+SUM(T19:AQ19) -> -368502.61 | AV19: CONSOLIDADO
A20: =A3+1 -> 46358 | B20: BLOCO SPOT
B21: Credito Vendas Cartão | AT21: Saidas | AU21: #REF!
B22: Desconto taxas Cartão | AT22: Saidas | AU22: #REF!
B23: Pix recebido maquininha
B24: Tarifa pix recebido maquinha
B25: BLOCO ITAU
B26: Pix e depositos Vendas
AS27: =#REF! -> #REF!
B28: BLOCO ESTOQUES
B29: Venda de Gasolina | AS29: =#REF! -> #REF!
B30: Venda de Etanol | AS30: =#REF! -> #REF!
B31: Venda de Diesel | AS31: =#REF! -> #REF!
B32: Separação Cartão/Outros | AS32: =#REF! -> #REF!
B33: Ajuste estoque e valor diário (lucro embutido) | AS33: =#REF! -> #REF!
AS34: =#REF! -> #REF!
B35: Saldo Giro no dia | C35: =D36+E36+F36+G36+H36+I36+J36+M36+P36 -> 117279.93 | AR35: =SUM($T19:AQ35) -> -487087.83 | AV35: TERCEIROS
B36: Saldo Líquido do dia | C36: =AR36 -> -368502.61 | D36: =SUM(D19:D35) -> 12717.607 | E36: =SUM(E19:E35) -> -43287.79 | F36: =SUM(F19:F35) -> 0.65 | G36: =SUM(G19:G35) -> 0 | H36: =SUM(H19:H35) -> 65082.293 | I36: =SUM(I19:I35) -> 10004.65 | J36: =SUM(J19:J35) -> 0 | K36: =SUM(K19:K35) -> 12170 | L36: =M36/K36 -> 5.1465924 | M36: =ROUND(SUM(M19:M35),2) -> 62634.03 | N36: =SUM(N19:N35) -> 2783 | O36: =P36/N36 -> 3.6394143 | P36: =ROUND(SUM(P19:P35),2) -> 10128.49 | Q36: =SUM(Q19:Q35) -> 214 | R36: =S36/Q36 -> 6.099486 | S36: =ROUND(SUM(S19:S35),2) -> 1305.29 | T36: =SUM(T19:T35) -> -537317.13 | U36: =SUM(U19:U35) -> 50229.3 | V36: =SUM(V19:V35) -> 0 | W36: =SUM(W19:W35) -> 0 | X36: =SUM(X19:X35) -> 0 | Y36: =SUM(Y19:Y35) -> 0 | Z36: =SUM(Z19:Z35) -> 0 | AA36: =SUM(AA19:AA35) -> 0 | ... AQ36: =SUM(AQ19:AQ35) -> 0 | AR36: =D36+E36+F36+G36+H36+I36+J36+M36+P36+S36+SUM(T36:AQ36) -> -368502.61 | AV36: CONSOLIDADO
A37: =A20+1 -> 46359 | B37: BLOCO SPOT
B38: Credito Vendas Cartão | AT38: Saidas | AU38: #REF!
B39: Desconto taxas Cartão | AT39: Saidas | AU39: #REF!
B40: Pix recebido maquininha
B41: Tarifa pix recebido maquinha
B42: BLOCO ITAU
B43: Pix e depositos Vendas
AS44: =#REF! -> #REF!
B45: BLOCO ESTOQUES
B46: Venda de Gasolina | AS46: =#REF! -> #REF!
B47: Venda de Etanol | AS47: =#REF! -> #REF!
B48: Venda de Diesel | AS48: =#REF! -> #REF!
B49: Separação Cartão/Outros | AS49: =#REF! -> #REF!
B50: Ajuste estoque e valor diário (lucro embutido) | AS50: =#REF! -> #REF!
AS51: =#REF! -> #REF!
B52: Saldo Giro no dia | C52: =D53+E53+F53+G53+H53+I53+J53+M53+P53 -> 117279.93 | AR52: =SUM($T36:AQ52) -> -487087.83 | AV52: TERCEIROS
B53: Saldo Líquido do dia | C53: =AR53 -> -368502.61 | D53: =SUM(D36:D52) -> 12717.607 | E53: =SUM(E36:E52) -> -43287.79 | F53: =SUM(F36:F52) -> 0.65 | G53: =SUM(G36:G52) -> 0 | H53: =SUM(H36:H52) -> 65082.293 | I53: =SUM(I36:I52) -> 10004.65 | J53: =SUM(J36:J52) -> 0 | K53: =SUM(K36:K52) -> 12170 | L53: =M53/K53 -> 5.1465924 | M53: =ROUND(SUM(M36:M52),2) -> 62634.03 | N53: =SUM(N36:N52) -> 2783 | O53: =P53/N53 -> 3.6394143 | P53: =ROUND(SUM(P36:P52),2) -> 10128.49 | Q53: =SUM(Q36:Q52) -> 214 | R53: =S53/Q53 -> 6.099486 | S53: =ROUND(SUM(S36:S52),2) -> 1305.29 | T53: =SUM(T36:T52) -> -537317.13 | U53: =SUM(U36:U52) -> 50229.3 | V53: =SUM(V36:V52) -> 0 | W53: =SUM(W36:W52) -> 0 | X53: =SUM(X36:X52) -> 0 | Y53: =SUM(Y36:Y52) -> 0 | Z53: =SUM(Z36:Z52) -> 0 | AA53: =SUM(AA36:AA52) -> 0 | ... AQ53: =SUM(AQ36:AQ52) -> 0 | AR53: =D53+E53+F53+G53+H53+I53+J53+M53+P53+S53+SUM(T53:AQ53) -> -368502.61 | AV53: CONSOLIDADO
A54: =A37+1 -> 46360 | B54: BLOCO SPOT
B55: Credito Vendas Cartão | AT55: Saidas | AU55: #REF!
B56: Desconto taxas Cartão | AT56: Saidas | AU56: #REF!
B57: Pix recebido maquininha
B58: Tarifa pix recebido maquinha
B59: BLOCO ITAU
B60: Pix e depositos Vendas
AS61: =#REF! -> #REF!
B62: BLOCO ESTOQUES
B63: Venda de Gasolina | AS63: =#REF! -> #REF!
B64: Venda de Etanol | AS64: =#REF! -> #REF!
B65: Venda de Diesel | AS65: =#REF! -> #REF!
B66: Separação Cartão/Outros | AS66: =#REF! -> #REF!
B67: Ajuste estoque e valor diário (lucro embutido) | AS67: =#REF! -> #REF!
AS68: =#REF! -> #REF!
B69: Saldo Giro no dia | C69: =D70+E70+F70+G70+H70+I70+J70+M70+P70 -> 117279.93 | AR69: =SUM($T53:AQ69) -> -487087.83 | AV69: TERCEIROS
B70: Saldo Líquido do dia | C70: =AR70 -> -368502.61 | D70: =SUM(D53:D69) -> 12717.607 | E70: =SUM(E53:E69) -> -43287.79 | F70: =SUM(F53:F69) -> 0.65 | G70: =SUM(G53:G69) -> 0 | H70: =SUM(H53:H69) -> 65082.293 | I70: =SUM(I53:I69) -> 10004.65 | J70: =SUM(J53:J69) -> 0 | K70: =SUM(K53:K69) -> 12170 | L70: =M70/K70 -> 5.1465924 | M70: =ROUND(SUM(M53:M69),2) -> 62634.03 | N70: =SUM(N53:N69) -> 2783 | O70: =P70/N70 -> 3.6394143 | P70: =ROUND(SUM(P53:P69),2) -> 10128.49 | Q70: =SUM(Q53:Q69) -> 214 | R70: =S70/Q70 -> 6.099486 | S70: =ROUND(SUM(S53:S69),2) -> 1305.29 | T70: =SUM(T53:T69) -> -537317.13 | U70: =SUM(U53:U69) -> 50229.3 | V70: =SUM(V53:V69) -> 0 | W70: =SUM(W53:W69) -> 0 | X70: =SUM(X53:X69) -> 0 | Y70: =SUM(Y53:Y69) -> 0 | Z70: =SUM(Z53:Z69) -> 0 | AA70: =SUM(AA53:AA69) -> 0 | ... AQ70: =SUM(AQ53:AQ69) -> 0 | AR70: =D70+E70+F70+G70+H70+I70+J70+M70+P70+S70+SUM(T70:AQ70) -> -368502.61 | AV70: CONSOLIDADO
A71: =A54+1 -> 46361 | B71: BLOCO SPOT
B72: Credito Vendas Cartão | AT72: Saidas | AU72: #REF!
B73: Desconto taxas Cartão | AT73: Saidas | AU73: #REF!
B74: Pix recebido maquininha
B75: Tarifa pix recebido maquinha
B76: BLOCO ITAU
B77: Pix e depositos Vendas
AS78: =#REF! -> #REF!
B79: BLOCO ESTOQUES
B80: Venda de Gasolina | AS80: =#REF! -> #REF!
B81: Venda de Etanol | AS81: =#REF! -> #REF!
B82: Venda de Diesel | AS82: =#REF! -> #REF!
B83: Separação Cartão/Outros | AS83: =#REF! -> #REF!
B84: Ajuste estoque e valor diário (lucro embutido) | AS84: =#REF! -> #REF!
AS85: =#REF! -> #REF!
B86: Saldo Giro no dia | C86: =D87+E87+F87+G87+H87+I87+J87+M87+P87 -> 117279.93 | AR86: =SUM($T70:AQ86) -> -487087.83 | AV86: TERCEIROS
B87: Saldo Líquido do dia | C87: =AR87 -> -368502.61 | D87: =SUM(D70:D86) -> 12717.607 | E87: =SUM(E70:E86) -> -43287.79 | F87: =SUM(F70:F86) -> 0.65 | G87: =SUM(G70:G86) -> 0 | H87: =SUM(H70:H86) -> 65082.293 | I87: =SUM(I70:I86) -> 10004.65 | J87: =SUM(J70:J86) -> 0 | K87: =SUM(K70:K86) -> 12170 | L87: =M87/K87 -> 5.1465924 | M87: =ROUND(SUM(M70:M86),2) -> 62634.03 | N87: =SUM(N70:N86) -> 2783 | O87: =P87/N87 -> 3.6394143 | P87: =ROUND(SUM(P70:P86),2) -> 10128.49 | Q87: =SUM(Q70:Q86) -> 214 | R87: =S87/Q87 -> 6.099486 | S87: =ROUND(SUM(S70:S86),2) -> 1305.29 | T87: =SUM(T70:T86) -> -537317.13 | U87: =SUM(U70:U86) -> 50229.3 | V87: =SUM(V70:V86) -> 0 | W87: =SUM(W70:W86) -> 0 | X87: =SUM(X70:X86) -> 0 | Y87: =SUM(Y70:Y86) -> 0 | Z87: =SUM(Z70:Z86) -> 0 | AA87: =SUM(AA70:AA86) -> 0 | ... AQ87: =SUM(AQ70:AQ86) -> 0 | AR87: =D87+E87+F87+G87+H87+I87+J87+M87+P87+S87+SUM(T87:AQ87) -> -368502.61 | AV87: CONSOLIDADO
A88: =A71+1 -> 46362 | B88: BLOCO SPOT
B89: Credito Vendas Cartão | AT89: Saidas | AU89: #REF!
B90: Desconto taxas Cartão | AT90: Saidas | AU90: #REF!
B91: Pix recebido maquininha
B92: Tarifa pix recebido maquinha
B93: BLOCO ITAU
B94: Pix e depositos Vendas
AS95: =#REF! -> #REF!
B96: BLOCO ESTOQUES
B97: Venda de Gasolina | AS97: =#REF! -> #REF!
B98: Venda de Etanol | AS98: =#REF! -> #REF!
B99: Venda de Diesel | AS99: =#REF! -> #REF!
B100: Separação Cartão/Outros | AS100: =#REF! -> #REF!
...

Sheet 01-30abr (2)
A1: PERÍODO 01 á 30/ABR/26 | C1: =D2+E2+F2+G2+H2+I2+J2+M2+P2 -> 117279.93 | D1: SPOT | E1: ITAU | F1: LUCILA | G1: HADEN | H1: CAIXA | I1: CARTAO | J1: VENDAS | K1: GASOLINA | N1: ETANOL | Q1: DIESEL | T1: ERALDO | U1: LUIZ F. | V1: LUCILA | W1: DIVIDA | X1: AVANT | Y1: WL | AR1: Total | AS1: Saldo Total | AT1: Saldo Edson | AU1: Saldo Master
B2: Saldo Inicial do dia | C2: =D2+E2+F2+G2+H2+I2+J2+M2+P2+SUM(T2:AQ2) -> -369807.9 | D2: ='Mar26'!D529 -> 12717.607 | E2: ='Mar26'!E529 -> -43287.79 | F2: ='Mar26'!F529 -> 0.65 | G2: ='Mar26'!G529 -> 0 | H2: ='Mar26'!H529 -> 65082.293 | I2: ='Mar26'!I529 -> 10004.65 | J2: ='Mar26'!J529 -> 0 | K2: ='Mar26'!K529 -> 12170 | ... P2: ='Mar26'!P529 -> 10128.49 | Q2: 214 | R2: 6.0995 | S2: =Q2*R2 -> 1305.293 | T2: ='Mar26'!T529 -> -537317.13 | U2: ='Mar26'!U529 -> 50229.3 | V2: ='Mar26'!V529 -> 0 | W2: ='Mar26'!W529 -> 0 | X2: ='Mar26'!X529 -> 0 | Y2: ='Mar26'!Y529 -> 0 | Z2: ='Mar26'!Z529 -> 0 | AA2: ='Mar26'!AA529 -> 0 | ... AR2: ='Mar26'!AR529 -> -368502.61 | AS2: =#REF! -> #REF! | AT2: =#REF! -> #REF! | AU2: =AS2-AT2 -> #REF!
A3: 46113 | B3: Credito Vendas Cartão | D3: 8574.06 | I3: =-D3 -> -8574.06 | AT3: Saidas | AU3: #REF!
B4: Desconto taxas Cartão | I4: =-I2-I3 -> -1430.59 | AT4: Saidas | AU4: #REF!
B5: Pix recebido maquininha | D5: =50+30+40+50+50+120+30+20+50.4+100+30+50+73 -> 693.4 | I5: =-D5 -> -693.4
B6: Tarifa pix recebido maquinha | D6: =-13*0.99 -> -12.87
AS7: =#REF! -> #REF!
B8: Venda de Gasolina | J8: =-M8 -> 6818.13 | K8: -1067 | L8: 6.39 | M8: =K8*L8 -> -6818.13 | AS8: =#REF! -> #REF!
B9: Venda de Etanol | J9: =-P9 -> 5814.38 | N9: -1391 | O9: 4.18 | P9: =N9*O9 -> -5814.38 | AS9: =#REF! -> #REF!
B10: Separação Cartão/Outros | H10: =-J10-I10 -> 4727.84 | I10: 7904.67 | J10: =-SUM(J8:J9) -> -12632.51 | AR10: =A2 -> 0 | AS10: =#REF! -> #REF!
B11: Ajuste estoque e valor diário (lucro embutido) | K11: -44 | M11: =(K14*M2/K2)-M2-M8 -> 1100.2658 | N11: -88 | P11: =(N14*((P2)/(N2))-P2-P9) -> 431.68625 | AS11: =#REF! -> #REF!
AR12: =A3 -> 46113 | AS12: =#REF! -> #REF!
B13: Saldo Giro no dia | C13: =D14+E14+F14+G14+H14+I14+J14+M14+P14 -> 117368.43 | M13: =K13*L13 -> 0 | P13: =N13*O13 -> 0 | S13: =Q13*R13 -> 0 | AR13: =SUM($T2:AQ13) -> -487087.83 | AV13: TERCEIROS
B14: Saldo Líquido do dia | C14: =AR14 -> -369719.4 | D14: =SUM(D2:D13) -> 21972.197 | E14: =SUM(E2:E13) -> -43287.79 | F14: =SUM(F2:F13) -> 0.65 | G14: =SUM(G2:G13) -> 0 | H14: =SUM(H2:H13) -> 69810.133 | I14: =SUM(I2:I13) -> 7211.27 | J14: =SUM(J2:J13) -> 0 | K14: =SUM(K2:K13) -> 11059 | L14: =M14/K14 -> 5.1465928 | M14: =ROUND(SUM(M2:M13),2) -> 56916.17 | N14: =SUM(N2:N13) -> 1304 | O14: =P14/N14 -> 3.6394172 | P14: =ROUND(SUM(P2:P13),2) -> 4745.8 | Q14: =SUM(Q2:Q13) -> 214 | R14: =S14/Q14 -> 6.099486 | S14: =ROUND(SUM(S2:S13),2) -> 1305.29 | T14: =SUM(T2:T13) -> -537317.13 | U14: =SUM(U2:U13) -> 50229.3 | V14: =SUM(V2:V13) -> 0 | W14: =SUM(W2:W13) -> 0 | X14: =SUM(X2:X13) -> 0 | Y14: =SUM(Y2:Y13) -> 0 | Z14: =SUM(Z2:Z13) -> 0 | AA14: =SUM(AA2:AA13) -> 0 | ... AK14: =SUM(AK2:AK13) -> 0 | AM14: =SUM(AM2:AM13) -> 0 | AN14: =SUM(AN2:AN13) -> 0 | AO14: =SUM(AO2:AO13) -> 0 | AP14: =SUM(AP2:AP13) -> 0 | AQ14: =SUM(AQ2:AQ13) -> 0 | AR14: =D14+E14+F14+G14+H14+I14+J14+M14+P14+SUM(T14:AQ14) -> -369719.4 | AV14: SALDO C/C
A15: =A3+1 -> 46114 | B15: Credito Vendas Cartão | D15: 7034.51 | I15: =-D15 -> -7034.51 | AS15: =#REF! -> #REF!
B16: Desconto taxas Cartão | I16: =-I14-I15 -> -176.76 | AS16: =#REF! -> #REF!
B17: Pix recebido maquininha | D17: =172+50+50+100+50+100+50+100+50+51.6+80+100 -> 953.6 | I17: =-D17 -> -953.6 | AS17: =#REF! -> #REF!
B18: Tarifa pix recebido maquinha | D18: =-11*0.99-1.38 -> -12.27 | AS18: =#REF! -> #REF!
B19: Transf. Lucila | D19: 28395 | F19: =-D19 -> -28395
B20: Pix e depósitos Banco Itaú | E20: =70+100+15+70+50+50+20+34+70+15+50+179+50+50+30+50+30+21+100+20+327+100+1130+1935+120+928+1168+752+1380+60 -> 8974 | H20: =-E20 -> -8974 | U20: =-D20 -> 0
B21: Pag Linx | E21: -184.86
B22: Tarifa pix enviado | D22: =-4.9-4.9 -> -9.8
AS23: =#REF! -> #REF!
B24: Venda de Gasolina | J24: =-M24 -> 8677.62 | K24: -1358 | L24: 6.39 | M24: =K24*L24 -> -8677.62 | AS24: =#REF! -> #REF!
B25: Venda de Etanol | J25: =-P25 -> 8669.32 | N25: -2074 | O25: 4.18 | P25: =N25*O25 -> -8669.32 | AS25: =#REF! -> #REF!
B26: Separação Cartão/Outros | H26: =-J26-I26 -> 6899.19 | I26: 10447.75 | J26: =-SUM(J24:J25) -> -17346.94 | AS26: =#REF! -> #REF!
B27: Ajuste estoque e valor diário (lucro embutido) | K27: -25 | M27: =(K30*(M14)/(K14))-M14-M24 -> 1559.8821 | N27: 226 | P27: =(N30*(P14)/(N14))-P14-P25 -> 1943.6771 | AS27: =#REF! -> #REF!
AR28: =A15 -> 46114 | AS28: =#REF! -> #REF!
B29: Saldo Giro no dia | C29: =D30+E30+F30+G30+H30+I30+J30+M30+P30 -> 120488.3 | AR29: =SUM($T14:AQ29) -> -487087.83 | AV29: TERCEIROS
B30: Saldo Líquido do dia | C30: =AR30 -> -366599.53 | D30: =SUM(D14:D29) -> 58333.237 | E30: =SUM(E14:E29) -> -34498.65 | F30: =SUM(F14:F29) -> -28394.35 | G30: =SUM(G14:G29) -> 0 | H30: =SUM(H14:H29) -> 67735.323 | I30: =SUM(I14:I29) -> 9494.15 | J30: =SUM(J14:J29) -> 0 | K30: =SUM(K14:K29) -> 9676 | L30: =M30/K30 -> 5.1465926 | M30: =ROUND(SUM(M14:M29),2) -> 49798.43 | N30: =SUM(N14:N29) -> -544 | O30: =P30/N30 -> 3.6394118 | P30: =ROUND(SUM(P14:P29),2) -> -1979.84 | Q30: =SUM(Q14:Q29) -> 214 | R30: =S30/Q30 -> 6.099486 | S30: =ROUND(SUM(S14:S29),2) -> 1305.29 | T30: =SUM(T14:T29) -> -537317.13 | U30: =SUM(U14:U29) -> 50229.3 | V30: =SUM(V14:V29) -> 0 | W30: =SUM(W14:W29) -> 0 | X30: =SUM(X14:X29) -> 0 | Y30: =SUM(Y14:Y29) -> 0 | Z30: =SUM(Z14:Z29) -> 0 | AA30: =SUM(AA14:AA29) -> 0 | ... AQ30: =SUM(AQ14:AQ29) -> 0 | AR30: =D30+E30+F30+G30+H30+I30+J30+M30+P30+SUM(T30:AQ30) -> -366599.53 | AV30: SALDO C/C
A31: =A15+1 -> 46115 | B31: Credito Vendas Cartão | D31: 9494.15 | I31: =-D31 -> -9494.15
B32: Desconto taxas Cartão | I32: =-I30-I31 -> 0
B33: Pix recebido maquininha | D33: =50+15+9+30+20+50+40+30+20+31+20+50+100+25+13.48 -> 503.48 | I33: =-D33 -> -503.48
B34: Tarifa pix recebido maquinha | D34: =-15*0.99 -> -14.85
B35: Transf. Eraldo | D35: -25300 | T35: =-D35 -> 25300
B36: Tarifa pix enviado | D36: -4.9
B37: Pix e depósitos Banco Itaú | E37: =125+100+70+60+50+80+70 -> 555 | H37: =-E37 -> -555 | U37: =-D37 -> 0
B38: Transf. Locaste | E38: -76
B39: IOF | E39: -268.84
B40: Transf. p/ Eraldo | E40: -24700 | T40: =-E40 -> 24700
B42: Venda de Gasolina | J42: =-M42 -> 5028.93 | K42: -787 | L42: 6.39 | M42: =K42*L42 -> -5028.93 | AS42: =#REF! -> #REF!
B43: Venda de Etanol | J43: =-P43 -> 6299.26 | N43: -1507 | O43: 4.18 | P43: =N43*O43 -> -6299.26 | AS43: =#REF! -> #REF!
B44: Separação Cartão/Outros | H44: =-J44-I44 -> 1207.63 | I44: 10120.56 | J44: =-SUM(J42:J43) -> -11328.19 | AR44: =A20 -> 0 | AS44: =#REF! -> #REF!
B45: Ajuste de saldo e valor estoque diário | K45: 10 | M45: =(K48*((M30)/(K30)))-M30-M42 -> 1030.0275 | N45: -103 | P45: =(N48*((P30)/(N30)))-P30-P43 -> 439.80706 | AR45: =A19 -> 0 | AS45: =#REF! -> #REF!
B47: Saldo Giro no dia | C47: =D48+E48+F48+G48+H48+I48+J48+M48+P48 -> 71593.55 | AR47: =SUM($T30:AQ47) -> -437087.83 | AV47: TERCEIROS
B48: Saldo Líquido do dia | C48: =AR48 -> -365494.28 | D48: =SUM(D30:D47) -> 43011.117 | E48: =SUM(E30:E47) -> -58988.49 | F48: =SUM(F30:F47) -> -28394.35 | G48: =SUM(G30:G47) -> 0 | H48: =SUM(H30:H47) -> 68387.953 | I48: =SUM(I30:I47) -> 9617.08 | J48: =SUM(J30:J47) -> 0 | K48: =SUM(K30:K47) -> 8899 | L48: =M48/K48 -> 5.1465929 | M48: =ROUND(SUM(M30:M47),2) -> 45799.53 | N48: =SUM(N30:N47) -> -2154 | O48: =P48/N48 -> 3.6394104 | P48: =ROUND(SUM(P30:P47),2) -> -7839.29 | Q48: =SUM(Q30:Q47) -> 214 | R48: =S48/Q48 -> 6.099486 | S48: =ROUND(SUM(S30:S47),2) -> 1305.29 | T48: =SUM(T30:T47) -> -487317.13 | U48: =SUM(U30:U47) -> 50229.3 | V48: =SUM(V30:V47) -> 0 | W48: =SUM(W30:W47) -> 0 | X48: =SUM(X30:X47) -> 0 | Y48: =SUM(Y30:Y47) -> 0 | Z48: =SUM(Z30:Z47) -> 0 | AA48: =SUM(AA30:AA47) -> 0 | ... AQ48: =SUM(AQ30:AQ47) -> 0 | AR48: =D48+E48+F48+G48+H48+I48+J48+M48+P48+SUM(T48:AQ48) -> -365494.28 | AV48: SALDO C/C
A49: =A31+1 -> 46116 | B49: Credito Vendas Cartão | D49: 9382.37 | I49: =-D49 -> -9382.37
B50: Desconto taxas Cartão | I50: =-I48-I49 -> -234.71
B51: Pix recebido maquininha | D51: =30+30+54+30+50+30+178.5+13.5+50+25+130.5+22+20 -> 663.5 | I51: =-D51 -> -663.5
B52: Tarifa pix recebido maquinha | D52: =-11*0.99-1.43-1.04 -> -13.36
B53: Pag boleto | D53: -291.95
B54: Pix e depósitos Banco Itaú | E54: =100+100+17.94+50+15+60+51+1085+1147+1268+1310 -> 5203.94 | H54: =-E54 -> -5203.94 | U54: =-D54 -> 0
B56: Venda de Gasolina | J56: =-M56 -> 6965.1 | K56: -1090 | L56: 6.39 | M56: =K56*L56 -> -6965.1 | AS56: =#REF! -> #REF!
B57: Venda de Etanol | J57: =-P57 -> 6357.78 | N57: -1521 | O57: 4.18 | P57: =N57*O57 -> -6357.78 | AS57: =#REF! -> #REF!
B58: Separação Cartão/Outros | H58: =-J58-I58 -> 3139.75 | I58: 10183.13 | J58: =-SUM(J56:J57) -> -13322.88 | AS58: =#REF! -> #REF!
B59: Ajuste de saldo e valor estoque diário | K59: 32 | M59: =(K62*((M48)/(K48)))-M48-M56 -> 1520.0047 | N59: -14 | P59: =(N62*((P48)/(N48)))-P48-P57 -> 771.28504 | AR59: =A30 -> 0 | AS59: =#REF! -> #REF!
AR60: =A49 -> 46116
B61: Saldo Giro no dia | C61: =D62+E62+F62+G62+H62+I62+J62+M62+P62 -> 73344.82 | AR61: =SUM($T48:AQ61) -> -437087.83 | AV61: TERCEIROS
B62: Saldo Líquido do dia | C62: =AR62 -> -363743.01 | D62: =SUM(D48:D61) -> 52751.677 | E62: =SUM(E48:E61) -> -53784.55 | F62: =SUM(F48:F61) -> -28394.35 | G62: =SUM(G48:G61) -> 0 | H62: =SUM(H48:H61) -> 66323.763 | I62: =SUM(I48:I61) -> 9519.63 | J62: =SUM(J48:J61) -> 0 | K62: =SUM(K48:K61) -> 7841 | L62: =M62/K62 -> 5.1465923 | M62: =ROUND(SUM(M48:M61),2) -> 40354.43 | N62: =SUM(N48:N61) -> -3689 | O62: =P62/N62 -> 3.6394091 | P62: =ROUND(SUM(P48:P61),2) -> -13425.78 | Q62: =SUM(Q48:Q61) -> 214 | R62: =S62/Q62 -> 6.099486 | S62: =ROUND(SUM(S48:S61),2) -> 1305.29 | T62: =SUM(T48:T61) -> -487317.13 | U62: =SUM(U48:U61) -> 50229.3 | V62: =SUM(V48:V61) -> 0 | W62: =SUM(W48:W61) -> 0 | X62: =SUM(X48:X61) -> 0 | Y62: =SUM(Y48:Y61) -> 0 | Z62: =SUM(Z48:Z61) -> 0 | AA62: =SUM(AA48:AA61) -> 0 | ... AQ62: =SUM(AQ48:AQ61) -> 0 | AR62: =D62+E62+F62+G62+H62+I62+J62+M62+P62+SUM(T62:AQ62) -> -363743.01 | AV62: SALDO C/C
A63: =A49+1 -> 46117 | B63: Credito Vendas Cartão | D63: 9295.4 | I63: =-D63 -> -9295.4
B64: Desconto taxas Cartão | I64: =-I62-I63 -> -224.23
B65: Pix recebido maquininha | D65: =150+15+15+25+20+100+50+30+50+197+40 -> 692 | I65: =-D65 -> -692
B66: Tarifa pix recebido maquinha | D66: =-9*0.99-1.2-1.58 -> -11.69
B67: Pix e depósitos Banco Itaú | E67: =100+30+15+20+55.29+2714.2+30+100+20+40+20+15+50+1677+1505+75 -> 6466.49 | H67: =-E67 -> -6466.49 | U67: =-D67 -> 0
B68: Crediario Emprestimo 6/6 parcelas 3.214,69 | E68: =-1141.12-5-50-700-20.7-20-20-50-100-170-30-50-50-25-50-732.87 -> -3214.69 | M68: =K68*L68 -> 0 | P68: =N68*O68 -> 0 | S68: =Q68*R68 -> 0 | W68: =-E68 -> 3214.69 | AT68: Saidas | AU68: #REF!
B69: Cesta básica (dinheiro) | H69: -791.28
B70: Vale refeição 5x767,00 | H70: -3835
B72: Venda de Gasolina | J72: =-M72 -> 5316.48 | K72: -832 | L72: 6.39 | M72: =K72*L72 -> -5316.48 | AS72: =#REF! -> #REF!
B73: Venda de Etanol | J73: =-P73 -> 4610.54 | N73: -1103 | O73: 4.18 | P73: =N73*O73 -> -4610.54 | AS73: =#REF! -> #REF!
B74: Separação Cartão/Outros | H74: =-J74-I74 -> -256.11 | I74: 10183.13 | J74: =-SUM(J72:J73) -> -9927.02 | AS74: =#REF! -> #REF!
B75: Ajuste de saldo e valor estoque diário | K75: -56 | M75: =(K78*((M62)/(K62)))-M62-M72 -> 746.30606 | N75: 23 | P75: =(N78*((P62)/(N62)))-P62-P73 -> 679.97822 | AR75: =A50 -> 0 | AS75: =#REF! -> #REF!
AR76: =A63 -> 46117
B77: Saldo Giro no dia | C77: =D78+E78+F78+G78+H78+I78+J78+M78+P78 -> 66694.22 | AR77: =SUM($T62:AQ77) -> -433873.14 | AV77: TERCEIROS
B78: Saldo Líquido do dia | C78: =AR78 -> -367178.92 | D78: =SUM(D62:D77) -> 62727.387 | E78: =SUM(E62:E77) -> -50532.75 | F78: =SUM(F62:F77) -> -28394.35 | G78: =SUM(G62:G77) -> 0 | H78: =SUM(H62:H77) -> 54974.883 | I78: =SUM(I62:I77) -> 9491.13 | J78: =SUM(J62:J77) -> 0 | K78: =SUM(K62:K77) -> 6953 | L78: =M78/K78 -> 5.1465928 | M78: =ROUND(SUM(M62:M77),2) -> 35784.26 | N78: =SUM(N62:N77) -> -4769 | O78: =P78/N78 -> 3.6394087 | P78: =ROUND(SUM(P62:P77),2) -> -17356.34 | Q78: =SUM(Q62:Q77) -> 214 | R78: =S78/Q78 -> 6.099486 | S78: =ROUND(SUM(S62:S77),2) -> 1305.29 | T78: =SUM(T62:T77) -> -487317.13 | U78: =SUM(U62:U77) -> 50229.3 | V78: =SUM(V62:V77) -> 0 | W78: =SUM(W62:W77) -> 3214.69 | X78: =SUM(X62:X77) -> 0 | Y78: =SUM(Y62:Y77) -> 0 | Z78: =SUM(Z62:Z77) -> 0 | AA78: =SUM(AA62:AA77) -> 0 | ... AQ78: =SUM(AQ62:AQ77) -> 0 | AR78: =D78+E78+F78+G78+H78+I78+J78+M78+P78+SUM(T78:AQ78) -> -367178.92 | AV78: SALDO C/C
A79: =A63+1 -> 46118 | B79: Credito Vendas Cartão | D79: 8916.35 | I79: =-D79 -> -8916.35
B80: Desconto taxas Cartão | I80: =-I78-I79 -> -574.78
B81: Pix recebido maquininha | D81: =30+100+81+50+30+15+5+50+20+102+30+30+40+20+50 -> 653 | I81: =-D81 -> -653
B82: Tarifa pix recebido maquinha | D82: =-15*0.99 -> -14.85
B83: Transf. p/ Eraldo | D83: -29100 | T83: =-D83 -> 29100
B84: Tarifa pix enviado | D84: -4.9
B85: Pix e depósitos Banco Itaú | E85: =20+20+100+80+8+30+50+60+1897+100+20+100+50+1126+1294.33 -> 4955.33 | H85: =-E85 -> -4955.33 | U85: =-D85 -> 0
B86: Transf. p/ Eraldo | E86: -16740 | T86: =-E86 -> 16740
B87: Pix Jose Ju | E87: -230
B88: Pag NF 513717 10x5,5966 GC RUFF | K88: 10000 | L88: 5.5966 | M88: =K88*L88 -> 55966 | T88: =-P88 -> 0
B89: Pag NF 130791 5x3,63 EH PETROWORLD | N89: 5000 | O89: 3.63 | P89: =N89*O89 -> 18150 | T89: =-P89 -> -18150
B91: Venda de Gasolina | J91: =-M91 -> 5738.22 | K91: -898 | L91: 6.39 | M91: =K91*L91 -> -5738.22 | AS91: =#REF! -> #REF!
B92: Venda de Etanol | J92: =-P92 -> 6391.22 | N92: -1529 | O92: 4.18 | P92: =N92*O92 -> -6391.22 | AS92: =#REF! -> #REF!
B93: Separação Cartão/Outros | H93: =-J93-I93 -> 1599.87 | I93: 10529.57 | J93: =-SUM(J91:J92) -> -12129.44 | AS93: =#REF! -> #REF!
B94: Ajuste de saldo e valor estoque diário | K94: 41 | M94: =(K97*((M78+M88)/(K78+K88)))-M78-M91-M88 -> 1100.1045 | N94: -65 | P94: =(N97*((P78+P89)/(N78+N89)))-P78-P92-P89 -> 914.62242 | AR94: =A67 -> 0 | AS94: =#REF! -> #REF!
AR95: =A79 -> 46118
B96: Saldo Giro no dia | C96: =D97+E97+F97+G97+H97+I97+J97+M97+P97 -> 96160.41 | AR96: =SUM($T78:AQ96) -> -406183.14 | AV96: TERCEIROS
